Workbook
Name Analysis_Period: 'Property Summary'!$C$8
Name Analysis_Start: 'Property Summary'!$C$7
Name Basis: 'Property Summary'!$F$6
Name Debt: 'Property Summary'!$F$18
Name Discount_Rate: 'Property Summary'!$C$12
Name Effective_Hold_Period: 'Property Summary'!$C$15
Name Equity_Share_LPs: 'Investor Returns'!$C$9
Name Equity_Share_Sponsor: 'Investor Returns'!$C$8
Name GP_Only_No_LPs: 'Investor Returns'!$E$8
Name Initial_Equity: 'Property Summary'!$F$23
Name Preferred_Return: 'Investor Returns'!$E$14
Name Promote_Method: 'Investor Returns'!$D$4
Name Property_Name: 'Property Summary'!$C$3
Name Purchase_Price: 'Property Summary'!$C$18
Name Terminal_Cap_Year: 'Property Summary'!$C$9
Name Total_Equity: 'Investor Returns'!$D$10
Name Units: 'Property Summary'!$F$3

Sheet Property Summary
B2: Property Summary
B3: Property Name | C3: XYZ Condos | E3: Number of Units | F3: 80 | H3: Capitalization | I3: % | J3: Amount
B4: City, State/Region | C4: Grand Cayman, CI | E4: Upfront CapEx | F4: 30000 | H4: GP/Sponsor | I4: =Equity_Share_Sponsor -> 0.1 | J4: ='Investor Returns'!D8 -> 1966879.2
B5: Current Occupancy | C5: 0.89 | E5: Acquisition Cost | F5: 0.01 | H5: LP Investors | I5: =1-I4 -> 0.9 | J5: ='Investor Returns'!D9 -> 17701913
B6: Purchase Price Method | C6: Cap Year 1 NOI | E6: All-in-Basis | F6: =((1+F5)*Purchase_Price)+(Debt*F30)+F4 -> 35928792 | H6: [See Investor Returns Tab To Configure]
B7: Analysis Start Date | C7: 43842 | E7: Going-In Cap Rate | F7: =$F$9/Purchase_Price -> 0.065
B8: Analysis Period (Years) | C8: 15 | E8: Price/Unit | F8: =Purchase_Price/Units -> 442278.36
B9: Terminal Cap Year | C9: =MIN(Analysis_Period+1,15) -> 15 | E9: Y1 NOI | F9: ='Property Returns'!$D$8 -> 2299847.5
B10: Terminal Cap Rate Growth/Yr | C10: 5 | E10: Y3 NOI | F10: ='Property Returns'!$F$8 -> 2407303.2
B11: Market Cap Rate (Y1) | C11: 0.065 | E11: ="Terminal Cap Rate (Yr "&Terminal_Cap_Year&")" -> Terminal Cap Rate (Yr 15) | F11: =$F$7+(Effective_Hold_Period*($C$10/10000)) -> 0.0725
B12: Discount Rate | C12: 0.05 | E12: Terminal Value | F12: =HLOOKUP(Effective_Hold_Period,'Property Returns'!$D$4:$R$42,10,FALSE) -> 37781965
B13: Replacement Cost (per unit) | C13: 210000
B14: Set Purchase Price | C14: 5000000 | E14: Other Income/Year | F14: 25000
B15: Effective Hold Period | C15: =MIN(Analysis_Period,Terminal_Cap_Year) -> 15 | E15: General Vacancy | F15: 0.13
B17: Property Metrics | E17: Financing Assumptions | H17: Inflation
B18: Purchase Price | C18: =IF($C$6="Manual Input", $C$14, IF($C$6="Present Value", $C$19, IF($C$6="Cap Year 1 NOI", $F$9/$C$11,$C$20))) -> 35382269 | E18: Loan Amount | F18: 16270000 | H18: Rent | I18: 0.015
B19: ="Present Value @ "&TEXT($C$12,"0.00%") -> Present Value @ 5.00% | C19: =NPV(Discount_Rate,'Property Returns'!$D$19:$R$19) -> 42321157 | E19: Value Basis for LTV | F19: Purchase Price | H19: Other Income | I19: 0.01
B20: ="Replacement Cost @ "&$C$13/1000&"k/unit" -> Replacement Cost @ 210k/unit | C20: =$C$13*Units -> 16800000 | E20: ="LTV ("&F19&")" -> LTV (Purchase Price) | F20: =IF($F$19="Purchase Price", Debt/Purchase_Price, IF($F$19="DCF Value", Debt/C19, Debt/F12)) -> 0.45983484 | H20: Operating Expenses | I20: 0.03
E21: LTC | F21: =Debt/Basis -> 0.45284017 | H21: Capital Expenditure | I21: 0.025
B22: Unlevered IRR | C22: =HLOOKUP(Effective_Hold_Period,'Property Returns'!$D$4:$S$42,18,FALSE) -> 0.066536708 | E22: Lender Fees ($) | F22: =Debt*$F$30 -> 162700 | H22: Releasing Costs | I22: 0.02
B23: Unlevered Equity Multiple (EM) | C23: =HLOOKUP(Effective_Hold_Period,'Property Returns'!$D$4:$S$42,19,FALSE) -> 2.0375574 | E23: Initial Equity Required | F23: =Basis-Debt -> 19658792
B24: Avg. Free and Clear Return | C24: =HLOOKUP(Effective_Hold_Period,'Property Returns'!$D$4:$S$42,15,FALSE) -> 0.065731889 | E24: Total Equity Required | F24: =Total_Equity -> 19668792
B26: Levered IRR | C26: =HLOOKUP(Effective_Hold_Period,'Property Returns'!$D$4:$S$42,36,FALSE) -> 0.90252903 | E26: Interest Rate | F26: 0.0725 | H26: Unit of Area | I26: SQFT
B27: Levered EM | C27: =HLOOKUP(Effective_Hold_Period,'Property Returns'!$D$4:$S$42,37,FALSE) -> 13.610558 | E27: Years I/O | F27: 0 | H27: Net Rentable Area (NRA) | I27: =SUMPRODUCT('Rent Roll'!C5:C10,'Rent Roll'!F5:F10) -> 62520
B28: Avg. Cash-on-Cash Return | C28: =HLOOKUP(Effective_Hold_Period,'Property Returns'!$D$4:$S$42,34,FALSE) -> 0.052382995 | E28: Amortization Period | F28: 30
E29: Term | F29: 10
B30: Min. DSCR (NOI) | C30: =MIN('Property Returns'!D28:R28) -> 1.7267665 | E30: Lender Fees (%) | F30: 0.01
B31: Min. Debt Yield (NOI) | C31: =MIN('Property Returns'!D29:R29) -> 0.12697548
B33: Investor Returns | C33: GP/Sponsor | E33: Limited Partner(s)
B34: IRR | C34: ='Investor Returns'!D43 -> 0.091151742 | E34: ='Investor Returns'!D29 -> 0.04584265
B35: Total Distributions | C35: ='Investor Returns'!D38 -> 5350982.4 | E35: ='Investor Returns'!D25 -> 29907409
B36: Total Contributions | C36: ='Investor Returns'!D40 -> 1966879.2 | E36: ='Investor Returns'!D26 -> 17701913
B37: Total Profit | C37: ='Investor Returns'!D41 -> 3704103.2 | E37: ='Investor Returns'!D27 -> 12205497
B38: Equity Multiple | C38: ='Investor Returns'!D44 -> 2.8928625 | E38: ='Investor Returns'!D30 -> 1.6895016

Sheet Rent Roll
B2: Property Unit Mix | G2: Total Units: | H2: =Units -> 80 | J2: Units Remaining: | K2: =H2-SUM(C5:C10) -> 0
P3: Blended
B4: Unit Type | C4: # of Units | D4: Beds | E4: Baths | F4: ="Rentable Area ("&'Property Summary'!$I$26&")" -> Rentable Area (SQFT) | G4: In-Place Rent/Mo. | H4: Market Rent/Mo. | I4: Month to Roll to Market | J4: Lease Term | K4: CapEx/Unit/Mo. | L4: Free Rent per Lease | M4: Days Vacant Between Leases | N4: Releasing Cost per Unit | O4: Probability of Renewal | P4: Free Rent | Q4: Days Vacant | R4: Releasing Cost
B5: Studio | C5: 22 | D5: 0 | E5: 1 | F5: 470 | G5: 2200 | H5: 2350 | I5: 13 | J5: 12 | K5: 70 | L5: 0 | M5: 25 | N5: 400 | O5: 0.6 | P5: =IF($B5<>"", (1-$O5)*$L5, "") -> 0 | Q5: =IF($B5<>"", (1-$O5)*$M5, "") -> 10 | R5: =IF($B5<>"", (1-$O5)*$N5, "") -> 160
B6: 1bd/1ba | C6: 24 | D6: 1 | E6: 1 | F6: 630 | G6: 2340 | H6: 2500 | I6: 16 | J6: 12 | K6: 75 | L6: 0 | M6: 25 | N6: 400 | O6: 0.6 | P6: =IF($B6<>"", (1-$O6)*$L6, "") -> 0 | Q6: =IF($B6<>"", (1-$O6)*$M6, "") -> 10 | R6: =IF($B6<>"", (1-$O6)*$N6, "") -> 160
B7: 2bd/2ba | C7: 20 | D7: 2 | E7: 2 | F7: 955 | G7: 4800 | H7: 4950 | I7: 19 | J7: 12 | K7: 120 | L7: 0 | M7: 28 | N7: 550 | O7: 0.6 | P7: =IF($B7<>"", (1-$O7)*$L7, "") -> 0 | Q7: =IF($B7<>"", (1-$O7)*$M7, "") -> 11.2 | R7: =IF($B7<>"", (1-$O7)*$N7, "") -> 220
B8: 3bd/3ba | C8: 8 | D8: 3 | E8: 3 | F8: 1120 | G8: 5400 | H8: 5500 | I8: 14 | J8: 12 | K8: 160 | L8: 0 | M8: 32 | N8: 600 | O8: 0.6 | P8: =IF($B8<>"", (1-$O8)*$L8, "") -> 0 | Q8: =IF($B8<>"", (1-$O8)*$M8, "") -> 12.8 | R8: =IF($B8<>"", (1-$O8)*$N8, "") -> 240
B9: 4bd/4ba | C9: 6 | D9: 4 | E9: 4 | F9: 1500 | G9: 5900 | H9: 6150 | I9: 20 | J9: 12 | K9: 180 | L9: 0 | M9: 38 | N9: 800 | O9: 0.6 | P9: =IF($B9<>"", (1-$O9)*$L9, "") -> 0 | Q9: =IF($B9<>"", (1-$O9)*$M9, "") -> 15.2 | R9: =IF($B9<>"", (1-$O9)*$N9, "") -> 320
P10: =IF($B10<>"", (1-$O10)*$L10, "") | Q10: =IF($B10<>"", (1-$O10)*$M10, "") | R10: =IF($B10<>"", (1-$O10)*$N10, "")

Sheet Expenses
B2: Operating Expenses Assumptions
B5: Growth Rate | D5: Year 1 Per Unit | E5: ='Property Returns'!D4 -> 1 | F5: ='Property Returns'!E4 -> 2 | G5: ='Property Returns'!F4 -> 3 | H5: ='Property Returns'!G4 -> 4 | I5: ='Property Returns'!H4 -> 5 | J5: ='Property Returns'!I4 -> 6 | K5: ='Property Returns'!J4 -> 7 | L5: ='Property Returns'!K4 -> 8 | ... S5: ='Property Returns'!R4 -> 15
B6: ='Property Summary'!$I$20 -> 0.03 | C6: -Marketing | D6: =E6/Units -> -300 | E6: -24000 | F6: =IF(OR(F$5="",F$5=0),"",-ABS((E6*(1+$B6)))) -> -24720 | G6: =IF(OR(G$5="",G$5=0),"",-ABS((F6*(1+$B6)))) -> -25461.6 | H6: =IF(OR(H$5="",H$5=0),"",-ABS((G6*(1+$B6)))) -> -26225.448 | I6: =IF(OR(I$5="",I$5=0),"",-ABS((H6*(1+$B6)))) -> -27012.211 | J6: =IF(OR(J$5="",J$5=0),"",-ABS((I6*(1+$B6)))) -> -27822.578 | K6: =IF(OR(K$5="",K$5=0),"",-ABS((J6*(1+$B6)))) -> -28657.255 | L6: =IF(OR(L$5="",L$5=0),"",-ABS((K6*(1+$B6)))) -> -29516.973 | M6: =IF(OR(M$5="",M$5=0),"",-ABS((L6*(1+$B6)))) -> -30402.482 | ... S6: =IF(OR(S$5="",S$5=0),"",-ABS((R6*(1+$B6)))) -> -36302.153
B7: ='Property Summary'!$I$20 -> 0.03 | C7: -Administrative | D7: =E7/Units -> -412.5 | E7: -33000 | F7: =IF(OR(F$5="",F$5=0),"",-ABS((E7*(1+$B7)))) -> -33990 | G7: =IF(OR(G$5="",G$5=0),"",-ABS((F7*(1+$B7)))) -> -35009.7 | H7: =IF(OR(H$5="",H$5=0),"",-ABS((G7*(1+$B7)))) -> -36059.991 | I7: =IF(OR(I$5="",I$5=0),"",-ABS((H7*(1+$B7)))) -> -37141.791 | J7: =IF(OR(J$5="",J$5=0),"",-ABS((I7*(1+$B7)))) -> -38256.044 | K7: =IF(OR(K$5="",K$5=0),"",-ABS((J7*(1+$B7)))) -> -39403.726 | L7: =IF(OR(L$5="",L$5=0),"",-ABS((K7*(1+$B7)))) -> -40585.838 | M7: =IF(OR(M$5="",M$5=0),"",-ABS((L7*(1+$B7)))) -> -41803.413 | ... S7: =IF(OR(S$5="",S$5=0),"",-ABS((R7*(1+$B7)))) -> -49915.461
B8: ='Property Summary'!$I$20 -> 0.03 | C8: -Utilities | D8: =E8/Units -> -1237.5 | E8: -99000 | F8: =IF(OR(F$5="",F$5=0),"",-ABS((E8*(1+$B8)))) -> -101970 | G8: =IF(OR(G$5="",G$5=0),"",-ABS((F8*(1+$B8)))) -> -105029.1 | H8: =IF(OR(H$5="",H$5=0),"",-ABS((G8*(1+$B8)))) -> -108179.97 | I8: =IF(OR(I$5="",I$5=0),"",-ABS((H8*(1+$B8)))) -> -111425.37 | J8: =IF(OR(J$5="",J$5=0),"",-ABS((I8*(1+$B8)))) -> -114768.13 | K8: =IF(OR(K$5="",K$5=0),"",-ABS((J8*(1+$B8)))) -> -118211.18 | L8: =IF(OR(L$5="",L$5=0),"",-ABS((K8*(1+$B8)))) -> -121757.51 | M8: =IF(OR(M$5="",M$5=0),"",-ABS((L8*(1+$B8)))) -> -125410.24 | ... S8: =IF(OR(S$5="",S$5=0),"",-ABS((R8*(1+$B8)))) -> -149746.38
B9: ='Property Summary'!$I$20 -> 0.03 | C9: -Payroll | D9: =E9/Units -> -1900 | E9: -152000 | F9: =IF(OR(F$5="",F$5=0),"",-ABS((E9*(1+$B9)))) -> -156560 | G9: =IF(OR(G$5="",G$5=0),"",-ABS((F9*(1+$B9)))) -> -161256.8 | H9: =IF(OR(H$5="",H$5=0),"",-ABS((G9*(1+$B9)))) -> -166094.5 | I9: =IF(OR(I$5="",I$5=0),"",-ABS((H9*(1+$B9)))) -> -171077.34 | J9: =IF(OR(J$5="",J$5=0),"",-ABS((I9*(1+$B9)))) -> -176209.66 | K9: =IF(OR(K$5="",K$5=0),"",-ABS((J9*(1+$B9)))) -> -181495.95 | L9: =IF(OR(L$5="",L$5=0),"",-ABS((K9*(1+$B9)))) -> -186940.83 | M9: =IF(OR(M$5="",M$5=0),"",-ABS((L9*(1+$B9)))) -> -192549.05 | ... S9: =IF(OR(S$5="",S$5=0),"",-ABS((R9*(1+$B9)))) -> -229913.64
B10: ='Property Summary'!$I$20 -> 0.03 | C10: -Repair and Maintenance | D10: =E10/Units -> -1055 | E10: -84400 | F10: =IF(OR(F$5="",F$5=0),"",-ABS((E10*(1+$B10)))) -> -86932 | G10: =IF(OR(G$5="",G$5=0),"",-ABS((F10*(1+$B10)))) -> -89539.96 | H10: =IF(OR(H$5="",H$5=0),"",-ABS((G10*(1+$B10)))) -> -92226.159 | I10: =IF(OR(I$5="",I$5=0),"",-ABS((H10*(1+$B10)))) -> -94992.944 | J10: =IF(OR(J$5="",J$5=0),"",-ABS((I10*(1+$B10)))) -> -97842.732 | K10: =IF(OR(K$5="",K$5=0),"",-ABS((J10*(1+$B10)))) -> -100778.01 | L10: =IF(OR(L$5="",L$5=0),"",-ABS((K10*(1+$B10)))) -> -103801.35 | M10: =IF(OR(M$5="",M$5=0),"",-ABS((L10*(1+$B10)))) -> -106915.39 | ... S10: =IF(OR(S$5="",S$5=0),"",-ABS((R10*(1+$B10)))) -> -127662.57
B11: 0.03 | C11: -Management (as % of EGR) | D11: =E11/Units -> -1102.2864 | E11: =IF(OR(E$5="",E$5=0),"",(-$B11*'Annual Cash Flow'!E11)) -> -88182.912 | F11: =IF(OR(F$5="",F$5=0),"",-ABS((E11*(1+$B11)))) -> -90828.399 | G11: =IF(OR(G$5="",G$5=0),"",-ABS((F11*(1+$B11)))) -> -93553.251 | H11: =IF(OR(H$5="",H$5=0),"",-ABS((G11*(1+$B11)))) -> -96359.849 | I11: =IF(OR(I$5="",I$5=0),"",-ABS((H11*(1+$B11)))) -> -99250.644 | J11: =IF(OR(J$5="",J$5=0),"",-ABS((I11*(1+$B11)))) -> -102228.16 | K11: =IF(OR(K$5="",K$5=0),"",-ABS((J11*(1+$B11)))) -> -105295.01 | L11: =IF(OR(L$5="",L$5=0),"",-ABS((K11*(1+$B11)))) -> -108453.86 | M11: =IF(OR(M$5="",M$5=0),"",-ABS((L11*(1+$B11)))) -> -111707.47 | ... S11: =IF(OR(S$5="",S$5=0),"",-ABS((R11*(1+$B11)))) -> -133384.57
B12: ='Property Summary'!$I$20 -> 0.03 | C12: -Insurance | D12: =E12/Units -> -487.5 | E12: -39000 | F12: =IF(OR(F$5="",F$5=0),"",-ABS((E12*(1+$B12)))) -> -40170 | G12: =IF(OR(G$5="",G$5=0),"",-ABS((F12*(1+$B12)))) -> -41375.1 | H12: =IF(OR(H$5="",H$5=0),"",-ABS((G12*(1+$B12)))) -> -42616.353 | I12: =IF(OR(I$5="",I$5=0),"",-ABS((H12*(1+$B12)))) -> -43894.844 | J12: =IF(OR(J$5="",J$5=0),"",-ABS((I12*(1+$B12)))) -> -45211.689 | K12: =IF(OR(K$5="",K$5=0),"",-ABS((J12*(1+$B12)))) -> -46568.04 | L12: =IF(OR(L$5="",L$5=0),"",-ABS((K12*(1+$B12)))) -> -47965.081 | M12: =IF(OR(M$5="",M$5=0),"",-ABS((L12*(1+$B12)))) -> -49404.033 | ... S12: =IF(OR(S$5="",S$5=0),"",-ABS((R12*(1+$B12)))) -> -58990.999
B13: ='Property Summary'!$I$20 -> 0.03 | C13: -Taxes | D13: =E13/Units -> -1500 | E13: -120000 | F13: =IF(OR(F$5="",F$5=0),"",-ABS((E13*(1+$B13)))) -> -123600 | G13: =IF(OR(G$5="",G$5=0),"",-ABS((F13*(1+$B13)))) -> -127308 | H13: =IF(OR(H$5="",H$5=0),"",-ABS((G13*(1+$B13)))) -> -131127.24 | I13: =IF(OR(I$5="",I$5=0),"",-ABS((H13*(1+$B13)))) -> -135061.06 | J13: =IF(OR(J$5="",J$5=0),"",-ABS((I13*(1+$B13)))) -> -139112.89 | K13: =IF(OR(K$5="",K$5=0),"",-ABS((J13*(1+$B13)))) -> -143286.28 | L13: =IF(OR(L$5="",L$5=0),"",-ABS((K13*(1+$B13)))) -> -147584.86 | M13: =IF(OR(M$5="",M$5=0),"",-ABS((L13*(1+$B13)))) -> -152012.41 | ... S13: =IF(OR(S$5="",S$5=0),"",-ABS((R13*(1+$B13)))) -> -181510.77
B14: ='Property Summary'!$I$20 -> 0.03 | C14: Operating Expenses | D14: =E14/Units -> -7994.7864 | E14: {=IF(OR(E5="",E5=0),"",-SUM(ABS(E6:E13)))} -> -639582.91 | F14: =IF(OR(F$5="",F$5=0),"",-ABS((E14*(1+$B14)))) -> -658770.4 | G14: =IF(OR(G$5="",G$5=0),"",-ABS((F14*(1+$B14)))) -> -678533.51 | H14: =IF(OR(H$5="",H$5=0),"",-ABS((G14*(1+$B14)))) -> -698889.52 | I14: =IF(OR(I$5="",I$5=0),"",-ABS((H14*(1+$B14)))) -> -719856.2 | J14: =IF(OR(J$5="",J$5=0),"",-ABS((I14*(1+$B14)))) -> -741451.89 | K14: =IF(OR(K$5="",K$5=0),"",-ABS((J14*(1+$B14)))) -> -763695.44 | L14: =IF(OR(L$5="",L$5=0),"",-ABS((K14*(1+$B14)))) -> -786606.31 | M14: =IF(OR(M$5="",M$5=0),"",-ABS((L14*(1+$B14)))) -> -810204.5 | ... S14: =IF(OR(S$5="",S$5=0),"",-ABS((R14*(1+$B14)))) -> -967426.54
D18: Year | E18: =E5 -> 1 | F18: =F5 -> 2 | G18: =G5 -> 3 | H18: =H5 -> 4 | I18: =I5 -> 5 | J18: =J5 -> 6 | K18: =K5 -> 7 | L18: =L5 -> 8 | ... S18: =S5 -> 15
B19: Property Renovation/Improvement Costs | E19: 350000 | F19: 200000 | G19: 0 | H19: 0 | I19: 0 | J19: 0 | K19: 0 | L19: 0 | M19: 0 | N19: 0 | O19: 0 | P19: 0 | Q19: 0 | R19: 0 | S19: 0
B20: Total | E20: =IF(OR(E18="",E18=0),"",-ABS(E19)) -> -350000 | F20: =IF(OR(F18="",F18=0),"",-ABS(F19)) -> -200000 | G20: =IF(OR(G18="",G18=0),"",-ABS(G19)) -> 0 | H20: =IF(OR(H18="",H18=0),"",-ABS(H19)) -> 0 | I20: =IF(OR(I18="",I18=0),"",-ABS(I19)) -> 0 | J20: =IF(OR(J18="",J18=0),"",-ABS(J19)) -> 0 | K20: =IF(OR(K18="",K18=0),"",-ABS(K19)) -> 0 | L20: =IF(OR(L18="",L18=0),"",-ABS(L19)) -> 0 | ... S20: =IF(OR(S18="",S18=0),"",-ABS(S19)) -> 0

Sheet Annual Cash Flow
B2: Annual Cash Flow
D4: Ratios | E4: ='Property Returns'!D4 -> 1 | F4: ='Property Returns'!E4 -> 2 | G4: ='Property Returns'!F4 -> 3 | H4: ='Property Returns'!G4 -> 4 | I4: ='Property Returns'!H4 -> 5 | J4: ='Property Returns'!I4 -> 6 | K4: ='Property Returns'!J4 -> 7 | L4: ='Property Returns'!K4 -> 8 | ... S4: ='Property Returns'!R4 -> 15
B5: + Base Rent | E5: =IF(OR(E$4="",E$4=0),"",SUMIF(Calculations!C$13:FZ$13,E4,Calculations!C$22:FZ$22)) -> 3349920 | F5: =IF(OR(F$4="",F$4=0),"",SUMIF(Calculations!D$13:GA$13,F4,Calculations!D$22:GA$22)) -> 3510255.7 | G5: =IF(OR(G$4="",G$4=0),"",SUMIF(Calculations!E$13:GB$13,G4,Calculations!E$22:GB$22)) -> 3604963.3 | H5: =IF(OR(H$4="",H$4=0),"",SUMIF(Calculations!F$13:GC$13,H4,Calculations!F$22:GC$22)) -> 3659037.8 | I5: =IF(OR(I$4="",I$4=0),"",SUMIF(Calculations!G$13:GD$13,I4,Calculations!G$22:GD$22)) -> 3713923.3 | J5: =IF(OR(J$4="",J$4=0),"",SUMIF(Calculations!H$13:GE$13,J4,Calculations!H$22:GE$22)) -> 3769632.2 | K5: =IF(OR(K$4="",K$4=0),"",SUMIF(Calculations!I$13:GF$13,K4,Calculations!I$22:GF$22)) -> 3826176.7 | L5: =IF(OR(L$4="",L$4=0),"",SUMIF(Calculations!J$13:GG$13,L4,Calculations!J$22:GG$22)) -> 3883569.3 | ... S5: =IF(OR(S$4="",S$4=0),"",SUMIF(Calculations!Q$13:GN$13,S4,Calculations!Q$22:GN$22)) -> 4310159.7
B6: + Other Income | D6: =AVERAGE(E6:P6)/AVERAGE(E7:P7) -> 0.0069287912 | E6: =IF(OR(E$4="",E$4=0),"",'Property Summary'!$F$14*(1+'Property Summary'!$I$19)^(E4-1)) -> 25000 | F6: =IF(OR(F$4="",F$4=0),"",'Property Summary'!$F$14*(1+'Property Summary'!$I$19)^(F4-1)) -> 25250 | G6: =IF(OR(G$4="",G$4=0),"",'Property Summary'!$F$14*(1+'Property Summary'!$I$19)^(G4-1)) -> 25502.5 | H6: =IF(OR(H$4="",H$4=0),"",'Property Summary'!$F$14*(1+'Property Summary'!$I$19)^(H4-1)) -> 25757.525 | I6: =IF(OR(I$4="",I$4=0),"",'Property Summary'!$F$14*(1+'Property Summary'!$I$19)^(I4-1)) -> 26015.1 | J6: =IF(OR(J$4="",J$4=0),"",'Property Summary'!$F$14*(1+'Property Summary'!$I$19)^(J4-1)) -> 26275.251 | K6: =IF(OR(K$4="",K$4=0),"",'Property Summary'!$F$14*(1+'Property Summary'!$I$19)^(K4-1)) -> 26538.004 | L6: =IF(OR(L$4="",L$4=0),"",'Property Summary'!$F$14*(1+'Property Summary'!$I$19)^(L4-1)) -> 26803.384 | ... S6: =IF(OR(S$4="",S$4=0),"",'Property Summary'!$F$14*(1+'Property Summary'!$I$19)^(S4-1)) -> 28736.855
B7: Gross Potential Income | E7: =IF(OR(E$4="",E$4=0),"",SUM(E5:E6)) -> 3374920 | F7: =IF(OR(F$4="",F$4=0),"",SUM(F5:F6)) -> 3535505.7 | G7: =IF(OR(G$4="",G$4=0),"",SUM(G5:G6)) -> 3630465.8 | H7: =IF(OR(H$4="",H$4=0),"",SUM(H5:H6)) -> 3684795.3 | I7: =IF(OR(I$4="",I$4=0),"",SUM(I5:I6)) -> 3739938.4 | J7: =IF(OR(J$4="",J$4=0),"",SUM(J5:J6)) -> 3795907.4 | K7: =IF(OR(K$4="",K$4=0),"",SUM(K5:K6)) -> 3852714.7 | L7: =IF(OR(L$4="",L$4=0),"",SUM(L5:L6)) -> 3910372.7 | ... S7: =IF(OR(S$4="",S$4=0),"",SUM(S5:S6)) -> 4338896.5
B9: - Rent Abatement | D9: =AVERAGE(E9:P9)/AVERAGE($E$7:$P$7) -> 0 | E9: =IF(OR(E$4="",E$4=0),"",-SUMIF(Calculations!$C$49:$FZ$49,E$4,Calculations!$C$58:$FZ$58)) -> 0 | F9: =IF(OR(F$4="",F$4=0),"",-SUMIF(Calculations!$C$49:$FZ$49,F$4,Calculations!$C$58:$FZ$58)) -> 0 | G9: =IF(OR(G$4="",G$4=0),"",-SUMIF(Calculations!$C$49:$FZ$49,G$4,Calculations!$C$58:$FZ$58)) -> 0 | H9: =IF(OR(H$4="",H$4=0),"",-SUMIF(Calculations!$C$49:$FZ$49,H$4,Calculations!$C$58:$FZ$58)) -> 0 | I9: =IF(OR(I$4="",I$4=0),"",-SUMIF(Calculations!$C$49:$FZ$49,I$4,Calculations!$C$58:$FZ$58)) -> 0 | J9: =IF(OR(J$4="",J$4=0),"",-SUMIF(Calculations!$C$49:$FZ$49,J$4,Calculations!$C$58:$FZ$58)) -> 0 | K9: =IF(OR(K$4="",K$4=0),"",-SUMIF(Calculations!$C$49:$FZ$49,K$4,Calculations!$C$58:$FZ$58)) -> 0 | L9: =IF(OR(L$4="",L$4=0),"",-SUMIF(Calculations!$C$49:$FZ$49,L$4,Calculations!$C$58:$FZ$58)) -> 0 | ... S9: =IF(OR(S$4="",S$4=0),"",-SUMIF(Calculations!$C$49:$FZ$49,S$4,Calculations!$C$58:$FZ$58)) -> 0
B10: - Vacancy | D10: =-AVERAGE(E10:P10)/AVERAGE($E$7:$P$7) -> 0.14845557 | E10: =IF(OR(E$4="",E$4=0),"",-SUMIF(Calculations!$C$61:$FZ$61,E$4,Calculations!$C$70:$FZ$70)) -> -435489.6 | F10: =IF(OR(F$4="",F$4=0),"",-SUMIF(Calculations!$C$61:$FZ$61,F$4,Calculations!$C$70:$FZ$70)) -> -528846.4 | G10: =IF(OR(G$4="",G$4=0),"",-SUMIF(Calculations!$C$61:$FZ$61,G$4,Calculations!$C$70:$FZ$70)) -> -544629.13 | H10: =IF(OR(H$4="",H$4=0),"",-SUMIF(Calculations!$C$61:$FZ$61,H$4,Calculations!$C$70:$FZ$70)) -> -552798.57 | I10: =IF(OR(I$4="",I$4=0),"",-SUMIF(Calculations!$C$61:$FZ$61,I$4,Calculations!$C$70:$FZ$70)) -> -561090.55 | J10: =IF(OR(J$4="",J$4=0),"",-SUMIF(Calculations!$C$61:$FZ$61,J$4,Calculations!$C$70:$FZ$70)) -> -569506.91 | K10: =IF(OR(K$4="",K$4=0),"",-SUMIF(Calculations!$C$61:$FZ$61,K$4,Calculations!$C$70:$FZ$70)) -> -578049.51 | L10: =IF(OR(L$4="",L$4=0),"",-SUMIF(Calculations!$C$61:$FZ$61,L$4,Calculations!$C$70:$FZ$70)) -> -586720.25 | ... S10: =IF(OR(S$4="",S$4=0),"",-SUMIF(Calculations!$C$61:$FZ$61,S$4,Calculations!$C$70:$FZ$70)) -> -651168.49
B11: Effective Gross Revenue | D11: =AVERAGE(E11:P11)/AVERAGE($E$7:$P$7) -> 0.85154443 | E11: =IF(OR(E$4="",E$4=0),"",SUM(E7:E10)) -> 2939430.4 | F11: =IF(OR(F$4="",F$4=0),"",SUM(F7:F10)) -> 3006659.3 | G11: =IF(OR(G$4="",G$4=0),"",SUM(G7:G10)) -> 3085836.7 | H11: =IF(OR(H$4="",H$4=0),"",SUM(H7:H10)) -> 3131996.7 | I11: =IF(OR(I$4="",I$4=0),"",SUM(I7:I10)) -> 3178847.9 | J11: =IF(OR(J$4="",J$4=0),"",SUM(J7:J10)) -> 3226400.5 | K11: =IF(OR(K$4="",K$4=0),"",SUM(K7:K10)) -> 3274665.2 | L11: =IF(OR(L$4="",L$4=0),"",SUM(L7:L10)) -> 3323652.4 | ... S11: =IF(OR(S$4="",S$4=0),"",SUM(S7:S10)) -> 3687728
B13: - Marketing | E13: =IF(OR(E$4="",E$4=0),"",-ABS(Expenses!E6)) -> -24000 | F13: =IF(OR(F$4="",F$4=0),"",-ABS(Expenses!F6)) -> -24720 | G13: =IF(OR(G$4="",G$4=0),"",-ABS(Expenses!G6)) -> -25461.6 | H13: =IF(OR(H$4="",H$4=0),"",-ABS(Expenses!H6)) -> -26225.448 | I13: =IF(OR(I$4="",I$4=0),"",-ABS(Expenses!I6)) -> -27012.211 | J13: =IF(OR(J$4="",J$4=0),"",-ABS(Expenses!J6)) -> -27822.578 | K13: =IF(OR(K$4="",K$4=0),"",-ABS(Expenses!K6)) -> -28657.255 | L13: =IF(OR(L$4="",L$4=0),"",-ABS(Expenses!L6)) -> -29516.973 | ... S13: =IF(OR(S$4="",S$4=0),"",-ABS(Expenses!S6)) -> -36302.153
B14: - Administrative | E14: =IF(OR(E$4="",E$4=0),"",-ABS(Expenses!E7)) -> -33000 | F14: =IF(OR(F$4="",F$4=0),"",-ABS(Expenses!F7)) -> -33990 | G14: =IF(OR(G$4="",G$4=0),"",-ABS(Expenses!G7)) -> -35009.7 | H14: =IF(OR(H$4="",H$4=0),"",-ABS(Expenses!H7)) -> -36059.991 | I14: =IF(OR(I$4="",I$4=0),"",-ABS(Expenses!I7)) -> -37141.791 | J14: =IF(OR(J$4="",J$4=0),"",-ABS(Expenses!J7)) -> -38256.044 | K14: =IF(OR(K$4="",K$4=0),"",-ABS(Expenses!K7)) -> -39403.726 | L14: =IF(OR(L$4="",L$4=0),"",-ABS(Expenses!L7)) -> -40585.838 | ... S14: =IF(OR(S$4="",S$4=0),"",-ABS(Expenses!S7)) -> -49915.461
B15: - Utilities | E15: =IF(OR(E$4="",E$4=0),"",-ABS(Expenses!E8)) -> -99000 | F15: =IF(OR(F$4="",F$4=0),"",-ABS(Expenses!F8)) -> -101970 | G15: =IF(OR(G$4="",G$4=0),"",-ABS(Expenses!G8)) -> -105029.1 | H15: =IF(OR(H$4="",H$4=0),"",-ABS(Expenses!H8)) -> -108179.97 | I15: =IF(OR(I$4="",I$4=0),"",-ABS(Expenses!I8)) -> -111425.37 | J15: =IF(OR(J$4="",J$4=0),"",-ABS(Expenses!J8)) -> -114768.13 | K15: =IF(OR(K$4="",K$4=0),"",-ABS(Expenses!K8)) -> -118211.18 | L15: =IF(OR(L$4="",L$4=0),"",-ABS(Expenses!L8)) -> -121757.51 | ... S15: =IF(OR(S$4="",S$4=0),"",-ABS(Expenses!S8)) -> -149746.38
B16: - Payroll | E16: =IF(OR(E$4="",E$4=0),"",-ABS(Expenses!E9)) -> -152000 | F16: =IF(OR(F$4="",F$4=0),"",-ABS(Expenses!F9)) -> -156560 | G16: =IF(OR(G$4="",G$4=0),"",-ABS(Expenses!G9)) -> -161256.8 | H16: =IF(OR(H$4="",H$4=0),"",-ABS(Expenses!H9)) -> -166094.5 | I16: =IF(OR(I$4="",I$4=0),"",-ABS(Expenses!I9)) -> -171077.34 | J16: =IF(OR(J$4="",J$4=0),"",-ABS(Expenses!J9)) -> -176209.66 | K16: =IF(OR(K$4="",K$4=0),"",-ABS(Expenses!K9)) -> -181495.95 | L16: =IF(OR(L$4="",L$4=0),"",-ABS(Expenses!L9)) -> -186940.83 | ... S16: =IF(OR(S$4="",S$4=0),"",-ABS(Expenses!S9)) -> -229913.64
B17: - Repair and maintenance | E17: =IF(OR(E$4="",E$4=0),"",-ABS(Expenses!E10)) -> -84400 | F17: =IF(OR(F$4="",F$4=0),"",-ABS(Expenses!F10)) -> -86932 | G17: =IF(OR(G$4="",G$4=0),"",-ABS(Expenses!G10)) -> -89539.96 | H17: =IF(OR(H$4="",H$4=0),"",-ABS(Expenses!H10)) -> -92226.159 | I17: =IF(OR(I$4="",I$4=0),"",-ABS(Expenses!I10)) -> -94992.944 | J17: =IF(OR(J$4="",J$4=0),"",-ABS(Expenses!J10)) -> -97842.732 | K17: =IF(OR(K$4="",K$4=0),"",-ABS(Expenses!K10)) -> -100778.01 | L17: =IF(OR(L$4="",L$4=0),"",-ABS(Expenses!L10)) -> -103801.35 | ... S17: =IF(OR(S$4="",S$4=0),"",-ABS(Expenses!S10)) -> -127662.57
B18: - Management (as % of EGR) | E18: =IF(OR(E$4="",E$4=0),"",-ABS(Expenses!E11)) -> -88182.912 | F18: =IF(OR(F$4="",F$4=0),"",-ABS(Expenses!F11)) -> -90828.399 | G18: =IF(OR(G$4="",G$4=0),"",-ABS(Expenses!G11)) -> -93553.251 | H18: =IF(OR(H$4="",H$4=0),"",-ABS(Expenses!H11)) -> -96359.849 | I18: =IF(OR(I$4="",I$4=0),"",-ABS(Expenses!I11)) -> -99250.644 | J18: =IF(OR(J$4="",J$4=0),"",-ABS(Expenses!J11)) -> -102228.16 | K18: =IF(OR(K$4="",K$4=0),"",-ABS(Expenses!K11)) -> -105295.01 | L18: =IF(OR(L$4="",L$4=0),"",-ABS(Expenses!L11)) -> -108453.86 | ... S18: =IF(OR(S$4="",S$4=0),"",-ABS(Expenses!S11)) -> -133384.57
B19: - Insurance | E19: =IF(OR(E$4="",E$4=0),"",-ABS(Expenses!E12)) -> -39000 | F19: =IF(OR(F$4="",F$4=0),"",-ABS(Expenses!F12)) -> -40170 | G19: =IF(OR(G$4="",G$4=0),"",-ABS(Expenses!G12)) -> -41375.1 | H19: =IF(OR(H$4="",H$4=0),"",-ABS(Expenses!H12)) -> -42616.353 | I19: =IF(OR(I$4="",I$4=0),"",-ABS(Expenses!I12)) -> -43894.844 | J19: =IF(OR(J$4="",J$4=0),"",-ABS(Expenses!J12)) -> -45211.689 | K19: =IF(OR(K$4="",K$4=0),"",-ABS(Expenses!K12)) -> -46568.04 | L19: =IF(OR(L$4="",L$4=0),"",-ABS(Expenses!L12)) -> -47965.081 | ... S19: =IF(OR(S$4="",S$4=0),"",-ABS(Expenses!S12)) -> -58990.999
B20: - Taxes | E20: =IF(OR(E$4="",E$4=0),"",-ABS(Expenses!E13)) -> -120000 | F20: =IF(OR(F$4="",F$4=0),"",-ABS(Expenses!F13)) -> -123600 | G20: =IF(OR(G$4="",G$4=0),"",-ABS(Expenses!G13)) -> -127308 | H20: =IF(OR(H$4="",H$4=0),"",-ABS(Expenses!H13)) -> -131127.24 | I20: =IF(OR(I$4="",I$4=0),"",-ABS(Expenses!I13)) -> -135061.06 | J20: =IF(OR(J$4="",J$4=0),"",-ABS(Expenses!J13)) -> -139112.89 | K20: =IF(OR(K$4="",K$4=0),"",-ABS(Expenses!K13)) -> -143286.28 | L20: =IF(OR(L$4="",L$4=0),"",-ABS(Expenses!L13)) -> -147584.86 | ... S20: =IF(OR(S$4="",S$4=0),"",-ABS(Expenses!S13)) -> -181510.77
B21: Operating Expenses | D21: =-AVERAGE(E21:P21)/AVERAGE($E$7:$P$7) -> 0.19835989 | E21: =IF(OR(E$4="",E$4=0),"",-ABS(Expenses!E14)) -> -639582.91 | F21: =IF(OR(F$4="",F$4=0),"",-ABS(Expenses!F14)) -> -658770.4 | G21: =IF(OR(G$4="",G$4=0),"",-ABS(Expenses!G14)) -> -678533.51 | H21: =IF(OR(H$4="",H$4=0),"",-ABS(Expenses!H14)) -> -698889.52 | I21: =IF(OR(I$4="",I$4=0),"",-ABS(Expenses!I14)) -> -719856.2 | J21: =IF(OR(J$4="",J$4=0),"",-ABS(Expenses!J14)) -> -741451.89 | K21: =IF(OR(K$4="",K$4=0),"",-ABS(Expenses!K14)) -> -763695.44 | L21: =IF(OR(L$4="",L$4=0),"",-ABS(Expenses!L14)) -> -786606.31 | ... S21: =IF(OR(S$4="",S$4=0),"",-ABS(Expenses!S14)) -> -967426.54
B23: Net Operating Income | D23: =AVERAGE(E23:P23)/AVERAGE($E$7:$P$7) -> 0.65318455 | E23: =IF(OR(E$4="",E$4=0),"",SUM(E11,E21)) -> 2299847.5 | F23: =IF(OR(F$4="",F$4=0),"",SUM(F11,F21)) -> 2347888.9 | G23: =IF(OR(G$4="",G$4=0),"",SUM(G11,G21)) -> 2407303.2 | H23: =IF(OR(H$4="",H$4=0),"",SUM(H11,H21)) -> 2433107.2 | I23: =IF(OR(I$4="",I$4=0),"",SUM(I11,I21)) -> 2458991.7 | J23: =IF(OR(J$4="",J$4=0),"",SUM(J11,J21)) -> 2484948.6 | K23: =IF(OR(K$4="",K$4=0),"",SUM(K11,K21)) -> 2510969.7 | L23: =IF(OR(L$4="",L$4=0),"",SUM(L11,L21)) -> 2537046.1 | ... S23: =IF(OR(S$4="",S$4=0),"",SUM(S11,S21)) -> 2720301.5
B25: - Releasing Costs | E25: =IF(OR(E$4="",E$4=0),"",-SUMIF(Calculations!$C$75:$FZ$75,E$4,Calculations!$C$84:$FZ$84)) -> 0 | F25: =IF(OR(F$4="",F$4=0),"",-SUMIF(Calculations!$C$75:$FZ$75,F$4,Calculations!$C$84:$FZ$84)) -> -15912 | G25: =IF(OR(G$4="",G$4=0),"",-SUMIF(Calculations!$C$75:$FZ$75,G$4,Calculations!$C$84:$FZ$84)) -> -16230.24 | H25: =IF(OR(H$4="",H$4=0),"",-SUMIF(Calculations!$C$75:$FZ$75,H$4,Calculations!$C$84:$FZ$84)) -> -16554.845 | I25: =IF(OR(I$4="",I$4=0),"",-SUMIF(Calculations!$C$75:$FZ$75,I$4,Calculations!$C$84:$FZ$84)) -> -16885.942 | J25: =IF(OR(J$4="",J$4=0),"",-SUMIF(Calculations!$C$75:$FZ$75,J$4,Calculations!$C$84:$FZ$84)) -> -17223.661 | K25: =IF(OR(K$4="",K$4=0),"",-SUMIF(Calculations!$C$75:$FZ$75,K$4,Calculations!$C$84:$FZ$84)) -> -17568.134 | L25: =IF(OR(L$4="",L$4=0),"",-SUMIF(Calculations!$C$75:$FZ$75,L$4,Calculations!$C$84:$FZ$84)) -> -17919.496 | ... S25: =IF(OR(S$4="",S$4=0),"",-SUMIF(Calculations!$C$75:$FZ$75,S$4,Calculations!$C$84:$FZ$84)) -> -20583.869
B26: - Value Add Costs | E26: =IF(OR(E$4="",E$4=0),"",Expenses!E20) -> -350000 | F26: =IF(OR(F$4="",F$4=0),"",Expenses!F20) -> -200000 | G26: =IF(OR(G$4="",G$4=0),"",Expenses!G20) -> 0 | H26: =IF(OR(H$4="",H$4=0),"",Expenses!H20) -> 0 | I26: =IF(OR(I$4="",I$4=0),"",Expenses!I20) -> 0 | J26: =IF(OR(J$4="",J$4=0),"",Expenses!J20) -> 0 | K26: =IF(OR(K$4="",K$4=0),"",Expenses!K20) -> 0 | L26: =IF(OR(L$4="",L$4=0),"",Expenses!L20) -> 0 | ... S26: =IF(OR(S$4="",S$4=0),"",Expenses!S20) -> 0
B27: - Misc. CapEx | E27: =IF(OR(E$4="",E$4=0),"",-SUMIF(Calculations!$C$25:$FZ$25,E$4,Calculations!$C$34:$FZ$34)) -> -97200 | F27: =IF(OR(F$4="",F$4=0),"",-SUMIF(Calculations!$C$25:$FZ$25,F$4,Calculations!$C$34:$FZ$34)) -> -99630 | G27: =IF(OR(G$4="",G$4=0),"",-SUMIF(Calculations!$C$25:$FZ$25,G$4,Calculations!$C$34:$FZ$34)) -> -102120.75 | H27: =IF(OR(H$4="",H$4=0),"",-SUMIF(Calculations!$C$25:$FZ$25,H$4,Calculations!$C$34:$FZ$34)) -> -104673.77 | I27: =IF(OR(I$4="",I$4=0),"",-SUMIF(Calculations!$C$25:$FZ$25,I$4,Calculations!$C$34:$FZ$34)) -> -107290.61 | J27: =IF(OR(J$4="",J$4=0),"",-SUMIF(Calculations!$C$25:$FZ$25,J$4,Calculations!$C$34:$FZ$34)) -> -109972.88 | K27: =IF(OR(K$4="",K$4=0),"",-SUMIF(Calculations!$C$25:$FZ$25,K$4,Calculations!$C$34:$FZ$34)) -> -112722.2 | L27: =IF(OR(L$4="",L$4=0),"",-SUMIF(Calculations!$C$25:$FZ$25,L$4,Calculations!$C$34:$FZ$34)) -> -115540.26 | ... S27: =IF(OR(S$4="",S$4=0),"",-SUMIF(Calculations!$C$25:$FZ$25,S$4,Calculations!$C$34:$FZ$34)) -> -137341.06
B28: Capital Expenditures | D28: =-AVERAGE(E28:P28)/AVERAGE($E$7:$P$7) -> 0.045553959 | E28: =IF(OR(E$4="",E$4=0),"",SUM(E25:E27)) -> -447200 | F28: =IF(OR(F$4="",F$4=0),"",SUM(F25:F27)) -> -315542 | G28: =IF(OR(G$4="",G$4=0),"",SUM(G25:G27)) -> -118350.99 | H28: =IF(OR(H$4="",H$4=0),"",SUM(H25:H27)) -> -121228.61 | I28: =IF(OR(I$4="",I$4=0),"",SUM(I25:I27)) -> -124176.55 | J28: =IF(OR(J$4="",J$4=0),"",SUM(J25:J27)) -> -127196.54 | K28: =IF(OR(K$4="",K$4=0),"",SUM(K25:K27)) -> -130290.33 | L28: =IF(OR(L$4="",L$4=0),"",SUM(L25:L27)) -> -133459.75 | ... S28: =IF(OR(S$4="",S$4=0),"",SUM(S25:S27)) -> -157924.92
B30: Cash Flow From Operations | D30: =AVERAGE(E30:P30)/AVERAGE($E$7:$P$7) -> 0.60763059 | E30: =IF(OR(E$4="",E$4=0),"",SUM(E23,E28)) -> 1852647.5 | F30: =IF(OR(F$4="",F$4=0),"",SUM(F23,F28)) -> 2032346.9 | G30: =IF(OR(G$4="",G$4=0),"",SUM(G23,G28)) -> 2288952.2 | H30: =IF(OR(H$4="",H$4=0),"",SUM(H23,H28)) -> 2311878.6 | I30: =IF(OR(I$4="",I$4=0),"",SUM(I23,I28)) -> 2334815.1 | J30: =IF(OR(J$4="",J$4=0),"",SUM(J23,J28)) -> 2357752.1 | K30: =IF(OR(K$4="",K$4=0),"",SUM(K23,K28)) -> 2380679.4 | L30: =IF(OR(L$4="",L$4=0),"",SUM(L23,L28)) -> 2403586.4 | ... S30: =IF(OR(S$4="",S$4=0),"",SUM(S23,S28)) -> 2562376.6

Sheet Property Returns
B2: Property Level Returns
D4: 1 | E4: =IF(OR(D4="",D4=Terminal_Cap_Year),"",D4+1) -> 2 | F4: =IF(OR(E4="",E4=Terminal_Cap_Year),"",E4+1) -> 3 | G4: =IF(OR(F4="",F4=Terminal_Cap_Year),"",F4+1) -> 4 | H4: =IF(OR(G4="",G4=Terminal_Cap_Year),"",G4+1) -> 5 | I4: =IF(OR(H4="",H4=Terminal_Cap_Year),"",H4+1) -> 6 | J4: =IF(OR(I4="",I4=Terminal_Cap_Year),"",I4+1) -> 7 | K4: =IF(OR(J4="",J4=Terminal_Cap_Year),"",J4+1) -> 8 | L4: =IF(OR(K4="",K4=Terminal_Cap_Year),"",K4+1) -> 9 | ... R4: =IF(OR(Q4="",Q4=Terminal_Cap_Year),"",Q4+1) -> 15
C5: Year Ending | D5: =EOMONTH(Analysis_Start,11) -> 44196 | E5: =EOMONTH(Analysis_Start,11) -> 44196 | F5: =IF(F4="","",EOMONTH(Analysis_Start,(11*F4)+E4)) -> 44926 | G5: =IF(G4="","",EOMONTH(Analysis_Start,(11*G4)+F4)) -> 45291 | H5: =IF(H4="","",EOMONTH(Analysis_Start,(11*H4)+G4)) -> 45657 | I5: =IF(I4="","",EOMONTH(Analysis_Start,(11*I4)+H4)) -> 46022 | J5: =IF(J4="","",EOMONTH(Analysis_Start,(11*J4)+I4)) -> 46387 | K5: =IF(K4="","",EOMONTH(Analysis_Start,(11*K4)+J4)) -> 46752 | L5: =IF(L4="","",EOMONTH(Analysis_Start,(11*L4)+K4)) -> 47118 | M5: =IF(M4="","",EOMONTH(Analysis_Start,(11*M4)+L4)) -> 47483 | ... R5: =IF(R4="","",EOMONTH(Analysis_Start,(11*R4)+Q4)) -> 49309
B6: Effective Gross Revenue | D6: =IF(OR(D$4="",D$4=0),"",'Annual Cash Flow'!E11) -> 2939430.4 | E6: =IF(OR(E$4="",E$4=0),"",'Annual Cash Flow'!F11) -> 3006659.3 | F6: =IF(OR(F$4="",F$4=0),"",'Annual Cash Flow'!G11) -> 3085836.7 | G6: =IF(OR(G$4="",G$4=0),"",'Annual Cash Flow'!H11) -> 3131996.7 | H6: =IF(OR(H$4="",H$4=0),"",'Annual Cash Flow'!I11) -> 3178847.9 | I6: =IF(OR(I$4="",I$4=0),"",'Annual Cash Flow'!J11) -> 3226400.5 | J6: =IF(OR(J$4="",J$4=0),"",'Annual Cash Flow'!K11) -> 3274665.2 | K6: =IF(OR(K$4="",K$4=0),"",'Annual Cash Flow'!L11) -> 3323652.4 | ... R6: =IF(OR(R$4="",R$4=0),"",'Annual Cash Flow'!S11) -> 3687728
B7: Operating Expenses | D7: =IF(OR(D$4="",D$4=0),"",'Annual Cash Flow'!E21) -> -639582.91 | E7: =IF(OR(E$4="",E$4=0),"",'Annual Cash Flow'!F21) -> -658770.4 | F7: =IF(OR(F$4="",F$4=0),"",'Annual Cash Flow'!G21) -> -678533.51 | G7: =IF(OR(G$4="",G$4=0),"",'Annual Cash Flow'!H21) -> -698889.52 | H7: =IF(OR(H$4="",H$4=0),"",'Annual Cash Flow'!I21) -> -719856.2 | I7: =IF(OR(I$4="",I$4=0),"",'Annual Cash Flow'!J21) -> -741451.89 | J7: =IF(OR(J$4="",J$4=0),"",'Annual Cash Flow'!K21) -> -763695.44 | K7: =IF(OR(K$4="",K$4=0),"",'Annual Cash Flow'!L21) -> -786606.31 | ... R7: =IF(OR(R$4="",R$4=0),"",'Annual Cash Flow'!S21) -> -967426.54
B8: Net Operating Income | D8: =IF(OR(D$4="",D$4=0),"",'Annual Cash Flow'!E23) -> 2299847.5 | E8: =IF(OR(E$4="",E$4=0),"",'Annual Cash Flow'!F23) -> 2347888.9 | F8: =IF(OR(F$4="",F$4=0),"",'Annual Cash Flow'!G23) -> 2407303.2 | G8: =IF(OR(G$4="",G$4=0),"",'Annual Cash Flow'!H23) -> 2433107.2 | H8: =IF(OR(H$4="",H$4=0),"",'Annual Cash Flow'!I23) -> 2458991.7 | I8: =IF(OR(I$4="",I$4=0),"",'Annual Cash Flow'!J23) -> 2484948.6 | J8: =IF(OR(J$4="",J$4=0),"",'Annual Cash Flow'!K23) -> 2510969.7 | K8: =IF(OR(K$4="",K$4=0),"",'Annual Cash Flow'!L23) -> 2537046.1 | ... R8: =IF(OR(R$4="",R$4=0),"",'Annual Cash Flow'!S23) -> 2720301.5
B9: Capital Expenditures | D9: =IF(OR(D$4="",D$4=0),"",'Annual Cash Flow'!E28) -> -447200 | E9: =IF(OR(E$4="",E$4=0),"",'Annual Cash Flow'!F28) -> -315542 | F9: =IF(OR(F$4="",F$4=0),"",'Annual Cash Flow'!G28) -> -118350.99 | G9: =IF(OR(G$4="",G$4=0),"",'Annual Cash Flow'!H28) -> -121228.61 | H9: =IF(OR(H$4="",H$4=0),"",'Annual Cash Flow'!I28) -> -124176.55 | I9: =IF(OR(I$4="",I$4=0),"",'Annual Cash Flow'!J28) -> -127196.54 | J9: =IF(OR(J$4="",J$4=0),"",'Annual Cash Flow'!K28) -> -130290.33 | K9: =IF(OR(K$4="",K$4=0),"",'Annual Cash Flow'!L28) -> -133459.75 | ... R9: =IF(OR(R$4="",R$4=0),"",'Annual Cash Flow'!S28) -> -157924.92
B10: Cash Flow From Operations | D10: =IF(OR(D$4="",D$4=0),"",'Annual Cash Flow'!E30) -> 1852647.5 | E10: =IF(OR(E$4="",E$4=0),"",'Annual Cash Flow'!F30) -> 2032346.9 | F10: =IF(OR(F$4="",F$4=0),"",'Annual Cash Flow'!G30) -> 2288952.2 | G10: =IF(OR(G$4="",G$4=0),"",'Annual Cash Flow'!H30) -> 2311878.6 | H10: =IF(OR(H$4="",H$4=0),"",'Annual Cash Flow'!I30) -> 2334815.1 | I10: =IF(OR(I$4="",I$4=0),"",'Annual Cash Flow'!J30) -> 2357752.1 | J10: =IF(OR(J$4="",J$4=0),"",'Annual Cash Flow'!K30) -> 2380679.4 | K10: =IF(OR(K$4="",K$4=0),"",'Annual Cash Flow'!L30) -> 2403586.4 | ... R10: =IF(OR(R$4="",R$4=0),"",'Annual Cash Flow'!S30) -> 2562376.6
B12: Cap Rate at Sale | D12: ='Property Summary'!$C$11 -> 0.065 | E12: =IF(OR(E$4="",E$4=0),"",IF(E$4>Effective_Hold_Period,"",(D$12+('Property Summary'!$C$10/10000)))) -> 0.0655 | F12: =IF(OR(F$4="",F$4=0),"",IF(F$4>Effective_Hold_Period,"",(E$12+('Property Summary'!$C$10/10000)))) -> 0.066 | G12: =IF(OR(G$4="",G$4=0),"",IF(G$4>Effective_Hold_Period,"",(F$12+('Property Summary'!$C$10/10000)))) -> 0.0665 | H12: =IF(OR(H$4="",H$4=0),"",IF(H$4>Effective_Hold_Period,"",(G$12+('Property Summary'!$C$10/10000)))) -> 0.067 | I12: =IF(OR(I$4="",I$4=0),"",IF(I$4>Effective_Hold_Period,"",(H$12+('Property Summary'!$C$10/10000)))) -> 0.0675 | J12: =IF(OR(J$4="",J$4=0),"",IF(J$4>Effective_Hold_Period,"",(I$12+('Property Summary'!$C$10/10000)))) -> 0.068 | K12: =IF(OR(K$4="",K$4=0),"",IF(K$4>Effective_Hold_Period,"",(J$12+('Property Summary'!$C$10/10000)))) -> 0.0685 | L12: =IF(OR(L$4="",L$4=0),"",IF(L$4>Effective_Hold_Period,"",(K$12+('Property Summary'!$C$10/10000)))) -> 0.069 | ... R12: =IF(OR(R$4="",R$4=0),"",IF(R$4>Effective_Hold_Period,"",(Q$12+('Property Summary'!$C$10/10000)))) -> 0.072
B13: Net Sales Price | D13: =IFERROR(HLOOKUP(Terminal_Cap_Year-Effective_Hold_Period+D$4,$D$4:$R$10,5,FALSE)/D$12,"") -> 35382269 | E13: =IFERROR(HLOOKUP(Terminal_Cap_Year-Effective_Hold_Period+E$4,$D$4:$R$10,5,FALSE)/E$12,"") -> 35845632 | F13: =IFERROR(HLOOKUP(Terminal_Cap_Year-Effective_Hold_Period+F$4,$D$4:$R$10,5,FALSE)/F$12,"") -> 36474291 | G13: =IFERROR(HLOOKUP(Terminal_Cap_Year-Effective_Hold_Period+G$4,$D$4:$R$10,5,FALSE)/G$12,"") -> 36588078 | H13: =IFERROR(HLOOKUP(Terminal_Cap_Year-Effective_Hold_Period+H$4,$D$4:$R$10,5,FALSE)/H$12,"") -> 36701368 | I13: =IFERROR(HLOOKUP(Terminal_Cap_Year-Effective_Hold_Period+I$4,$D$4:$R$10,5,FALSE)/I$12,"") -> 36814054 | J13: =IFERROR(HLOOKUP(Terminal_Cap_Year-Effective_Hold_Period+J$4,$D$4:$R$10,5,FALSE)/J$12,"") -> 36926025 | K13: =IFERROR(HLOOKUP(Terminal_Cap_Year-Effective_Hold_Period+K$4,$D$4:$R$10,5,FALSE)/K$12,"") -> 37037170 | ... R13: =IFERROR(HLOOKUP(Terminal_Cap_Year-Effective_Hold_Period+R$4,$D$4:$R$10,5,FALSE)/R$12,"") -> 37781965
B14: ="Net Sales Price Per "&'Property Summary'!$I$26 -> Net Sales Price Per SQFT | D14: =IFERROR(IF(OR(D$4="",D$4=0),"",D13/'Property Summary'!$I$27),"") -> 565.93521 | E14: =IFERROR(IF(OR(E$4="",E$4=0),"",E13/'Property Summary'!$I$27),"") -> 573.34664 | F14: =IFERROR(IF(OR(F$4="",F$4=0),"",F13/'Property Summary'!$I$27),"") -> 583.40196 | G14: =IFERROR(IF(OR(G$4="",G$4=0),"",G13/'Property Summary'!$I$27),"") -> 585.22198 | H14: =IFERROR(IF(OR(H$4="",H$4=0),"",H13/'Property Summary'!$I$27),"") -> 587.03404 | I14: =IFERROR(IF(OR(I$4="",I$4=0),"",I13/'Property Summary'!$I$27),"") -> 588.83644 | J14: =IFERROR(IF(OR(J$4="",J$4=0),"",J13/'Property Summary'!$I$27),"") -> 590.6274 | K14: =IFERROR(IF(OR(K$4="",K$4=0),"",K13/'Property Summary'!$I$27),"") -> 592.40515 | ... R14: =IFERROR(IF(OR(R$4="",R$4=0),"",R13/'Property Summary'!$I$27),"") -> 604.31806
B16: Cash Flow from Operations | D16: =IF(D$4>Analysis_Period,"",D$10) -> 1852647.5 | E16: =IF(E$4>Analysis_Period,"",E$10) -> 2032346.9 | F16: =IF(F$4>Analysis_Period,"",F$10) -> 2288952.2 | G16: =IF(G$4>Analysis_Period,"",G$10) -> 2311878.6 | H16: =IF(H$4>Analysis_Period,"",H$10) -> 2334815.1 | I16: =IF(I$4>Analysis_Period,"",I$10) -> 2357752.1 | J16: =IF(J$4>Analysis_Period,"",J$10) -> 2380679.4 | K16: =IF(K$4>Analysis_Period,"",K$10) -> 2403586.4 | ... R16: =IF(R$4>Analysis_Period,"",R$10) -> 2562376.6
B17: Free and Clear Return | D17: =IF(D$10="","",D$10/-D$50) -> 0.051564425 | E17: =IF(E$10="","",IF(E$4>Effective_Hold_Period,"",E$10/-E$50)) -> 0.056565969 | F17: =IF(F$10="","",IF(F$4>Effective_Hold_Period,"",F$10/-F$50)) -> 0.06370802 | G17: =IF(G$10="","",IF(G$4>Effective_Hold_Period,"",G$10/-G$50)) -> 0.064346127 | H17: =IF(H$10="","",IF(H$4>Effective_Hold_Period,"",H$10/-H$50)) -> 0.064984516 | I17: =IF(I$10="","",IF(I$4>Effective_Hold_Period,"",I$10/-I$50)) -> 0.065622917 | J17: =IF(J$10="","",IF(J$4>Effective_Hold_Period,"",J$10/-J$50)) -> 0.066261048 | K17: =IF(K$10="","",IF(K$4>Effective_Hold_Period,"",K$10/-K$50)) -> 0.066898615 | L17: =IF(L$10="","",IF(L$4>Effective_Hold_Period,"",L$10/-L$50)) -> 0.06753531 | ... R17: =IF(R$10="","",IF(R$4>Effective_Hold_Period,"",R$10/-R$50)) -> 0.071318194
B18: Avg. Free and Clear Return | D18: =IF(D17="","",AVERAGE($D$17:D$17)) -> 0.051564425 | E18: =IF(E17="","",AVERAGE($D$17:E$17)) -> 0.054065197 | F18: =IF(F17="","",AVERAGE($D$17:F$17)) -> 0.057279471 | G18: =IF(G17="","",AVERAGE($D$17:G$17)) -> 0.059046135 | H18: =IF(H17="","",AVERAGE($D$17:H$17)) -> 0.060233811 | I18: =IF(I17="","",AVERAGE($D$17:I$17)) -> 0.061131995 | J18: =IF(J17="","",AVERAGE($D$17:J$17)) -> 0.061864717 | K18: =IF(K17="","",AVERAGE($D$17:K$17)) -> 0.062493954 | ... R18: =IF(R17="","",AVERAGE($D$17:R$17)) -> 0.065731889
B19: Unlevered CF w/ Residual | D19: =IF(D4=Analysis_Period,D$13+D$16,D$16) -> 1852647.5 | E19: =IF(E4=Analysis_Period,E$13+E$16,E$16) -> 2032346.9 | F19: =IF(F4=Analysis_Period,F$13+F$16,F$16) -> 2288952.2 | G19: =IF(G4=Analysis_Period,G$13+G$16,G$16) -> 2311878.6 | H19: =IF(H4=Analysis_Period,H$13+H$16,H$16) -> 2334815.1 | I19: =IF(I4=Analysis_Period,I$13+I$16,I$16) -> 2357752.1 | J19: =IF(J4=Analysis_Period,J$13+J$16,J$16) -> 2380679.4 | K19: =IF(K4=Analysis_Period,K$13+K$16,K$16) -> 2403586.4 | ... R19: =IF(R4=Analysis_Period,R$13+R$16,R$16) -> 40344342
B21: Unlevered IRR | D21: =IF(D4>Analysis_Period,"",D49) -> 0.036353151 | E21: =IF(E4>Analysis_Period,"",E49) -> 0.05287331 | F21: =IF(F4>Analysis_Period,"",F49) -> 0.061797984 | G21: =IF(G4>Analysis_Period,"",G49) -> 0.062874554 | H21: =IF(H4>Analysis_Period,"",H49) -> 0.063589214 | I21: =IF(I4>Analysis_Period,"",I49) -> 0.06412065 | J21: =IF(J4>Analysis_Period,"",J49) -> 0.064545229 | K21: =IF(K4>Analysis_Period,"",K49) -> 0.064901085 | ... R21: =IF(R4>Analysis_Period,"",R49) -> 0.066536708
B22: Unlevered EM | D22: =IF(D$48="","",SUMIF(D50:D65,">0")/-SUMIF(D50:D65,"<0")) -> 1.0363532 | E22: =IF(E$48="","",SUMIF(E50:E65,">0")/-SUMIF(E50:E65,"<0")) -> 1.1058158 | F22: =IF(F$48="","",SUMIF(F50:F65,">0")/-SUMIF(F50:F65,"<0")) -> 1.1870212 | G22: =IF(G$48="","",SUMIF(G50:G65,">0")/-SUMIF(G50:G65,"<0")) -> 1.2545344 | H22: =IF(H$48="","",SUMIF(H50:H65,">0")/-SUMIF(H50:H65,"<0")) -> 1.3226721 | I22: =IF(I$48="","",SUMIF(I50:I65,">0")/-SUMIF(I50:I65,"<0")) -> 1.3914313 | J22: =IF(J$48="","",SUMIF(J50:J65,">0")/-SUMIF(J50:J65,"<0")) -> 1.4608089 | K22: =IF(K$48="","",SUMIF(K50:K65,">0")/-SUMIF(K50:K65,"<0")) -> 1.5308009 | ... R22: =IF(R$48="","",SUMIF(R50:R65,">0")/-SUMIF(R50:R65,"<0")) -> 2.0375574
B24: % of Total Cash from Operations | D24: =IFERROR(SUM($D$19:D$19)/(SUM($D$19:D$19)+D13),"") -> 0.04975565 | E24: =IFERROR(SUM($D$19:E$19)/(SUM($D$19:E$19)+E13),"") -> 0.097783366 | F24: =IFERROR(SUM($D$19:F$19)/(SUM($D$19:F$19)+F13),"") -> 0.1447644 | G24: =IFERROR(SUM($D$19:G$19)/(SUM($D$19:G$19)+G13),"") -> 0.18826471 | H24: =IFERROR(SUM($D$19:H$19)/(SUM($D$19:H$19)+H13),"") -> 0.22769745 | I24: =IFERROR(SUM($D$19:I$19)/(SUM($D$19:I$19)+I13),"") -> 0.26360767 | J24: =IFERROR(SUM($D$19:J$19)/(SUM($D$19:J$19)+J13),"") -> 0.29644742 | K24: =IFERROR(SUM($D$19:K$19)/(SUM($D$19:K$19)+K13),"") -> 0.32659481 | ... R24: =IFERROR(SUM($D$19:R$19)/(SUM($D$19:R$19)+R13),"") -> 0.65958802
B25: % of Total Cash from Sale | D25: =IFERROR(1-D24,"") -> 0.95024435 | E25: =IFERROR(1-E24,"") -> 0.90221663 | F25: =IFERROR(1-F24,"") -> 0.8552356 | G25: =IFERROR(1-G24,"") -> 0.81173529 | H25: =IFERROR(1-H24,"") -> 0.77230255 | I25: =IFERROR(1-I24,"") -> 0.73639233 | J25: =IFERROR(1-J24,"") -> 0.70355258 | K25: =IFERROR(1-K24,"") -> 0.67340519 | ... R25: =IFERROR(1-R24,"") -> 0.34041198
B27: Debt Service | D27: =Debt!D$6 -> 1331881 | E27: =Debt!E$6 -> 1331881 | F27: =Debt!F$6 -> 1331881 | G27: =Debt!G$6 -> 1331881 | H27: =Debt!H$6 -> 1331881 | I27: =Debt!I$6 -> 1331881 | J27: =Debt!J$6 -> 1331881 | K27: =Debt!K$6 -> 1331881 | ... R27: =Debt!R$6 -> 1331881
B28: Debt Service Coverage Ratio (NOI) | D28: =IFERROR(D$8/D$27,"") -> 1.7267665 | E28: =IFERROR(E$8/E$27,"") -> 1.7628369 | F28: =IFERROR(F$8/F$27,"") -> 1.8074462 | G28: =IFERROR(G$8/G$27,"") -> 1.8268203 | H28: =IFERROR(H$8/H$27,"") -> 1.8462548 | I28: =IFERROR(I$8/I$27,"") -> 1.8657438 | J28: =IFERROR(J$8/J$27,"") -> 1.8852809 | K28: =IFERROR(K$8/K$27,"") -> 1.9048595 | ... R28: =IFERROR(R$8/R$27,"") -> 2.0424509
B29: Debt Yield (NOI) | D29: =IFERROR(D$8/D$30,"") -> 0.12697548 | E29: =IFERROR(E$8/E$30,"") -> 0.12976655 | F29: =IFERROR(F$8/F$30,"") -> 0.13320353 | G29: =IFERROR(G$8/G$30,"") -> 0.13479819 | H29: =IFERROR(H$8/H$30,"") -> 0.13641395 | I29: =IFERROR(I$8/I$30,"") -> 0.13805187 | J29: =IFERROR(J$8/J$30,"") -> 0.13971314 | K29: =IFERROR(K$8/K$30,"") -> 0.14139904 | ... R29: =IFERROR(R$8/R$30,"") -> 0.15403424
B30: Loan Balance | D30: =Debt!D$7 -> 18112533 | E30: =Debt!E$7 -> 18093176 | F30: =Debt!F$7 -> 18072368 | G30: =Debt!G$7 -> 18050000 | H30: =Debt!H$7 -> 18025955 | I30: =Debt!I$7 -> 18000108 | J30: =Debt!J$7 -> 17972324 | K30: =Debt!K$7 -> 17942457 | ... R30: =Debt!R$7 -> 17660369
B32: Net Cash on Sale | D32: =IFERROR(D$13-D$30,"") -> 17269736 | E32: =IFERROR(E$13-E$30,"") -> 17752456 | F32: =IFERROR(F$13-F$30,"") -> 18401923 | G32: =IFERROR(G$13-G$30,"") -> 18538079 | H32: =IFERROR(H$13-H$30,"") -> 18675413 | I32: =IFERROR(I$13-I$30,"") -> 18813946 | J32: =IFERROR(J$13-J$30,"") -> 18953701 | K32: =IFERROR(K$13-K$30,"") -> 19094713 | ... R32: =IFERROR(R$13-R$30,"") -> 20121596
B33: Net Gain | D33: =IFERROR(D$32-(-D71),"") -> 18311269 | E33: =IFERROR(E$32-(-E71),"") -> 35022193 | F33: =IFERROR(F$32-(-F71),"") -> 35671659 | G33: =IFERROR(G$32-(-G71),"") -> 35807815 | H33: =IFERROR(H$32-(-H71),"") -> 35945150 | I33: =IFERROR(I$32-(-I71),"") -> 36083682 | J33: =IFERROR(J$32-(-J71),"") -> 36223438 | K33: =IFERROR(K$32-(-K71),"") -> 36364449 | ... R33: =IFERROR(R$32-(-R71),"") -> 37391332
B35: Cash Flow After Financing | D35: =IFERROR(D$10-D$27,"") -> 520766.52 | E35: =IFERROR(E$10-E$27,"") -> 700465.93 | F35: =IFERROR(F$10-F$27,"") -> 957071.22 | G35: =IFERROR(G$10-G$27,"") -> 979997.63 | H35: =IFERROR(H$10-H$27,"") -> 1002934.2 | I35: =IFERROR(I$10-I$27,"") -> 1025871.1 | J35: =IFERROR(J$10-J$27,"") -> 1048798.4 | K35: =IFERROR(K$10-K$27,"") -> 1071705.4 | ... R35: =IFERROR(R$10-R$27,"") -> 1230495.6
B36: Cash-on-Cash Return | D36: =IF(D35="","",D35/(-D70)) -> 0.026490261 | E36: =IF(E35="","",E35/(-E70)) -> 0.035631179 | F36: =IF(F35="","",F35/(-F70)) -> 0.048684132 | G36: =IF(G35="","",G35/(-G70)) -> 0.049850349 | H36: =IF(H35="","",H35/(-H70)) -> 0.051017081 | I36: =IF(I35="","",I35/(-I70)) -> 0.052183835 | J36: =IF(J35="","",J35/(-J70)) -> 0.053350095 | K36: =IF(K35="","",K35/(-K70)) -> 0.054515325 | ... R36: =IF(R35="","",R35/(-R70)) -> 0.062592636
B37: Avg. Cash-on-Cash Return | D37: =IF(D36="","",AVERAGE($D$36:D$36)) -> 0.026490261 | E37: =IF(E36="","",AVERAGE($D$36:E$36)) -> 0.03106072 | F37: =IF(F36="","",AVERAGE($D$36:F$36)) -> 0.036935191 | G37: =IF(G36="","",AVERAGE($D$36:G$36)) -> 0.04016398 | H37: =IF(H36="","",AVERAGE($D$36:H$36)) -> 0.0423346 | I37: =IF(I36="","",AVERAGE($D$36:I$36)) -> 0.043976139 | J37: =IF(J36="","",AVERAGE($D$36:J$36)) -> 0.045315276 | K37: =IF(K36="","",AVERAGE($D$36:K$36)) -> 0.046465282 | ... R37: =IF(R36="","",AVERAGE($D$36:R$36)) -> 0.052382995
B39: Levered IRR | D39: =D$69 -> -0.94701948 | E39: =E$69 -> -0.046767434 | F39: =F$69 -> 0.51634898 | G39: =G$69 -> 0.73145868 | H39: =H$69 -> 0.82159013 | I39: =I$69 -> 0.86261375 | J39: =J$69 -> 0.88234595 | K39: =K$69 -> 0.89218105 | ... R39: =R$69 -> 0.90252903
B40: Levered EM | D40: =IF(D$48="","",SUMIF(D$70:D$85,">0")/-SUMIF(D$70:D$85,"<0")) -> 0.052980521 | E40: =IF(E$48="","",SUMIF(E$70:E$85,">0")/-SUMIF(E$70:E$85,"<0")) -> 0.9497363 | F40: =IF(F$48="","",SUMIF(F$70:F$85,">0")/-SUMIF(F$70:F$85,"<0")) -> 1.8788711 | G40: =IF(G$48="","",SUMIF(G$70:G$85,">0")/-SUMIF(G$70:G$85,"<0")) -> 2.8172693 | H40: =IF(H$48="","",SUMIF(H$70:H$85,">0")/-SUMIF(H$70:H$85,"<0")) -> 3.7625945 | I40: =IF(I$48="","",SUMIF(I$70:I$85,">0")/-SUMIF(I$70:I$85,"<0")) -> 4.7149057 | J40: =IF(J$48="","",SUMIF(J$70:J$85,">0")/-SUMIF(J$70:J$85,"<0")) -> 5.6742628 | K40: =IF(K$48="","",SUMIF(K$70:K$85,">0")/-SUMIF(K$70:K$85,"<0")) -> 6.6407268 | ... R40: =IF(R$48="","",SUMIF(R$70:R$85,">0")/-SUMIF(R$70:R$85,"<0")) -> 13.610558
B42: Levered Before Tax Cash Flow | D42: =IF(D$4=Effective_Hold_Period,D$32+D$35,D$35) -> 520766.52 | E42: =IF(E$4=Effective_Hold_Period,E$32+E$35,E$35) -> 700465.93 | F42: =IF(F$4=Effective_Hold_Period,F$32+F$35,F$35) -> 957071.22 | G42: =IF(G$4=Effective_Hold_Period,G$32+G$35,G$35) -> 979997.63 | H42: =IF(H$4=Effective_Hold_Period,H$32+H$35,H$35) -> 1002934.2 | I42: =IF(I$4=Effective_Hold_Period,I$32+I$35,I$35) -> 1025871.1 | J42: =IF(J$4=Effective_Hold_Period,J$32+J$35,J$35) -> 1048798.4 | K42: =IF(K$4=Effective_Hold_Period,K$32+K$35,K$35) -> 1071705.4 | ... R42: =IF(R$4=Effective_Hold_Period,R$32+R$35,R$35) -> 21352091
B46: Internal Rate of Return Calculations
B47: Unlevered
C48: Year | D48: =IF(OR(D$13="",D$13=0),"",D$4) -> 1 | E48: =IF(OR(E$13="",E$13=0),"",E$4) -> 2 | F48: =IF(OR(F$13="",F$13=0),"",F$4) -> 3 | G48: =IF(OR(G$13="",G$13=0),"",G$4) -> 4 | H48: =IF(OR(H$13="",H$13=0),"",H$4) -> 5 | I48: =IF(OR(I$13="",I$13=0),"",I$4) -> 6 | J48: =IF(OR(J$13="",J$13=0),"",J$4) -> 7 | K48: =IF(OR(K$13="",K$13=0),"",K$4) -> 8 | ... R48: =IF(OR(R$13="",R$13=0),"",R$4) -> 15
C49: IRR | D49: =IF(OR(D$48="",D$48=0),"",IF(AND(MIN(D$50:D$65)<0,MAX(D$50:D$65)>0),IRR(D$50:D$65))) -> 0.036353151 | E49: =IF(OR(E$48="",E$48=0),"",IF(AND(MIN(E$50:E$65)<0,MAX(E$50:E$65)>0),IRR(E$50:E$65))) -> 0.05287331 | F49: =IF(OR(F$48="",F$48=0),"",IF(AND(MIN(F$50:F$65)<0,MAX(F$50:F$65)>0),IRR(F$50:F$65))) -> 0.061797984 | G49: =IF(OR(G$48="",G$48=0),"",IF(AND(MIN(G$50:G$65)<0,MAX(G$50:G$65)>0),IRR(G$50:G$65))) -> 0.062874554 | H49: =IF(OR(H$48="",H$48=0),"",IF(AND(MIN(H$50:H$65)<0,MAX(H$50:H$65)>0),IRR(H$50:H$65))) -> 0.063589214 | I49: =IF(OR(I$48="",I$48=0),"",IF(AND(MIN(I$50:I$65)<0,MAX(I$50:I$65)>0),IRR(I$50:I$65))) -> 0.06412065 | J49: =IF(OR(J$48="",J$48=0),"",IF(AND(MIN(J$50:J$65)<0,MAX(J$50:J$65)>0),IRR(J$50:J$65))) -> 0.064545229 | K49: =IF(OR(K$48="",K$48=0),"",IF(AND(MIN(K$50:K$65)<0,MAX(K$50:K$65)>0),IRR(K$50:K$65))) -> 0.064901085 | ... R49: =IF(OR(R$48="",R$48=0),"",IF(AND(MIN(R$50:R$65)<0,MAX(R$50:R$65)>0),IRR(R$50:R$65))) -> 0.066536708
C50: 0 | D50: =IF(OR(D$48="",D$48=0),"",-Basis) -> -35928792 | E50: =IF(OR(E$48="",E$48=0),"",-Basis) -> -35928792 | F50: =IF(OR(F$48="",F$48=0),"",-Basis) -> -35928792 | G50: =IF(OR(G$48="",G$48=0),"",-Basis) -> -35928792 | H50: =IF(OR(H$48="",H$48=0),"",-Basis) -> -35928792 | I50: =IF(OR(I$48="",I$48=0),"",-Basis) -> -35928792 | J50: =IF(OR(J$48="",J$48=0),"",-Basis) -> -35928792 | K50: =IF(OR(K$48="",K$48=0),"",-Basis) -> -35928792 | ... R50: =IF(OR(R$48="",R$48=0),"",-Basis) -> -35928792
C51: =C50+1 -> 1 | D51: =IF($C51>D$48,"",IF(OR(D$48="",D$48=0),"",IF(D$48=$C51,OFFSET($D$16,0,$C50)+OFFSET($D$13,0,$C50),OFFSET($D$16,0,$C50)))) -> 37234917 | E51: =IF($C51>E$48,"",IF(OR(E$48="",E$48=0),"",IF(E$48=$C51,OFFSET($D$16,0,$C50)+OFFSET($D$13,0,$C50),OFFSET($D$16,0,$C50)))) -> 1852647.5 | F51: =IF($C51>F$48,"",IF(OR(F$48="",F$48=0),"",IF(F$48=$C51,OFFSET($D$16,0,$C50)+OFFSET($D$13,0,$C50),OFFSET($D$16,0,$C50)))) -> 1852647.5 | G51: =IF($C51>G$48,"",IF(OR(G$48="",G$48=0),"",IF(G$48=$C51,OFFSET($D$16,0,$C50)+OFFSET($D$13,0,$C50),OFFSET($D$16,0,$C50)))) -> 1852647.5 | H51: =IF($C51>H$48,"",IF(OR(H$48="",H$48=0),"",IF(H$48=$C51,OFFSET($D$16,0,$C50)+OFFSET($D$13,0,$C50),OFFSET($D$16,0,$C50)))) -> 1852647.5 | I51: =IF($C51>I$48,"",IF(OR(I$48="",I$48=0),"",IF(I$48=$C51,OFFSET($D$16,0,$C50)+OFFSET($D$13,0,$C50),OFFSET($D$16,0,$C50)))) -> 1852647.5 | J51: =IF($C51>J$48,"",IF(OR(J$48="",J$48=0),"",IF(J$48=$C51,OFFSET($D$16,0,$C50)+OFFSET($D$13,0,$C50),OFFSET($D$16,0,$C50)))) -> 1852647.5 | K51: =IF($C51>K$48,"",IF(OR(K$48="",K$48=0),"",IF(K$48=$C51,OFFSET($D$16,0,$C50)+OFFSET($D$13,0,$C50),OFFSET($D$16,0,$C50)))) -> 1852647.5 | ... R51: =IF($C51>R$48,"",IF(OR(R$48="",R$48=0),"",IF(R$48=$C51,OFFSET($D$16,0,$C50)+OFFSET($D$13,0,$C50),OFFSET($D$16,0,$C50)))) -> 1852647.5
C52: =C51+1 -> 2 | D52: =IF($C52>D$48,"",IF(OR(D$48="",D$48=0),"",IF(D$48=$C52,OFFSET($D$16,0,$C51)+OFFSET($D$13,0,$C51),OFFSET($D$16,0,$C51)))) | E52: =IF($C52>E$48,"",IF(OR(E$48="",E$48=0),"",IF(E$48=$C52,OFFSET($D$16,0,$C51)+OFFSET($D$13,0,$C51),OFFSET($D$16,0,$C51)))) -> 37877979 | F52: =IF($C52>F$48,"",IF(OR(F$48="",F$48=0),"",IF(F$48=$C52,OFFSET($D$16,0,$C51)+OFFSET($D$13,0,$C51),OFFSET($D$16,0,$C51)))) -> 2032346.9 | G52: =IF($C52>G$48,"",IF(OR(G$48="",G$48=0),"",IF(G$48=$C52,OFFSET($D$16,0,$C51)+OFFSET($D$13,0,$C51),OFFSET($D$16,0,$C51)))) -> 2032346.9 | H52: =IF($C52>H$48,"",IF(OR(H$48="",H$48=0),"",IF(H$48=$C52,OFFSET($D$16,0,$C51)+OFFSET($D$13,0,$C51),OFFSET($D$16,0,$C51)))) -> 2032346.9 | I52: =IF($C52>I$48,"",IF(OR(I$48="",I$48=0),"",IF(I$48=$C52,OFFSET($D$16,0,$C51)+OFFSET($D$13,0,$C51),OFFSET($D$16,0,$C51)))) -> 2032346.9 | J52: =IF($C52>J$48,"",IF(OR(J$48="",J$48=0),"",IF(J$48=$C52,OFFSET($D$16,0,$C51)+OFFSET($D$13,0,$C51),OFFSET($D$16,0,$C51)))) -> 2032346.9 | K52: =IF($C52>K$48,"",IF(OR(K$48="",K$48=0),"",IF(K$48=$C52,OFFSET($D$16,0,$C51)+OFFSET($D$13,0,$C51),OFFSET($D$16,0,$C51)))) -> 2032346.9 | ... R52: =IF($C52>R$48,"",IF(OR(R$48="",R$48=0),"",IF(R$48=$C52,OFFSET($D$16,0,$C51)+OFFSET($D$13,0,$C51),OFFSET($D$16,0,$C51)))) -> 2032346.9
C53: =C52+1 -> 3 | D53: =IF($C53>D$48,"",IF(OR(D$48="",D$48=0),"",IF(D$48=$C53,OFFSET($D$16,0,$C52)+OFFSET($D$13,0,$C52),OFFSET($D$16,0,$C52)))) | E53: =IF($C53>E$48,"",IF(OR(E$48="",E$48=0),"",IF(E$48=$C53,OFFSET($D$16,0,$C52)+OFFSET($D$13,0,$C52),OFFSET($D$16,0,$C52)))) | F53: =IF($C53>F$48,"",IF(OR(F$48="",F$48=0),"",IF(F$48=$C53,OFFSET($D$16,0,$C52)+OFFSET($D$13,0,$C52),OFFSET($D$16,0,$C52)))) -> 38763243 | G53: =IF($C53>G$48,"",IF(OR(G$48="",G$48=0),"",IF(G$48=$C53,OFFSET($D$16,0,$C52)+OFFSET($D$13,0,$C52),OFFSET($D$16,0,$C52)))) -> 2288952.2 | H53: =IF($C53>H$48,"",IF(OR(H$48="",H$48=0),"",IF(H$48=$C53,OFFSET($D$16,0,$C52)+OFFSET($D$13,0,$C52),OFFSET($D$16,0,$C52)))) -> 2288952.2 | I53: =IF($C53>I$48,"",IF(OR(I$48="",I$48=0),"",IF(I$48=$C53,OFFSET($D$16,0,$C52)+OFFSET($D$13,0,$C52),OFFSET($D$16,0,$C52)))) -> 2288952.2 | J53: =IF($C53>J$48,"",IF(OR(J$48="",J$48=0),"",IF(J$48=$C53,OFFSET($D$16,0,$C52)+OFFSET($D$13,0,$C52),OFFSET($D$16,0,$C52)))) -> 2288952.2 | K53: =IF($C53>K$48,"",IF(OR(K$48="",K$48=0),"",IF(K$48=$C53,OFFSET($D$16,0,$C52)+OFFSET($D$13,0,$C52),OFFSET($D$16,0,$C52)))) -> 2288952.2 | ... R53: =IF($C53>R$48,"",IF(OR(R$48="",R$48=0),"",IF(R$48=$C53,OFFSET($D$16,0,$C52)+OFFSET($D$13,0,$C52),OFFSET($D$16,0,$C52)))) -> 2288952.2
C54: =C53+1 -> 4 | D54: =IF($C54>D$48,"",IF(OR(D$48="",D$48=0),"",IF(D$48=$C54,OFFSET($D$16,0,$C53)+OFFSET($D$13,0,$C53),OFFSET($D$16,0,$C53)))) | E54: =IF($C54>E$48,"",IF(OR(E$48="",E$48=0),"",IF(E$48=$C54,OFFSET($D$16,0,$C53)+OFFSET($D$13,0,$C53),OFFSET($D$16,0,$C53)))) | F54: =IF($C54>F$48,"",IF(OR(F$48="",F$48=0),"",IF(F$48=$C54,OFFSET($D$16,0,$C53)+OFFSET($D$13,0,$C53),OFFSET($D$16,0,$C53)))) | G54: =IF($C54>G$48,"",IF(OR(G$48="",G$48=0),"",IF(G$48=$C54,OFFSET($D$16,0,$C53)+OFFSET($D$13,0,$C53),OFFSET($D$16,0,$C53)))) -> 38899957 | H54: =IF($C54>H$48,"",IF(OR(H$48="",H$48=0),"",IF(H$48=$C54,OFFSET($D$16,0,$C53)+OFFSET($D$13,0,$C53),OFFSET($D$16,0,$C53)))) -> 2311878.6 | I54: =IF($C54>I$48,"",IF(OR(I$48="",I$48=0),"",IF(I$48=$C54,OFFSET($D$16,0,$C53)+OFFSET($D$13,0,$C53),OFFSET($D$16,0,$C53)))) -> 2311878.6 | J54: =IF($C54>J$48,"",IF(OR(J$48="",J$48=0),"",IF(J$48=$C54,OFFSET($D$16,0,$C53)+OFFSET($D$13,0,$C53),OFFSET($D$16,0,$C53)))) -> 2311878.6 | K54: =IF($C54>K$48,"",IF(OR(K$48="",K$48=0),"",IF(K$48=$C54,OFFSET($D$16,0,$C53)+OFFSET($D$13,0,$C53),OFFSET($D$16,0,$C53)))) -> 2311878.6 | ... R54: =IF($C54>R$48,"",IF(OR(R$48="",R$48=0),"",IF(R$48=$C54,OFFSET($D$16,0,$C53)+OFFSET($D$13,0,$C53),OFFSET($D$16,0,$C53)))) -> 2311878.6
C55: =C54+1 -> 5 | D55: =IF($C55>D$48,"",IF(OR(D$48="",D$48=0),"",IF(D$48=$C55,OFFSET($D$16,0,$C54)+OFFSET($D$13,0,$C54),OFFSET($D$16,0,$C54)))) | E55: =IF($C55>E$48,"",IF(OR(E$48="",E$48=0),"",IF(E$48=$C55,OFFSET($D$16,0,$C54)+OFFSET($D$13,0,$C54),OFFSET($D$16,0,$C54)))) | F55: =IF($C55>F$48,"",IF(OR(F$48="",F$48=0),"",IF(F$48=$C55,OFFSET($D$16,0,$C54)+OFFSET($D$13,0,$C54),OFFSET($D$16,0,$C54)))) | G55: =IF($C55>G$48,"",IF(OR(G$48="",G$48=0),"",IF(G$48=$C55,OFFSET($D$16,0,$C54)+OFFSET($D$13,0,$C54),OFFSET($D$16,0,$C54)))) | H55: =IF($C55>H$48,"",IF(OR(H$48="",H$48=0),"",IF(H$48=$C55,OFFSET($D$16,0,$C54)+OFFSET($D$13,0,$C54),OFFSET($D$16,0,$C54)))) -> 39036184 | I55: =IF($C55>I$48,"",IF(OR(I$48="",I$48=0),"",IF(I$48=$C55,OFFSET($D$16,0,$C54)+OFFSET($D$13,0,$C54),OFFSET($D$16,0,$C54)))) -> 2334815.1 | J55: =IF($C55>J$48,"",IF(OR(J$48="",J$48=0),"",IF(J$48=$C55,OFFSET($D$16,0,$C54)+OFFSET($D$13,0,$C54),OFFSET($D$16,0,$C54)))) -> 2334815.1 | K55: =IF($C55>K$48,"",IF(OR(K$48="",K$48=0),"",IF(K$48=$C55,OFFSET($D$16,0,$C54)+OFFSET($D$13,0,$C54),OFFSET($D$16,0,$C54)))) -> 2334815.1 | ... R55: =IF($C55>R$48,"",IF(OR(R$48="",R$48=0),"",IF(R$48=$C55,OFFSET($D$16,0,$C54)+OFFSET($D$13,0,$C54),OFFSET($D$16,0,$C54)))) -> 2334815.1
C56: =C55+1 -> 6 | D56: =IF($C56>D$48,"",IF(OR(D$48="",D$48=0),"",IF(D$48=$C56,OFFSET($D$16,0,$C55)+OFFSET($D$13,0,$C55),OFFSET($D$16,0,$C55)))) | E56: =IF($C56>E$48,"",IF(OR(E$48="",E$48=0),"",IF(E$48=$C56,OFFSET($D$16,0,$C55)+OFFSET($D$13,0,$C55),OFFSET($D$16,0,$C55)))) | F56: =IF($C56>F$48,"",IF(OR(F$48="",F$48=0),"",IF(F$48=$C56,OFFSET($D$16,0,$C55)+OFFSET($D$13,0,$C55),OFFSET($D$16,0,$C55)))) | G56: =IF($C56>G$48,"",IF(OR(G$48="",G$48=0),"",IF(G$48=$C56,OFFSET($D$16,0,$C55)+OFFSET($D$13,0,$C55),OFFSET($D$16,0,$C55)))) | H56: =IF($C56>H$48,"",IF(OR(H$48="",H$48=0),"",IF(H$48=$C56,OFFSET($D$16,0,$C55)+OFFSET($D$13,0,$C55),OFFSET($D$16,0,$C55)))) | I56: =IF($C56>I$48,"",IF(OR(I$48="",I$48=0),"",IF(I$48=$C56,OFFSET($D$16,0,$C55)+OFFSET($D$13,0,$C55),OFFSET($D$16,0,$C55)))) -> 39171806 | J56: =IF($C56>J$48,"",IF(OR(J$48="",J$48=0),"",IF(J$48=$C56,OFFSET($D$16,0,$C55)+OFFSET($D$13,0,$C55),OFFSET($D$16,0,$C55)))) -> 2357752.1 | K56: =IF($C56>K$48,"",IF(OR(K$48="",K$48=0),"",IF(K$48=$C56,OFFSET($D$16,0,$C55)+OFFSET($D$13,0,$C55),OFFSET($D$16,0,$C55)))) -> 2357752.1 | ... R56: =IF($C56>R$48,"",IF(OR(R$48="",R$48=0),"",IF(R$48=$C56,OFFSET($D$16,0,$C55)+OFFSET($D$13,0,$C55),OFFSET($D$16,0,$C55)))) -> 2357752.1
C57: =C56+1 -> 7 | D57: =IF($C57>D$48,"",IF(OR(D$48="",D$48=0),"",IF(D$48=$C57,OFFSET($D$16,0,$C56)+OFFSET($D$13,0,$C56),OFFSET($D$16,0,$C56)))) | E57: =IF($C57>E$48,"",IF(OR(E$48="",E$48=0),"",IF(E$48=$C57,OFFSET($D$16,0,$C56)+OFFSET($D$13,0,$C56),OFFSET($D$16,0,$C56)))) | F57: =IF($C57>F$48,"",IF(OR(F$48="",F$48=0),"",IF(F$48=$C57,OFFSET($D$16,0,$C56)+OFFSET($D$13,0,$C56),OFFSET($D$16,0,$C56)))) | G57: =IF($C57>G$48,"",IF(OR(G$48="",G$48=0),"",IF(G$48=$C57,OFFSET($D$16,0,$C56)+OFFSET($D$13,0,$C56),OFFSET($D$16,0,$C56)))) | H57: =IF($C57>H$48,"",IF(OR(H$48="",H$48=0),"",IF(H$48=$C57,OFFSET($D$16,0,$C56)+OFFSET($D$13,0,$C56),OFFSET($D$16,0,$C56)))) | I57: =IF($C57>I$48,"",IF(OR(I$48="",I$48=0),"",IF(I$48=$C57,OFFSET($D$16,0,$C56)+OFFSET($D$13,0,$C56),OFFSET($D$16,0,$C56)))) | J57: =IF($C57>J$48,"",IF(OR(J$48="",J$48=0),"",IF(J$48=$C57,OFFSET($D$16,0,$C56)+OFFSET($D$13,0,$C56),OFFSET($D$16,0,$C56)))) -> 39306705 | K57: =IF($C57>K$48,"",IF(OR(K$48="",K$48=0),"",IF(K$48=$C57,OFFSET($D$16,0,$C56)+OFFSET($D$13,0,$C56),OFFSET($D$16,0,$C56)))) -> 2380679.4 | ... R57: =IF($C57>R$48,"",IF(OR(R$48="",R$48=0),"",IF(R$48=$C57,OFFSET($D$16,0,$C56)+OFFSET($D$13,0,$C56),OFFSET($D$16,0,$C56)))) -> 2380679.4
C58: =C57+1 -> 8 | D58: =IF($C58>D$48,"",IF(OR(D$48="",D$48=0),"",IF(D$48=$C58,OFFSET($D$16,0,$C57)+OFFSET($D$13,0,$C57),OFFSET($D$16,0,$C57)))) | E58: =IF($C58>E$48,"",IF(OR(E$48="",E$48=0),"",IF(E$48=$C58,OFFSET($D$16,0,$C57)+OFFSET($D$13,0,$C57),OFFSET($D$16,0,$C57)))) | F58: =IF($C58>F$48,"",IF(OR(F$48="",F$48=0),"",IF(F$48=$C58,OFFSET($D$16,0,$C57)+OFFSET($D$13,0,$C57),OFFSET($D$16,0,$C57)))) | G58: =IF($C58>G$48,"",IF(OR(G$48="",G$48=0),"",IF(G$48=$C58,OFFSET($D$16,0,$C57)+OFFSET($D$13,0,$C57),OFFSET($D$16,0,$C57)))) | H58: =IF($C58>H$48,"",IF(OR(H$48="",H$48=0),"",IF(H$48=$C58,OFFSET($D$16,0,$C57)+OFFSET($D$13,0,$C57),OFFSET($D$16,0,$C57)))) | I58: =IF($C58>I$48,"",IF(OR(I$48="",I$48=0),"",IF(I$48=$C58,OFFSET($D$16,0,$C57)+OFFSET($D$13,0,$C57),OFFSET($D$16,0,$C57)))) | J58: =IF($C58>J$48,"",IF(OR(J$48="",J$48=0),"",IF(J$48=$C58,OFFSET($D$16,0,$C57)+OFFSET($D$13,0,$C57),OFFSET($D$16,0,$C57)))) | K58: =IF($C58>K$48,"",IF(OR(K$48="",K$48=0),"",IF(K$48=$C58,OFFSET($D$16,0,$C57)+OFFSET($D$13,0,$C57),OFFSET($D$16,0,$C57)))) -> 39440756 | ... R58: =IF($C58>R$48,"",IF(OR(R$48="",R$48=0),"",IF(R$48=$C58,OFFSET($D$16,0,$C57)+OFFSET($D$13,0,$C57),OFFSET($D$16,0,$C57)))) -> 2403586.4
C59: =C58+1 -> 9 | D59: =IF($C59>D$48,"",IF(OR(D$48="",D$48=0),"",IF(D$48=$C59,OFFSET($D$16,0,$C58)+OFFSET($D$13,0,$C58),OFFSET($D$16,0,$C58)))) | E59: =IF($C59>E$48,"",IF(OR(E$48="",E$48=0),"",IF(E$48=$C59,OFFSET($D$16,0,$C58)+OFFSET($D$13,0,$C58),OFFSET($D$16,0,$C58)))) | F59: =IF($C59>F$48,"",IF(OR(F$48="",F$48=0),"",IF(F$48=$C59,OFFSET($D$16,0,$C58)+OFFSET($D$13,0,$C58),OFFSET($D$16,0,$C58)))) | G59: =IF($C59>G$48,"",IF(OR(G$48="",G$48=0),"",IF(G$48=$C59,OFFSET($D$16,0,$C58)+OFFSET($D$13,0,$C58),OFFSET($D$16,0,$C58)))) | H59: =IF($C59>H$48,"",IF(OR(H$48="",H$48=0),"",IF(H$48=$C59,OFFSET($D$16,0,$C58)+OFFSET($D$13,0,$C58),OFFSET($D$16,0,$C58)))) | I59: =IF($C59>I$48,"",IF(OR(I$48="",I$48=0),"",IF(I$48=$C59,OFFSET($D$16,0,$C58)+OFFSET($D$13,0,$C58),OFFSET($D$16,0,$C58)))) | J59: =IF($C59>J$48,"",IF(OR(J$48="",J$48=0),"",IF(J$48=$C59,OFFSET($D$16,0,$C58)+OFFSET($D$13,0,$C58),OFFSET($D$16,0,$C58)))) | K59: =IF($C59>K$48,"",IF(OR(K$48="",K$48=0),"",IF(K$48=$C59,OFFSET($D$16,0,$C58)+OFFSET($D$13,0,$C58),OFFSET($D$16,0,$C58)))) | ... R59: =IF($C59>R$48,"",IF(OR(R$48="",R$48=0),"",IF(R$48=$C59,OFFSET($D$16,0,$C58)+OFFSET($D$13,0,$C58),OFFSET($D$16,0,$C58)))) -> 2426462.1
C60: =C59+1 -> 10 | D60: =IF($C60>D$48,"",IF(OR(D$48="",D$48=0),"",IF(D$48=$C60,OFFSET($D$16,0,$C59)+OFFSET($D$13,0,$C59),OFFSET($D$16,0,$C59)))) | E60: =IF($C60>E$48,"",IF(OR(E$48="",E$48=0),"",IF(E$48=$C60,OFFSET($D$16,0,$C59)+OFFSET($D$13,0,$C59),OFFSET($D$16,0,$C59)))) | F60: =IF($C60>F$48,"",IF(OR(F$48="",F$48=0),"",IF(F$48=$C60,OFFSET($D$16,0,$C59)+OFFSET($D$13,0,$C59),OFFSET($D$16,0,$C59)))) | G60: =IF($C60>G$48,"",IF(OR(G$48="",G$48=0),"",IF(G$48=$C60,OFFSET($D$16,0,$C59)+OFFSET($D$13,0,$C59),OFFSET($D$16,0,$C59)))) | H60: =IF($C60>H$48,"",IF(OR(H$48="",H$48=0),"",IF(H$48=$C60,OFFSET($D$16,0,$C59)+OFFSET($D$13,0,$C59),OFFSET($D$16,0,$C59)))) | I60: =IF($C60>I$48,"",IF(OR(I$48="",I$48=0),"",IF(I$48=$C60,OFFSET($D$16,0,$C59)+OFFSET($D$13,0,$C59),OFFSET($D$16,0,$C59)))) | J60: =IF($C60>J$48,"",IF(OR(J$48="",J$48=0),"",IF(J$48=$C60,OFFSET($D$16,0,$C59)+OFFSET($D$13,0,$C59),OFFSET($D$16,0,$C59)))) | K60: =IF($C60>K$48,"",IF(OR(K$48="",K$48=0),"",IF(K$48=$C60,OFFSET($D$16,0,$C59)+OFFSET($D$13,0,$C59),OFFSET($D$16,0,$C59)))) | ... R60: =IF($C60>R$48,"",IF(OR(R$48="",R$48=0),"",IF(R$48=$C60,OFFSET($D$16,0,$C59)+OFFSET($D$13,0,$C59),OFFSET($D$16,0,$C59)))) -> 2449294.9
C61: =C60+1 -> 11 | D61: =IF($C61>D$48,"",IF(OR(D$48="",D$48=0),"",IF(D$48=$C61,OFFSET($D$16,0,$C60)+OFFSET($D$13,0,$C60),OFFSET($D$16,0,$C60)))) | E61: =IF($C61>E$48,"",IF(OR(E$48="",E$48=0),"",IF(E$48=$C61,OFFSET($D$16,0,$C60)+OFFSET($D$13,0,$C60),OFFSET($D$16,0,$C60)))) | F61: =IF($C61>F$48,"",IF(OR(F$48="",F$48=0),"",IF(F$48=$C61,OFFSET($D$16,0,$C60)+OFFSET($D$13,0,$C60),OFFSET($D$16,0,$C60)))) | G61: =IF($C61>G$48,"",IF(OR(G$48="",G$48=0),"",IF(G$48=$C61,OFFSET($D$16,0,$C60)+OFFSET($D$13,0,$C60),OFFSET($D$16,0,$C60)))) | H61: =IF($C61>H$48,"",IF(OR(H$48="",H$48=0),"",IF(H$48=$C61,OFFSET($D$16,0,$C60)+OFFSET($D$13,0,$C60),OFFSET($D$16,0,$C60)))) | I61: =IF($C61>I$48,"",IF(OR(I$48="",I$48=0),"",IF(I$48=$C61,OFFSET($D$16,0,$C60)+OFFSET($D$13,0,$C60),OFFSET($D$16,0,$C60)))) | J61: =IF($C61>J$48,"",IF(OR(J$48="",J$48=0),"",IF(J$48=$C61,OFFSET($D$16,0,$C60)+OFFSET($D$13,0,$C60),OFFSET($D$16,0,$C60)))) | K61: =IF($C61>K$48,"",IF(OR(K$48="",K$48=0),"",IF(K$48=$C61,OFFSET($D$16,0,$C60)+OFFSET($D$13,0,$C60),OFFSET($D$16,0,$C60)))) | ... R61: =IF($C61>R$48,"",IF(OR(R$48="",R$48=0),"",IF(R$48=$C61,OFFSET($D$16,0,$C60)+OFFSET($D$13,0,$C60),OFFSET($D$16,0,$C60)))) -> 2472072.8
C62: =C61+1 -> 12 | D62: =IF($C62>D$48,"",IF(OR(D$48="",D$48=0),"",IF(D$48=$C62,OFFSET($D$16,0,$C61)+OFFSET($D$13,0,$C61),OFFSET($D$16,0,$C61)))) | E62: =IF($C62>E$48,"",IF(OR(E$48="",E$48=0),"",IF(E$48=$C62,OFFSET($D$16,0,$C61)+OFFSET($D$13,0,$C61),OFFSET($D$16,0,$C61)))) | F62: =IF($C62>F$48,"",IF(OR(F$48="",F$48=0),"",IF(F$48=$C62,OFFSET($D$16,0,$C61)+OFFSET($D$13,0,$C61),OFFSET($D$16,0,$C61)))) | G62: =IF($C62>G$48,"",IF(OR(G$48="",G$48=0),"",IF(G$48=$C62,OFFSET($D$16,0,$C61)+OFFSET($D$13,0,$C61),OFFSET($D$16,0,$C61)))) | H62: =IF($C62>H$48,"",IF(OR(H$48="",H$48=0),"",IF(H$48=$C62,OFFSET($D$16,0,$C61)+OFFSET($D$13,0,$C61),OFFSET($D$16,0,$C61)))) | I62: =IF($C62>I$48,"",IF(OR(I$48="",I$48=0),"",IF(I$48=$C62,OFFSET($D$16,0,$C61)+OFFSET($D$13,0,$C61),OFFSET($D$16,0,$C61)))) | J62: =IF($C62>J$48,"",IF(OR(J$48="",J$48=0),"",IF(J$48=$C62,OFFSET($D$16,0,$C61)+OFFSET($D$13,0,$C61),OFFSET($D$16,0,$C61)))) | K62: =IF($C62>K$48,"",IF(OR(K$48="",K$48=0),"",IF(K$48=$C62,OFFSET($D$16,0,$C61)+OFFSET($D$13,0,$C61),OFFSET($D$16,0,$C61)))) | ... R62: =IF($C62>R$48,"",IF(OR(R$48="",R$48=0),"",IF(R$48=$C62,OFFSET($D$16,0,$C61)+OFFSET($D$13,0,$C61),OFFSET($D$16,0,$C61)))) -> 2494783.3
... C65: =C64+1 -> 15 | D65: =IF($C65>D$48,"",IF(OR(D$48="",D$48=0),"",IF(D$48=$C65,OFFSET($D$16,0,$C64)+OFFSET($D$13,0,$C64),OFFSET($D$16,0,$C64)))) | E65: =IF($C65>E$48,"",IF(OR(E$48="",E$48=0),"",IF(E$48=$C65,OFFSET($D$16,0,$C64)+OFFSET($D$13,0,$C64),OFFSET($D$16,0,$C64)))) | F65: =IF($C65>F$48,"",IF(OR(F$48="",F$48=0),"",IF(F$48=$C65,OFFSET($D$16,0,$C64)+OFFSET($D$13,0,$C64),OFFSET($D$16,0,$C64)))) | G65: =IF($C65>G$48,"",IF(OR(G$48="",G$48=0),"",IF(G$48=$C65,OFFSET($D$16,0,$C64)+OFFSET($D$13,0,$C64),OFFSET($D$16,0,$C64)))) | H65: =IF($C65>H$48,"",IF(OR(H$48="",H$48=0),"",IF(H$48=$C65,OFFSET($D$16,0,$C64)+OFFSET($D$13,0,$C64),OFFSET($D$16,0,$C64)))) | I65: =IF($C65>I$48,"",IF(OR(I$48="",I$48=0),"",IF(I$48=$C65,OFFSET($D$16,0,$C64)+OFFSET($D$13,0,$C64),OFFSET($D$16,0,$C64)))) | J65: =IF($C65>J$48,"",IF(OR(J$48="",J$48=0),"",IF(J$48=$C65,OFFSET($D$16,0,$C64)+OFFSET($D$13,0,$C64),OFFSET($D$16,0,$C64)))) | K65: =IF($C65>K$48,"",IF(OR(K$48="",K$48=0),"",IF(K$48=$C65,OFFSET($D$16,0,$C64)+OFFSET($D$13,0,$C64),OFFSET($D$16,0,$C64)))) | ... R65: =IF($C65>R$48,"",IF(OR(R$48="",R$48=0),"",IF(R$48=$C65,OFFSET($D$16,0,$C64)+OFFSET($D$13,0,$C64),OFFSET($D$16,0,$C64)))) -> 40344342
B67: Levered
C68: Year | D68: =IF(OR(D$13="",D$13=0),"",D$4) -> 1 | E68: =IF(OR(E$13="",E$13=0),"",E$4) -> 2 | F68: =IF(OR(F$13="",F$13=0),"",F$4) -> 3 | G68: =IF(OR(G$13="",G$13=0),"",G$4) -> 4 | H68: =IF(OR(H$13="",H$13=0),"",H$4) -> 5 | I68: =IF(OR(I$13="",I$13=0),"",I$4) -> 6 | J68: =IF(OR(J$13="",J$13=0),"",J$4) -> 7 | K68: =IF(OR(K$13="",K$13=0),"",K$4) -> 8 | ... R68: =IF(OR(R$13="",R$13=0),"",R$4) -> 15
C69: IRR | D69: =IF(OR(D$48="",D$48=0),"",IF(AND(MIN(D$70:D$85)<0,MAX(D$70:D$85)>0),IRR(D$70:D$85),"-")) -> -0.94701948 | E69: =IF(OR(E$48="",E$48=0),"",IF(AND(MIN(E$70:E$85)<0,MAX(E$70:E$85)>0),IRR(E$70:E$85),"-")) -> -0.046767434 | F69: =IF(OR(F$48="",F$48=0),"",IF(AND(MIN(F$70:F$85)<0,MAX(F$70:F$85)>0),IRR(F$70:F$85),"-")) -> 0.51634898 | G69: =IF(OR(G$48="",G$48=0),"",IF(AND(MIN(G$70:G$85)<0,MAX(G$70:G$85)>0),IRR(G$70:G$85),"-")) -> 0.73145868 | H69: =IF(OR(H$48="",H$48=0),"",IF(AND(MIN(H$70:H$85)<0,MAX(H$70:H$85)>0),IRR(H$70:H$85),"-")) -> 0.82159013 | I69: =IF(OR(I$48="",I$48=0),"",IF(AND(MIN(I$70:I$85)<0,MAX(I$70:I$85)>0),IRR(I$70:I$85),"-")) -> 0.86261375 | J69: =IF(OR(J$48="",J$48=0),"",IF(AND(MIN(J$70:J$85)<0,MAX(J$70:J$85)>0),IRR(J$70:J$85),"-")) -> 0.88234595 | K69: =IF(OR(K$48="",K$48=0),"",IF(AND(MIN(K$70:K$85)<0,MAX(K$70:K$85)>0),IRR(K$70:K$85),"-")) -> 0.89218105 | ... R69: =IF(OR(R$48="",R$48=0),"",IF(AND(MIN(R$70:R$85)<0,MAX(R$70:R$85)>0),IRR(R$70:R$85),"-")) -> 0.90252903
C70: 0 | D70: =IF(OR(D$48="",D$48=0),"",-Initial_Equity) -> -19658792 | E70: =IF(OR(E$48="",E$48=0),"",-Initial_Equity) -> -19658792 | F70: =IF(OR(F$48="",F$48=0),"",-Initial_Equity) -> -19658792 | G70: =IF(OR(G$48="",G$48=0),"",-Initial_Equity) -> -19658792 | H70: =IF(OR(H$48="",H$48=0),"",-Initial_Equity) -> -19658792 | I70: =IF(OR(I$48="",I$48=0),"",-Initial_Equity) -> -19658792 | J70: =IF(OR(J$48="",J$48=0),"",-Initial_Equity) -> -19658792 | K70: =IF(OR(K$48="",K$48=0),"",-Initial_Equity) -> -19658792 | ... R70: =IF(OR(R$48="",R$48=0),"",-Initial_Equity) -> -19658792
C71: =C70+1 -> 1 | D71: =IF($C71>D$48,"",IF(OR(D$48="",D$48=0),"",IF(D$48=$C71,OFFSET($D$35,0,$C70)+OFFSET($D$35,0,$C70),OFFSET($D$32,0,$C70)))) -> 1041533 | E71: =IF($C71>E$48,"",IF(OR(E$48="",E$48=0),"",IF(E$48=$C71,OFFSET($D$35,0,$C70)+OFFSET($D$35,0,$C70),OFFSET($D$32,0,$C70)))) -> 17269736 | F71: =IF($C71>F$48,"",IF(OR(F$48="",F$48=0),"",IF(F$48=$C71,OFFSET($D$35,0,$C70)+OFFSET($D$35,0,$C70),OFFSET($D$32,0,$C70)))) -> 17269736 | G71: =IF($C71>G$48,"",IF(OR(G$48="",G$48=0),"",IF(G$48=$C71,OFFSET($D$35,0,$C70)+OFFSET($D$35,0,$C70),OFFSET($D$32,0,$C70)))) -> 17269736 | H71: =IF($C71>H$48,"",IF(OR(H$48="",H$48=0),"",IF(H$48=$C71,OFFSET($D$35,0,$C70)+OFFSET($D$35,0,$C70),OFFSET($D$32,0,$C70)))) -> 17269736 | I71: =IF($C71>I$48,"",IF(OR(I$48="",I$48=0),"",IF(I$48=$C71,OFFSET($D$35,0,$C70)+OFFSET($D$35,0,$C70),OFFSET($D$32,0,$C70)))) -> 17269736 | J71: =IF($C71>J$48,"",IF(OR(J$48="",J$48=0),"",IF(J$48=$C71,OFFSET($D$35,0,$C70)+OFFSET($D$35,0,$C70),OFFSET($D$32,0,$C70)))) -> 17269736 | K71: =IF($C71>K$48,"",IF(OR(K$48="",K$48=0),"",IF(K$48=$C71,OFFSET($D$35,0,$C70)+OFFSET($D$35,0,$C70),OFFSET($D$32,0,$C70)))) -> 17269736 | ... R71: =IF($C71>R$48,"",IF(OR(R$48="",R$48=0),"",IF(R$48=$C71,OFFSET($D$35,0,$C70)+OFFSET($D$35,0,$C70),OFFSET($D$32,0,$C70)))) -> 17269736
C72: =C71+1 -> 2 | D72: =IF($C72>D$48,"",IF(OR(D$48="",D$48=0),"",IF(D$48=$C72,OFFSET($D$35,0,$C71)+OFFSET($D$35,0,$C71),OFFSET($D$32,0,$C71)))) | E72: =IF($C72>E$48,"",IF(OR(E$48="",E$48=0),"",IF(E$48=$C72,OFFSET($D$35,0,$C71)+OFFSET($D$35,0,$C71),OFFSET($D$32,0,$C71)))) -> 1400931.9 | F72: =IF($C72>F$48,"",IF(OR(F$48="",F$48=0),"",IF(F$48=$C72,OFFSET($D$35,0,$C71)+OFFSET($D$35,0,$C71),OFFSET($D$32,0,$C71)))) -> 17752456 | G72: =IF($C72>G$48,"",IF(OR(G$48="",G$48=0),"",IF(G$48=$C72,OFFSET($D$35,0,$C71)+OFFSET($D$35,0,$C71),OFFSET($D$32,0,$C71)))) -> 17752456 | H72: =IF($C72>H$48,"",IF(OR(H$48="",H$48=0),"",IF(H$48=$C72,OFFSET($D$35,0,$C71)+OFFSET($D$35,0,$C71),OFFSET($D$32,0,$C71)))) -> 17752456 | I72: =IF($C72>I$48,"",IF(OR(I$48="",I$48=0),"",IF(I$48=$C72,OFFSET($D$35,0,$C71)+OFFSET($D$35,0,$C71),OFFSET($D$32,0,$C71)))) -> 17752456 | J72: =IF($C72>J$48,"",IF(OR(J$48="",J$48=0),"",IF(J$48=$C72,OFFSET($D$35,0,$C71)+OFFSET($D$35,0,$C71),OFFSET($D$32,0,$C71)))) -> 17752456 | K72: =IF($C72>K$48,"",IF(OR(K$48="",K$48=0),"",IF(K$48=$C72,OFFSET($D$35,0,$C71)+OFFSET($D$35,0,$C71),OFFSET($D$32,0,$C71)))) -> 17752456 | ... R72: =IF($C72>R$48,"",IF(OR(R$48="",R$48=0),"",IF(R$48=$C72,OFFSET($D$35,0,$C71)+OFFSET($D$35,0,$C71),OFFSET($D$32,0,$C71)))) -> 17752456
C73: =C72+1 -> 3 | D73: =IF($C73>D$48,"",IF(OR(D$48="",D$48=0),"",IF(D$48=$C73,OFFSET($D$35,0,$C72)+OFFSET($D$35,0,$C72),OFFSET($D$32,0,$C72)))) | E73: =IF($C73>E$48,"",IF(OR(E$48="",E$48=0),"",IF(E$48=$C73,OFFSET($D$35,0,$C72)+OFFSET($D$35,0,$C72),OFFSET($D$32,0,$C72)))) | F73: =IF($C73>F$48,"",IF(OR(F$48="",F$48=0),"",IF(F$48=$C73,OFFSET($D$35,0,$C72)+OFFSET($D$35,0,$C72),OFFSET($D$32,0,$C72)))) -> 1914142.4 | G73: =IF($C73>G$48,"",IF(OR(G$48="",G$48=0),"",IF(G$48=$C73,OFFSET($D$35,0,$C72)+OFFSET($D$35,0,$C72),OFFSET($D$32,0,$C72)))) -> 18401923 | H73: =IF($C73>H$48,"",IF(OR(H$48="",H$48=0),"",IF(H$48=$C73,OFFSET($D$35,0,$C72)+OFFSET($D$35,0,$C72),OFFSET($D$32,0,$C72)))) -> 18401923 | I73: =IF($C73>I$48,"",IF(OR(I$48="",I$48=0),"",IF(I$48=$C73,OFFSET($D$35,0,$C72)+OFFSET($D$35,0,$C72),OFFSET($D$32,0,$C72)))) -> 18401923 | J73: =IF($C73>J$48,"",IF(OR(J$48="",J$48=0),"",IF(J$48=$C73,OFFSET($D$35,0,$C72)+OFFSET($D$35,0,$C72),OFFSET($D$32,0,$C72)))) -> 18401923 | K73: =IF($C73>K$48,"",IF(OR(K$48="",K$48=0),"",IF(K$48=$C73,OFFSET($D$35,0,$C72)+OFFSET($D$35,0,$C72),OFFSET($D$32,0,$C72)))) -> 18401923 | ... R73: =IF($C73>R$48,"",IF(OR(R$48="",R$48=0),"",IF(R$48=$C73,OFFSET($D$35,0,$C72)+OFFSET($D$35,0,$C72),OFFSET($D$32,0,$C72)))) -> 18401923
C74: =C73+1 -> 4 | D74: =IF($C74>D$48,"",IF(OR(D$48="",D$48=0),"",IF(D$48=$C74,OFFSET($D$35,0,$C73)+OFFSET($D$35,0,$C73),OFFSET($D$32,0,$C73)))) | E74: =IF($C74>E$48,"",IF(OR(E$48="",E$48=0),"",IF(E$48=$C74,OFFSET($D$35,0,$C73)+OFFSET($D$35,0,$C73),OFFSET($D$32,0,$C73)))) | F74: =IF($C74>F$48,"",IF(OR(F$48="",F$48=0),"",IF(F$48=$C74,OFFSET($D$35,0,$C73)+OFFSET($D$35,0,$C73),OFFSET($D$32,0,$C73)))) | G74: =IF($C74>G$48,"",IF(OR(G$48="",G$48=0),"",IF(G$48=$C74,OFFSET($D$35,0,$C73)+OFFSET($D$35,0,$C73),OFFSET($D$32,0,$C73)))) -> 1959995.3 | H74: =IF($C74>H$48,"",IF(OR(H$48="",H$48=0),"",IF(H$48=$C74,OFFSET($D$35,0,$C73)+OFFSET($D$35,0,$C73),OFFSET($D$32,0,$C73)))) -> 18538079 | I74: =IF($C74>I$48,"",IF(OR(I$48="",I$48=0),"",IF(I$48=$C74,OFFSET($D$35,0,$C73)+OFFSET($D$35,0,$C73),OFFSET($D$32,0,$C73)))) -> 18538079 | J74: =IF($C74>J$48,"",IF(OR(J$48="",J$48=0),"",IF(J$48=$C74,OFFSET($D$35,0,$C73)+OFFSET($D$35,0,$C73),OFFSET($D$32,0,$C73)))) -> 18538079 | K74: =IF($C74>K$48,"",IF(OR(K$48="",K$48=0),"",IF(K$48=$C74,OFFSET($D$35,0,$C73)+OFFSET($D$35,0,$C73),OFFSET($D$32,0,$C73)))) -> 18538079 | ... R74: =IF($C74>R$48,"",IF(OR(R$48="",R$48=0),"",IF(R$48=$C74,OFFSET($D$35,0,$C73)+OFFSET($D$35,0,$C73),OFFSET($D$32,0,$C73)))) -> 18538079
C75: =C74+1 -> 5 | D75: =IF($C75>D$48,"",IF(OR(D$48="",D$48=0),"",IF(D$48=$C75,OFFSET($D$35,0,$C74)+OFFSET($D$35,0,$C74),OFFSET($D$32,0,$C74)))) | E75: =IF($C75>E$48,"",IF(OR(E$48="",E$48=0),"",IF(E$48=$C75,OFFSET($D$35,0,$C74)+OFFSET($D$35,0,$C74),OFFSET($D$32,0,$C74)))) | F75: =IF($C75>F$48,"",IF(OR(F$48="",F$48=0),"",IF(F$48=$C75,OFFSET($D$35,0,$C74)+OFFSET($D$35,0,$C74),OFFSET($D$32,0,$C74)))) | G75: =IF($C75>G$48,"",IF(OR(G$48="",G$48=0),"",IF(G$48=$C75,OFFSET($D$35,0,$C74)+OFFSET($D$35,0,$C74),OFFSET($D$32,0,$C74)))) | H75: =IF($C75>H$48,"",IF(OR(H$48="",H$48=0),"",IF(H$48=$C75,OFFSET($D$35,0,$C74)+OFFSET($D$35,0,$C74),OFFSET($D$32,0,$C74)))) -> 2005868.3 | I75: =IF($C75>I$48,"",IF(OR(I$48="",I$48=0),"",IF(I$48=$C75,OFFSET($D$35,0,$C74)+OFFSET($D$35,0,$C74),OFFSET($D$32,0,$C74)))) -> 18675413 | J75: =IF($C75>J$48,"",IF(OR(J$48="",J$48=0),"",IF(J$48=$C75,OFFSET($D$35,0,$C74)+OFFSET($D$35,0,$C74),OFFSET($D$32,0,$C74)))) -> 18675413 | K75: =IF($C75>K$48,"",IF(OR(K$48="",K$48=0),"",IF(K$48=$C75,OFFSET($D$35,0,$C74)+OFFSET($D$35,0,$C74),OFFSET($D$32,0,$C74)))) -> 18675413 | ... R75: =IF($C75>R$48,"",IF(OR(R$48="",R$48=0),"",IF(R$48=$C75,OFFSET($D$35,0,$C74)+OFFSET($D$35,0,$C74),OFFSET($D$32,0,$C74)))) -> 18675413
C76: =C75+1 -> 6 | D76: =IF($C76>D$48,"",IF(OR(D$48="",D$48=0),"",IF(D$48=$C76,OFFSET($D$35,0,$C75)+OFFSET($D$35,0,$C75),OFFSET($D$32,0,$C75)))) | E76: =IF($C76>E$48,"",IF(OR(E$48="",E$48=0),"",IF(E$48=$C76,OFFSET($D$35,0,$C75)+OFFSET($D$35,0,$C75),OFFSET($D$32,0,$C75)))) | F76: =IF($C76>F$48,"",IF(OR(F$48="",F$48=0),"",IF(F$48=$C76,OFFSET($D$35,0,$C75)+OFFSET($D$35,0,$C75),OFFSET($D$32,0,$C75)))) | G76: =IF($C76>G$48,"",IF(OR(G$48="",G$48=0),"",IF(G$48=$C76,OFFSET($D$35,0,$C75)+OFFSET($D$35,0,$C75),OFFSET($D$32,0,$C75)))) | H76: =IF($C76>H$48,"",IF(OR(H$48="",H$48=0),"",IF(H$48=$C76,OFFSET($D$35,0,$C75)+OFFSET($D$35,0,$C75),OFFSET($D$32,0,$C75)))) | I76: =IF($C76>I$48,"",IF(OR(I$48="",I$48=0),"",IF(I$48=$C76,OFFSET($D$35,0,$C75)+OFFSET($D$35,0,$C75),OFFSET($D$32,0,$C75)))) -> 2051742.3 | J76: =IF($C76>J$48,"",IF(OR(J$48="",J$48=0),"",IF(J$48=$C76,OFFSET($D$35,0,$C75)+OFFSET($D$35,0,$C75),OFFSET($D$32,0,$C75)))) -> 18813946 | K76: =IF($C76>K$48,"",IF(OR(K$48="",K$48=0),"",IF(K$48=$C76,OFFSET($D$35,0,$C75)+OFFSET($D$35,0,$C75),OFFSET($D$32,0,$C75)))) -> 18813946 | ... R76: =IF($C76>R$48,"",IF(OR(R$48="",R$48=0),"",IF(R$48=$C76,OFFSET($D$35,0,$C75)+OFFSET($D$35,0,$C75),OFFSET($D$32,0,$C75)))) -> 18813946
C77: =C76+1 -> 7 | D77: =IF($C77>D$48,"",IF(OR(D$48="",D$48=0),"",IF(D$48=$C77,OFFSET($D$35,0,$C76)+OFFSET($D$35,0,$C76),OFFSET($D$32,0,$C76)))) | E77: =IF($C77>E$48,"",IF(OR(E$48="",E$48=0),"",IF(E$48=$C77,OFFSET($D$35,0,$C76)+OFFSET($D$35,0,$C76),OFFSET($D$32,0,$C76)))) | F77: =IF($C77>F$48,"",IF(OR(F$48="",F$48=0),"",IF(F$48=$C77,OFFSET($D$35,0,$C76)+OFFSET($D$35,0,$C76),OFFSET($D$32,0,$C76)))) | G77: =IF($C77>G$48,"",IF(OR(G$48="",G$48=0),"",IF(G$48=$C77,OFFSET($D$35,0,$C76)+OFFSET($D$35,0,$C76),OFFSET($D$32,0,$C76)))) | H77: =IF($C77>H$48,"",IF(OR(H$48="",H$48=0),"",IF(H$48=$C77,OFFSET($D$35,0,$C76)+OFFSET($D$35,0,$C76),OFFSET($D$32,0,$C76)))) | I77: =IF($C77>I$48,"",IF(OR(I$48="",I$48=0),"",IF(I$48=$C77,OFFSET($D$35,0,$C76)+OFFSET($D$35,0,$C76),OFFSET($D$32,0,$C76)))) | J77: =IF($C77>J$48,"",IF(OR(J$48="",J$48=0),"",IF(J$48=$C77,OFFSET($D$35,0,$C76)+OFFSET($D$35,0,$C76),OFFSET($D$32,0,$C76)))) -> 2097596.8 | K77: =IF($C77>K$48,"",IF(OR(K$48="",K$48=0),"",IF(K$48=$C77,OFFSET($D$35,0,$C76)+OFFSET($D$35,0,$C76),OFFSET($D$32,0,$C76)))) -> 18953701 | ... R77: =IF($C77>R$48,"",IF(OR(R$48="",R$48=0),"",IF(R$48=$C77,OFFSET($D$35,0,$C76)+OFFSET($D$35,0,$C76),OFFSET($D$32,0,$C76)))) -> 18953701
C78: =C77+1 -> 8 | D78: =IF($C78>D$48,"",IF(OR(D$48="",D$48=0),"",IF(D$48=$C78,OFFSET($D$35,0,$C77)+OFFSET($D$35,0,$C77),OFFSET($D$32,0,$C77)))) | E78: =IF($C78>E$48,"",IF(OR(E$48="",E$48=0),"",IF(E$48=$C78,OFFSET($D$35,0,$C77)+OFFSET($D$35,0,$C77),OFFSET($D$32,0,$C77)))) | F78: =IF($C78>F$48,"",IF(OR(F$48="",F$48=0),"",IF(F$48=$C78,OFFSET($D$35,0,$C77)+OFFSET($D$35,0,$C77),OFFSET($D$32,0,$C77)))) | G78: =IF($C78>G$48,"",IF(OR(G$48="",G$48=0),"",IF(G$48=$C78,OFFSET($D$35,0,$C77)+OFFSET($D$35,0,$C77),OFFSET($D$32,0,$C77)))) | H78: =IF($C78>H$48,"",IF(OR(H$48="",H$48=0),"",IF(H$48=$C78,OFFSET($D$35,0,$C77)+OFFSET($D$35,0,$C77),OFFSET($D$32,0,$C77)))) | I78: =IF($C78>I$48,"",IF(OR(I$48="",I$48=0),"",IF(I$48=$C78,OFFSET($D$35,0,$C77)+OFFSET($D$35,0,$C77),OFFSET($D$32,0,$C77)))) | J78: =IF($C78>J$48,"",IF(OR(J$48="",J$48=0),"",IF(J$48=$C78,OFFSET($D$35,0,$C77)+OFFSET($D$35,0,$C77),OFFSET($D$32,0,$C77)))) | K78: =IF($C78>K$48,"",IF(OR(K$48="",K$48=0),"",IF(K$48=$C78,OFFSET($D$35,0,$C77)+OFFSET($D$35,0,$C77),OFFSET($D$32,0,$C77)))) -> 2143410.8 | ... R78: =IF($C78>R$48,"",IF(OR(R$48="",R$48=0),"",IF(R$48=$C78,OFFSET($D$35,0,$C77)+OFFSET($D$35,0,$C77),OFFSET($D$32,0,$C77)))) -> 19094713
C79: =C78+1 -> 9 | D79: =IF($C79>D$48,"",IF(OR(D$48="",D$48=0),"",IF(D$48=$C79,OFFSET($D$35,0,$C78)+OFFSET($D$35,0,$C78),OFFSET($D$32,0,$C78)))) | E79: =IF($C79>E$48,"",IF(OR(E$48="",E$48=0),"",IF(E$48=$C79,OFFSET($D$35,0,$C78)+OFFSET($D$35,0,$C78),OFFSET($D$32,0,$C78)))) | F79: =IF($C79>F$48,"",IF(OR(F$48="",F$48=0),"",IF(F$48=$C79,OFFSET($D$35,0,$C78)+OFFSET($D$35,0,$C78),OFFSET($D$32,0,$C78)))) | G79: =IF($C79>G$48,"",IF(OR(G$48="",G$48=0),"",IF(G$48=$C79,OFFSET($D$35,0,$C78)+OFFSET($D$35,0,$C78),OFFSET($D$32,0,$C78)))) | H79: =IF($C79>H$48,"",IF(OR(H$48="",H$48=0),"",IF(H$48=$C79,OFFSET($D$35,0,$C78)+OFFSET($D$35,0,$C78),OFFSET($D$32,0,$C78)))) | I79: =IF($C79>I$48,"",IF(OR(I$48="",I$48=0),"",IF(I$48=$C79,OFFSET($D$35,0,$C78)+OFFSET($D$35,0,$C78),OFFSET($D$32,0,$C78)))) | J79: =IF($C79>J$48,"",IF(OR(J$48="",J$48=0),"",IF(J$48=$C79,OFFSET($D$35,0,$C78)+OFFSET($D$35,0,$C78),OFFSET($D$32,0,$C78)))) | K79: =IF($C79>K$48,"",IF(OR(K$48="",K$48=0),"",IF(K$48=$C79,OFFSET($D$35,0,$C78)+OFFSET($D$35,0,$C78),OFFSET($D$32,0,$C78)))) | ... R79: =IF($C79>R$48,"",IF(OR(R$48="",R$48=0),"",IF(R$48=$C79,OFFSET($D$35,0,$C78)+OFFSET($D$35,0,$C78),OFFSET($D$32,0,$C78)))) -> 19237022
C80: =C79+1 -> 10 | D80: =IF($C80>D$48,"",IF(OR(D$48="",D$48=0),"",IF(D$48=$C80,OFFSET($D$35,0,$C79)+OFFSET($D$35,0,$C79),OFFSET($D$32,0,$C79)))) | E80: =IF($C80>E$48,"",IF(OR(E$48="",E$48=0),"",IF(E$48=$C80,OFFSET($D$35,0,$C79)+OFFSET($D$35,0,$C79),OFFSET($D$32,0,$C79)))) | F80: =IF($C80>F$48,"",IF(OR(F$48="",F$48=0),"",IF(F$48=$C80,OFFSET($D$35,0,$C79)+OFFSET($D$35,0,$C79),OFFSET($D$32,0,$C79)))) | G80: =IF($C80>G$48,"",IF(OR(G$48="",G$48=0),"",IF(G$48=$C80,OFFSET($D$35,0,$C79)+OFFSET($D$35,0,$C79),OFFSET($D$32,0,$C79)))) | H80: =IF($C80>H$48,"",IF(OR(H$48="",H$48=0),"",IF(H$48=$C80,OFFSET($D$35,0,$C79)+OFFSET($D$35,0,$C79),OFFSET($D$32,0,$C79)))) | I80: =IF($C80>I$48,"",IF(OR(I$48="",I$48=0),"",IF(I$48=$C80,OFFSET($D$35,0,$C79)+OFFSET($D$35,0,$C79),OFFSET($D$32,0,$C79)))) | J80: =IF($C80>J$48,"",IF(OR(J$48="",J$48=0),"",IF(J$48=$C80,OFFSET($D$35,0,$C79)+OFFSET($D$35,0,$C79),OFFSET($D$32,0,$C79)))) | K80: =IF($C80>K$48,"",IF(OR(K$48="",K$48=0),"",IF(K$48=$C80,OFFSET($D$35,0,$C79)+OFFSET($D$35,0,$C79),OFFSET($D$32,0,$C79)))) | ... R80: =IF($C80>R$48,"",IF(OR(R$48="",R$48=0),"",IF(R$48=$C80,OFFSET($D$35,0,$C79)+OFFSET($D$35,0,$C79),OFFSET($D$32,0,$C79)))) -> 19380677
C81: =C80+1 -> 11 | D81: =IF($C81>D$48,"",IF(OR(D$48="",D$48=0),"",IF(D$48=$C81,OFFSET($D$35,0,$C80)+OFFSET($D$35,0,$C80),OFFSET($D$32,0,$C80)))) | E81: =IF($C81>E$48,"",IF(OR(E$48="",E$48=0),"",IF(E$48=$C81,OFFSET($D$35,0,$C80)+OFFSET($D$35,0,$C80),OFFSET($D$32,0,$C80)))) | F81: =IF($C81>F$48,"",IF(OR(F$48="",F$48=0),"",IF(F$48=$C81,OFFSET($D$35,0,$C80)+OFFSET($D$35,0,$C80),OFFSET($D$32,0,$C80)))) | G81: =IF($C81>G$48,"",IF(OR(G$48="",G$48=0),"",IF(G$48=$C81,OFFSET($D$35,0,$C80)+OFFSET($D$35,0,$C80),OFFSET($D$32,0,$C80)))) | H81: =IF($C81>H$48,"",IF(OR(H$48="",H$48=0),"",IF(H$48=$C81,OFFSET($D$35,0,$C80)+OFFSET($D$35,0,$C80),OFFSET($D$32,0,$C80)))) | I81: =IF($C81>I$48,"",IF(OR(I$48="",I$48=0),"",IF(I$48=$C81,OFFSET($D$35,0,$C80)+OFFSET($D$35,0,$C80),OFFSET($D$32,0,$C80)))) | J81: =IF($C81>J$48,"",IF(OR(J$48="",J$48=0),"",IF(J$48=$C81,OFFSET($D$35,0,$C80)+OFFSET($D$35,0,$C80),OFFSET($D$32,0,$C80)))) | K81: =IF($C81>K$48,"",IF(OR(K$48="",K$48=0),"",IF(K$48=$C81,OFFSET($D$35,0,$C80)+OFFSET($D$35,0,$C80),OFFSET($D$32,0,$C80)))) | ... R81: =IF($C81>R$48,"",IF(OR(R$48="",R$48=0),"",IF(R$48=$C81,OFFSET($D$35,0,$C80)+OFFSET($D$35,0,$C80),OFFSET($D$32,0,$C80)))) -> 19525737
C82: =C81+1 -> 12 | D82: =IF($C82>D$48,"",IF(OR(D$48="",D$48=0),"",IF(D$48=$C82,OFFSET($D$35,0,$C81)+OFFSET($D$35,0,$C81),OFFSET($D$32,0,$C81)))) | E82: =IF($C82>E$48,"",IF(OR(E$48="",E$48=0),"",IF(E$48=$C82,OFFSET($D$35,0,$C81)+OFFSET($D$35,0,$C81),OFFSET($D$32,0,$C81)))) | F82: =IF($C82>F$48,"",IF(OR(F$48="",F$48=0),"",IF(F$48=$C82,OFFSET($D$35,0,$C81)+OFFSET($D$35,0,$C81),OFFSET($D$32,0,$C81)))) | G82: =IF($C82>G$48,"",IF(OR(G$48="",G$48=0),"",IF(G$48=$C82,OFFSET($D$35,0,$C81)+OFFSET($D$35,0,$C81),OFFSET($D$32,0,$C81)))) | H82: =IF($C82>H$48,"",IF(OR(H$48="",H$48=0),"",IF(H$48=$C82,OFFSET($D$35,0,$C81)+OFFSET($D$35,0,$C81),OFFSET($D$32,0,$C81)))) | I82: =IF($C82>I$48,"",IF(OR(I$48="",I$48=0),"",IF(I$48=$C82,OFFSET($D$35,0,$C81)+OFFSET($D$35,0,$C81),OFFSET($D$32,0,$C81)))) | J82: =IF($C82>J$48,"",IF(OR(J$48="",J$48=0),"",IF(J$48=$C82,OFFSET($D$35,0,$C81)+OFFSET($D$35,0,$C81),OFFSET($D$32,0,$C81)))) | K82: =IF($C82>K$48,"",IF(OR(K$48="",K$48=0),"",IF(K$48=$C82,OFFSET($D$35,0,$C81)+OFFSET($D$35,0,$C81),OFFSET($D$32,0,$C81)))) | ... R82: =IF($C82>R$48,"",IF(OR(R$48="",R$48=0),"",IF(R$48=$C82,OFFSET($D$35,0,$C81)+OFFSET($D$35,0,$C81),OFFSET($D$32,0,$C81)))) -> 19672273
... C85: =C84+1 -> 15 | D85: =IF($C85>D$48,"",IF(OR(D$48="",D$48=0),"",IF(D$48=$C85,OFFSET($D$35,0,$C84)+OFFSET($D$35,0,$C84),OFFSET($D$32,0,$C84)))) | E85: =IF($C85>E$48,"",IF(OR(E$48="",E$48=0),"",IF(E$48=$C85,OFFSET($D$35,0,$C84)+OFFSET($D$35,0,$C84),OFFSET($D$32,0,$C84)))) | F85: =IF($C85>F$48,"",IF(OR(F$48="",F$48=0),"",IF(F$48=$C85,OFFSET($D$35,0,$C84)+OFFSET($D$35,0,$C84),OFFSET($D$32,0,$C84)))) | G85: =IF($C85>G$48,"",IF(OR(G$48="",G$48=0),"",IF(G$48=$C85,OFFSET($D$35,0,$C84)+OFFSET($D$35,0,$C84),OFFSET($D$32,0,$C84)))) | H85: =IF($C85>H$48,"",IF(OR(H$48="",H$48=0),"",IF(H$48=$C85,OFFSET($D$35,0,$C84)+OFFSET($D$35,0,$C84),OFFSET($D$32,0,$C84)))) | I85: =IF($C85>I$48,"",IF(OR(I$48="",I$48=0),"",IF(I$48=$C85,OFFSET($D$35,0,$C84)+OFFSET($D$35,0,$C84),OFFSET($D$32,0,$C84)))) | J85: =IF($C85>J$48,"",IF(OR(J$48="",J$48=0),"",IF(J$48=$C85,OFFSET($D$35,0,$C84)+OFFSET($D$35,0,$C84),OFFSET($D$32,0,$C84)))) | K85: =IF($C85>K$48,"",IF(OR(K$48="",K$48=0),"",IF(K$48=$C85,OFFSET($D$35,0,$C84)+OFFSET($D$35,0,$C84),OFFSET($D$32,0,$C84)))) | ... R85: =IF($C85>R$48,"",IF(OR(R$48="",R$48=0),"",IF(R$48=$C85,OFFSET($D$35,0,$C84)+OFFSET($D$35,0,$C84),OFFSET($D$32,0,$C84)))) -> 2460991.2
B87: DCF Calculations
C88: Year | D88: =IF(OR(D$10="",D$10=0),"",D$4) -> 1 | E88: =IF(OR(E$10="",E$10=0),"",E$4) -> 2 | F88: =IF(OR(F$10="",F$10=0),"",F$4) -> 3 | G88: =IF(OR(G$10="",G$10=0),"",G$4) -> 4 | H88: =IF(OR(H$10="",H$10=0),"",H$4) -> 5 | I88: =IF(OR(I$10="",I$10=0),"",I$4) -> 6 | J88: =IF(OR(J$10="",J$10=0),"",J$4) -> 7 | K88: =IF(OR(K$10="",K$10=0),"",K$4) -> 8 | ... R88: =IF(OR(R$10="",R$10=0),"",R$4) -> 15
C89: CFFO | D89: =IF(OR(D$88="",D$88=0),"",D$10) -> 1852647.5 | E89: =IF(OR(E$88="",E$88=0),"",E$10) -> 2032346.9 | F89: =IF(OR(F$88="",F$88=0),"",F$10) -> 2288952.2 | G89: =IF(OR(G$88="",G$88=0),"",G$10) -> 2311878.6 | H89: =IF(OR(H$88="",H$88=0),"",H$10) -> 2334815.1 | I89: =IF(OR(I$88="",I$88=0),"",I$10) -> 2357752.1 | J89: =IF(OR(J$88="",J$88=0),"",J$10) -> 2380679.4 | K89: =IF(OR(K$88="",K$88=0),"",K$10) -> 2403586.4 | ... R89: =IF(OR(R$88="",R$88=0),"",R$10) -> 2562376.6
C90: Sale Price | D90: =IF(OR(D$88="",D$88=0),"",D$13) -> 35382269 | E90: =IF(OR(E$88="",E$88=0),"",E$13) -> 35845632 | F90: =IF(OR(F$88="",F$88=0),"",F$13) -> 36474291 | G90: =IF(OR(G$88="",G$88=0),"",G$13) -> 36588078 | H90: =IF(OR(H$88="",H$88=0),"",H$13) -> 36701368 | I90: =IF(OR(I$88="",I$88=0),"",I$13) -> 36814054 | J90: =IF(OR(J$88="",J$88=0),"",J$13) -> 36926025 | K90: =IF(OR(K$88="",K$88=0),"",K$13) -> 37037170 | ... R90: =IF(OR(R$88="",R$88=0),"",R$13) -> 37781965
C91: Total CFs | D91: =IF(D$88=$C$97,SUM(D$89:D$90),D$89) -> 1852647.5 | E91: =IF(E$88=$C$97,SUM(E$89:E$90),E$89) -> 2032346.9 | F91: =IF(F$88=$C$97,SUM(F$89:F$90),F$89) -> 2288952.2 | G91: =IF(G$88=$C$97,SUM(G$89:G$90),G$89) -> 2311878.6 | H91: =IF(H$88=$C$97,SUM(H$89:H$90),H$89) -> 2334815.1 | I91: =IF(I$88=$C$97,SUM(I$89:I$90),I$89) -> 2357752.1 | J91: =IF(J$88=$C$97,SUM(J$89:J$90),J$89) -> 2380679.4 | K91: =IF(K$88=$C$97,SUM(K$89:K$90),K$89) -> 2403586.4 | ... R91: =IF(R$88=$C$97,SUM(R$89:R$90),R$89) -> 40344342
B92: NPV:
B93: -Formulaically | C93: =SUM(D93:R93) -> 42321157 | D93: =D91/(1+$C$96)^D88 -> 1764426.2 | E93: =E91/(1+$C$96)^E88 -> 1843398.6 | F93: =F91/(1+$C$96)^F88 -> 1977283 | G93: =G91/(1+$C$96)^G88 -> 1901988.2 | H93: =H91/(1+$C$96)^H88 -> 1829388.7 | I93: =I91/(1+$C$96)^I88 -> 1759390.9 | J93: =J91/(1+$C$96)^J88 -> 1691904.4 | K93: =K91/(1+$C$96)^K88 -> 1626841.9 | ... R93: =R91/(1+$C$96)^R88 -> 19406318
B94: -NPV() | C94: =NPV(C96,D91:R91) -> 42321157
B96: Discount Rate: | C96: =Discount_Rate -> 0.05
B97: Building Sale Year: | C97: =Terminal_Cap_Year -> 15

Sheet Investor Returns
B2: Property Level Returns
B4: Promote Structure Method | D4: IRR
B5: Return of Capital Method | D5: Pari Passu
B7: Equity Contributions | C7: % | D7: Amount | J7: Error Check: | K7: =IF(ROUND(K9,0)=ROUND(K8,0),"OK","Error") -> OK
B8: General Partner (GP) | C8: 0.1 | D8: =Equity_Share_Sponsor*Total_Equity -> 1966879.2 | E8: =Equity_Share_Sponsor=1 -> FALSE | J8: Profit Dist.: | K8: =(D27+D41)/1000000 -> 15.9096
B9: Limited Partner (LP) | C9: =1-C8 -> 0.9 | D9: =Equity_Share_LPs*Total_Equity -> 17701913 | J9: Net BTCF: | K9: =SUM(F48:U48)/1000000 -> 15.9096
B10: Total Equity | C10: =SUM(C8:C9) -> 1 | D10: =-SUMIF(F51:U51,"<0") -> 19668792
F12: Promote Structure Incentive Breakdown | H12: Distribution as %
B13: ="Promote Structure ("&$D$4&" Hurdles)" -> Promote Structure (IRR Hurdles) | H13: Sponsor % | I13: LP % | J13: Total Check | K13: Description
B14: Hurdle 1 (Preferred Return) | C14: Equity Multiple | D14: Pref | E14: =IF($D$4="EM",C15,D15) -> 0.08 | F14: Sponsor Promote | H14: =Equity_Share_Sponsor -> 0.1 | I14: =1-H14 -> 0.9 | J14: =SUM(H14:I14) -> 1 | K14: =IF(I14=Equity_Share_LPs,"Pref pro rata to LP/GP, then pro rata return of capital","Return of capital and pref NOT pro rata") -> Pref pro rata to LP/GP, then pro rata return of capital
B15: Hurdle 2 | C15: 1.15 | D15: 0.08 | E15: =IF($D$4="EM",C16,D16) -> 0.12 | F15: 0.1 | H15: =1-(Equity_Share_LPs*(1-F15)) -> 0.19 | I15: =1-H15 -> 0.81 | J15: =SUM(H15:I15) -> 1 | K15: =IF(Equity_Share_Sponsor<>H14,TEXT(I14,"0.00%")&"/"&TEXT(H14,"0.00%")&" to "&(IF(D4="IRR",TEXT(E14,"0.00%"),TEXT(E14,"0.00x")))&", then "&TEXT(I15,"0.00%")&"/"&TEXT(H15,"0.00%")&" to "&(IF(D4="IRR",TEXT(E15,"0.00%"),TEXT(E15,"0.00x"))),"Pro rata to LP/GP to "&(IF(D4="IRR",TEXT(E14,"0.00%"),TEXT(E14,"0.00x")))&", then "&TEXT(I15,"0.00%")&"/"&TEXT(H15,"0.00%")&" to "&(IF(D4="IRR",TEXT(E15,"0.00%"),TEXT(E15,"0.00x")))) -> Pro rata to LP/GP to 8.00%, then 81.00%/19.00% to 12.00%
B16: Hurdle 3 | C16: 1.3 | D16: 0.12 | E16: =IF($D$4="EM",C17,D17) -> 0.15 | F16: 0.12 | H16: =1-(Equity_Share_LPs*(1-F16)) -> 0.208 | I16: =1-H16 -> 0.792 | J16: =SUM(H16:I16) -> 1 | K16: =TEXT(I15,"0.00%")&"/"&TEXT(H15,"0.00%")&" to "&(IF(D4="IRR",TEXT(E15,"0.00%"),TEXT(E15,"0.00x")))&", then "&TEXT(I16,"0.00%")&"/"&TEXT(H16,"0.00%")&" to "&(IF(D4="IRR",TEXT(E16,"0.00%"),TEXT(E16,"0.00x"))) -> 81.00%/19.00% to 12.00%, then 79.20%/20.80% to 15.00%
B17: Hurdle 4 | C17: 1.45 | D17: 0.15 | F17: 0.15 | H17: =1-(Equity_Share_LPs*(1-F17)) -> 0.235 | I17: =1-H17 -> 0.765 | J17: =SUM(H17:I17) -> 1 | K17: =TEXT(I16,"0.00%")&"/"&TEXT(H16,"0.00%")&" to "&(IF(D4="IRR",TEXT(E16,"0.00%"),TEXT(E16,"0.00x")))&", then "&TEXT(I17,"0.00%")&"/"&TEXT(H17,"0.00%")&" thereafter" -> 79.20%/20.80% to 15.00%, then 76.50%/23.50% thereafter
B19: Summary of Partnership Level Returns | F19: 0 | G19: =IF(OR(F$19="",F$19=Effective_Hold_Period),"",F$19+1) -> 1 | H19: =IF(OR(G$19="",G$19=Effective_Hold_Period),"",G$19+1) -> 2 | I19: =IF(OR(H$19="",H$19=Effective_Hold_Period),"",H$19+1) -> 3 | J19: =IF(OR(I$19="",I$19=Effective_Hold_Period),"",I$19+1) -> 4 | K19: =IF(OR(J$19="",J$19=Effective_Hold_Period),"",J$19+1) -> 5 | L19: =IF(OR(K$19="",K$19=Effective_Hold_Period),"",K$19+1) -> 6 | M19: =IF(OR(L$19="",L$19=Effective_Hold_Period),"",L$19+1) -> 7 | N19: =IF(OR(M$19="",M$19=Effective_Hold_Period),"",M$19+1) -> 8 | ... U19: =IF(OR(T$19="",T$19=Effective_Hold_Period),"",T$19+1) -> 15
B20: Limited Partner (LP) Returns | C20: Error Check
B21: Preferred Return | C21: =IF(ROUND(D21,0)=ROUND(SUM(F21:U21),0),"OK","ERROR") -> OK | D21: =(Promote_Method="IRR")*(SUM($F$78:$U$78)-D22)+(Promote_Method="EM")*(SUM($F$78:$U$78)-D22) -> -2953070.6 | F21: =IF(F$19="","",0) -> 0 | G21: =IF(G$19="","",MIN($D21-SUM($F$21:F$21),G$25)) -> -2953070.6 | H21: =IF(H$19="","",MIN($D21-SUM($F$21:G$21),H$25)) -> 0 | I21: =IF(I$19="","",MIN($D21-SUM($F$21:H$21),I$25)) -> 0 | J21: =IF(J$19="","",MIN($D21-SUM($F$21:I$21),J$25)) -> 0 | K21: =IF(K$19="","",MIN($D21-SUM($F$21:J$21),K$25)) -> 0 | L21: =IF(L$19="","",MIN($D21-SUM($F$21:K$21),L$25)) -> 0 | M21: =IF(M$19="","",MIN($D21-SUM($F$21:L$21),M$25)) -> 0 | N21: =IF(N$19="","",MIN($D21-SUM($F$21:M$21),N$25)) -> 0 | ... U21: =IF(U$19="","",MIN($D21-SUM($F$21:T$21),U$25)) -> 0
B22: Return of Capital | C22: =IF(ROUND(D22,0)=ROUND(SUM(F22:U22),0),"OK","ERROR") -> OK | D22: =MIN(D25,D26) -> 17701913 | F22: =IF(F$19="","",0) -> 0 | G22: =IF(G$19="","",MIN($D22-SUM($F$22:F$22),G$25-G$21)) -> 3403760.4 | H22: =IF(H$19="","",MIN($D22-SUM($F$22:G$22),H$25-H$21)) -> 612419.34 | I22: =IF(I$19="","",MIN($D22-SUM($F$22:H$22),I$25-I$21)) -> 843364.09 | J22: =IF(J$19="","",MIN($D22-SUM($F$22:I$22),J$25-J$21)) -> 863997.86 | K22: =IF(K$19="","",MIN($D22-SUM($F$22:J$22),K$25-K$21)) -> 884640.75 | L22: =IF(L$19="","",MIN($D22-SUM($F$22:K$22),L$25-L$21)) -> 905284.02 | M22: =IF(M$19="","",MIN($D22-SUM($F$22:L$22),M$25-M$21)) -> 925918.57 | N22: =IF(N$19="","",MIN($D22-SUM($F$22:M$22),N$25-N$21)) -> 946534.88 | ... U22: =IF(U$19="","",MIN($D22-SUM($F$22:T$22),U$25-U$21)) -> 2206171.8
B23: Excess Cash Flow | C23: =IF(ROUND(D23,0)=ROUND(SUM(F23:U23),0),"OK","ERROR") -> OK | D23: =D25-D22-D21 -> 15158567 | F23: =IF(F$19="","",0) -> 0 | G23: =IF(G$19="","",G$25-G$22-G$21) -> 0 | H23: =IF(H$19="","",H$25-H$22-H$21) -> 0 | I23: =IF(I$19="","",I$25-I$22-I$21) -> 0 | J23: =IF(J$19="","",J$25-J$22-J$21) -> 0 | K23: =IF(K$19="","",K$25-K$22-K$21) -> 0 | L23: =IF(L$19="","",L$25-L$22-L$21) -> 0 | M23: =IF(M$19="","",M$25-M$22-M$21) -> 0 | N23: =IF(N$19="","",N$25-N$22-N$21) -> 0 | ... U23: =IF(U$19="","",U$25-U$22-U$21) -> 15158567
B25: Total LP Distributions | D25: =SUM(F25:U25) -> 29907409 | F25: =IF(F$19="","",IF(GP_Only_No_LPs,0,F$78+F$91+F$104+F$112)) -> 0 | G25: =IF(G$19="","",IF(GP_Only_No_LPs,0,G$78+G$91+G$104+G$112)) -> 450689.87 | H25: =IF(H$19="","",IF(GP_Only_No_LPs,0,H$78+H$91+H$104+H$112)) -> 612419.34 | I25: =IF(I$19="","",IF(GP_Only_No_LPs,0,I$78+I$91+I$104+I$112)) -> 843364.09 | J25: =IF(J$19="","",IF(GP_Only_No_LPs,0,J$78+J$91+J$104+J$112)) -> 863997.86 | K25: =IF(K$19="","",IF(GP_Only_No_LPs,0,K$78+K$91+K$104+K$112)) -> 884640.75 | L25: =IF(L$19="","",IF(GP_Only_No_LPs,0,L$78+L$91+L$104+L$112)) -> 905284.02 | M25: =IF(M$19="","",IF(GP_Only_No_LPs,0,M$78+M$91+M$104+M$112)) -> 925918.57 | ... U25: =IF(U$19="","",IF(GP_Only_No_LPs,0,U$78+U$91+U$104+U$112)) -> 17364739
B26: Total LP Contributions | D26: =SUM(F26:U26) -> 17701913 | F26: =IF(F$19="","",F$60) -> 17701913 | G26: =IF(G$19="","",G$60) -> 0 | H26: =IF(H$19="","",H$60) -> 0 | I26: =IF(I$19="","",I$60) -> 0 | J26: =IF(J$19="","",J$60) -> 0 | K26: =IF(K$19="","",K$60) -> 0 | L26: =IF(L$19="","",L$60) -> 0 | M26: =IF(M$19="","",M$60) -> 0 | ... U26: =IF(U$19="","",U$60) -> 0
B27: Total LP Profit | D27: =D25-D26 -> 12205497
B29: LP IRR | D29: =IF(GP_Only_No_LPs,"N/A",IF(AND(MIN(F$29:U$29)<0,MAX(F$29:U$29)>0),IRR(F$29:U$29),"-")) -> 0.04584265 | F29: =IF(F$19="","",-F$26+F$25) -> -17701913 | G29: =IF(G$19="","",-G$26+G$25) -> 450689.87 | H29: =IF(H$19="","",-H$26+H$25) -> 612419.34 | I29: =IF(I$19="","",-I$26+I$25) -> 843364.09 | J29: =IF(J$19="","",-J$26+J$25) -> 863997.86 | K29: =IF(K$19="","",-K$26+K$25) -> 884640.75 | L29: =IF(L$19="","",-L$26+L$25) -> 905284.02 | M29: =IF(M$19="","",-M$26+M$25) -> 925918.57 | ... U29: =IF(U$19="","",-U$26+U$25) -> 17364739
B30: LP Equity Multiple | D30: =IF(GP_Only_No_LPs,"N/A",D25/D26) -> 1.6895016
B32: GP Returns | C32: Error Check
B33: Preferred Return | C33: =IF(ROUND(D33,0)=ROUND(SUM(F33:U33),0),"OK","ERROR") -> OK | D33: =(Promote_Method="IRR")*(SUM($F$79:$U$79)-D34)+(Promote_Method="EM")*(SUM($F$79:$U$79)-D34) -> -328118.95 | F33: =IF(F$19="","",0) -> 0 | G33: =IF(G$19="","",MIN($D$33-SUM($F$33:F$33),G$38)) -> -328118.95 | H33: =IF(H$19="","",MIN($D$33-SUM($F$33:G$33),H$38)) -> 0 | I33: =IF(I$19="","",MIN($D$33-SUM($F$33:H$33),I$38)) -> 0 | J33: =IF(J$19="","",MIN($D$33-SUM($F$33:I$33),J$38)) -> 0 | K33: =IF(K$19="","",MIN($D$33-SUM($F$33:J$33),K$38)) -> 0 | L33: =IF(L$19="","",MIN($D$33-SUM($F$33:K$33),L$38)) -> 0 | M33: =IF(M$19="","",MIN($D$33-SUM($F$33:L$33),M$38)) -> 0 | N33: =IF(N$19="","",MIN($D$33-SUM($F$33:M$33),N$38)) -> 0 | ... U33: =IF(U$19="","",MIN($D$33-SUM($F$33:T$33),U$38)) -> 0
B34: Return of Capital | C34: =IF(ROUND(D34,0)=ROUND(SUM(F34:U34),0),"OK","ERROR") -> OK | D34: =MIN(D38,D40) -> 1966879.2 | F34: =IF(F$19="","",0) -> 0 | G34: =IF(G$19="","",MIN($D$34-SUM($F$34:F$34),G$38-G$33)) -> 378195.6 | H34: =IF(H$19="","",MIN($D$34-SUM($F$34:G$34),H$38-H$33)) -> 68046.593 | I34: =IF(I$19="","",MIN($D$34-SUM($F$34:H$34),I$38-I$33)) -> 93707.122 | J34: =IF(J$19="","",MIN($D$34-SUM($F$34:I$34),J$38-J$33)) -> 95999.763 | K34: =IF(K$19="","",MIN($D$34-SUM($F$34:J$34),K$38-K$33)) -> 98293.416 | L34: =IF(L$19="","",MIN($D$34-SUM($F$34:K$34),L$38-L$33)) -> 100587.11 | M34: =IF(M$19="","",MIN($D$34-SUM($F$34:L$34),M$38-M$33)) -> 102879.84 | N34: =IF(N$19="","",MIN($D$34-SUM($F$34:M$34),N$38-N$33)) -> 105170.54 | ... U34: =IF(U$19="","",MIN($D$34-SUM($F$34:T$34),U$38-U$33)) -> 245130.2
B35: Promote | C35: =IF(ROUND(D35,0)=ROUND(SUM(F35:U35),0),"OK","ERROR") -> OK | D35: =D38-D34-D36-D33 -> 2027936.9 | F35: =IF(F$19="","",0) -> 0 | G35: =IF(G$19="","",G$38-G$36-G$34-G$33) -> 0 | H35: =IF(H$19="","",H$38-H$36-H$34-H$33) -> 0 | I35: =IF(I$19="","",I$38-I$36-I$34-I$33) -> 0 | J35: =IF(J$19="","",J$38-J$36-J$34-J$33) -> 0 | K35: =IF(K$19="","",K$38-K$36-K$34-K$33) -> 0 | L35: =IF(L$19="","",L$38-L$36-L$34-L$33) -> 0 | M35: =IF(M$19="","",M$38-M$36-M$34-M$33) -> 0 | N35: =IF(N$19="","",N$38-N$36-N$34-N$33) -> 0 | ... U35: =IF(U$19="","",U$38-U$36-U$34-U$33) -> 2027936.9
B36: Excess Cash Flow | C36: =IF(ROUND(D36,0)=ROUND(SUM(F36:U36),0),"OK","ERROR") -> OK | D36: =$D$23/Equity_Share_LPs*Equity_Share_Sponsor -> 1684285.3 | F36: =IF(F$19="","",F$23/Equity_Share_LPs*Equity_Share_Sponsor) -> 0 | G36: =IF(G$19="","",G$23/Equity_Share_LPs*Equity_Share_Sponsor) -> 0 | H36: =IF(H$19="","",H$23/Equity_Share_LPs*Equity_Share_Sponsor) -> 0 | I36: =IF(I$19="","",I$23/Equity_Share_LPs*Equity_Share_Sponsor) -> 0 | J36: =IF(J$19="","",J$23/Equity_Share_LPs*Equity_Share_Sponsor) -> 0 | K36: =IF(K$19="","",K$23/Equity_Share_LPs*Equity_Share_Sponsor) -> 0 | L36: =IF(L$19="","",L$23/Equity_Share_LPs*Equity_Share_Sponsor) -> 0 | M36: =IF(M$19="","",M$23/Equity_Share_LPs*Equity_Share_Sponsor) -> 0 | ... U36: =IF(U$19="","",U$23/Equity_Share_LPs*Equity_Share_Sponsor) -> 1684285.3
B38: Total GP Distributions | D38: =SUM(F38:U38) -> 5350982.4 | F38: =IF(F19="","",F$79+F$92+F$105+F$113) -> 0 | G38: =IF(G19="","",G$79+G$92+G$105+G$113) -> 50076.652 | H38: =IF(H19="","",H$79+H$92+H$105+H$113) -> 68046.593 | I38: =IF(I19="","",I$79+I$92+I$105+I$113) -> 93707.122 | J38: =IF(J19="","",J$79+J$92+J$105+J$113) -> 95999.763 | K38: =IF(K19="","",K$79+K$92+K$105+K$113) -> 98293.416 | L38: =IF(L19="","",L$79+L$92+L$105+L$113) -> 100587.11 | M38: =IF(M19="","",M$79+M$92+M$105+M$113) -> 102879.84 | ... U38: =IF(U19="","",U$79+U$92+U$105+U$113) -> 3957352.3
B39: Total GP Fees | D39: =SUM(F39:U39) -> 320000 | F39: =IF(F$19="","",SUM(F49:F50)) -> 10000 | G39: =IF(G$19="","",SUM(G49:G50)) -> 20000 | H39: =IF(H$19="","",SUM(H49:H50)) -> 20000 | I39: =IF(I$19="","",SUM(I49:I50)) -> 20000 | J39: =IF(J$19="","",SUM(J49:J50)) -> 20000 | K39: =IF(K$19="","",SUM(K49:K50)) -> 20000 | L39: =IF(L$19="","",SUM(L49:L50)) -> 20000 | M39: =IF(M$19="","",SUM(M49:M50)) -> 20000 | ... U39: =IF(U$19="","",SUM(U49:U50)) -> 30000
B40: Total GP Contributions | D40: =SUM(F40:U40) -> 1966879.2 | F40: =IF(F19="","",F$67) -> 1966879.2 | G40: =IF(G19="","",G$67) -> 0 | H40: =IF(H19="","",H$67) -> 0 | I40: =IF(I19="","",I$67) -> 0 | J40: =IF(J19="","",J$67) -> 0 | K40: =IF(K19="","",K$67) -> 0 | L40: =IF(L19="","",L$67) -> 0 | M40: =IF(M19="","",M$67) -> 0 | ... U40: =IF(U19="","",U$67) -> 0
B41: Total GP Profit (incl. fees) | D41: =D38+D39-D40 -> 3704103.2
B43: Sponsor IRR | D43: =IF(AND(MIN($F$43:$U$43)<0,MAX($F$43:$U$43)>0),IRR($F$43:$U$43),"-") -> 0.091151742 | F43: =IF(F19="","",(-F40)+F38+F39) -> -1956879.2 | G43: =IF(G19="","",(-G40)+G38+G39) -> 70076.652 | H43: =IF(H19="","",(-H40)+H38+H39) -> 88046.593 | I43: =IF(I19="","",(-I40)+I38+I39) -> 113707.12 | J43: =IF(J19="","",(-J40)+J38+J39) -> 115999.76 | K43: =IF(K19="","",(-K40)+K38+K39) -> 118293.42 | L43: =IF(L19="","",(-L40)+L38+L39) -> 120587.11 | M43: =IF(M19="","",(-M40)+M38+M39) -> 122879.84 | ... U43: =IF(U19="","",(-U40)+U38+U39) -> 3987352.3
B44: Sponsor EM | D44: =SUMIF(F43:U43,">0")/-SUMIF(F43:U43,"<0") -> 2.8928625
F46: =F19 -> 0 | G46: =G19 -> 1 | H46: =H19 -> 2 | I46: =I19 -> 3 | J46: =J19 -> 4 | K46: =K19 -> 5 | L46: =L19 -> 6 | M46: =M19 -> 7 | ... U46: =U19 -> 15
B47: Net Cash Flow For Distribution | E47: Year Ending | F47: =EOMONTH(G47,-12) -> 43830 | G47: =IF(G$46="","",'Property Returns'!D$5) -> 44196 | H47: =IF(H$46="","",'Property Returns'!E$5) -> 44196 | I47: =IF(I$46="","",'Property Returns'!F$5) -> 44926 | J47: =IF(J$46="","",'Property Returns'!G$5) -> 45291 | K47: =IF(K$46="","",'Property Returns'!H$5) -> 45657 | L47: =IF(L$46="","",'Property Returns'!I$5) -> 46022 | M47: =IF(M$46="","",'Property Returns'!J$5) -> 46387 | N47: =IF(N$46="","",'Property Returns'!K$5) -> 46752 | ... U47: =IF(U$46="","",'Property Returns'!R$5) -> 49309
B48: Net Property-Level Cash Flow | F48: =-Initial_Equity -> -19658792 | G48: =IF(G$19="","",'Property Returns'!D$35+(G$19=Effective_Hold_Period)*'Property Returns'!D$32) -> 520766.52 | H48: =IF(H$19="","",'Property Returns'!E$35+(H$19=Effective_Hold_Period)*'Property Returns'!E$32) -> 700465.93 | I48: =IF(I$19="","",'Property Returns'!F$35+(I$19=Effective_Hold_Period)*'Property Returns'!F$32) -> 957071.22 | J48: =IF(J$19="","",'Property Returns'!G$35+(J$19=Effective_Hold_Period)*'Property Returns'!G$32) -> 979997.63 | K48: =IF(K$19="","",'Property Returns'!H$35+(K$19=Effective_Hold_Period)*'Property Returns'!H$32) -> 1002934.2 | L48: =IF(L$19="","",'Property Returns'!I$35+(L$19=Effective_Hold_Period)*'Property Returns'!I$32) -> 1025871.1 | M48: =IF(M$19="","",'Property Returns'!J$35+(M$19=Effective_Hold_Period)*'Property Returns'!J$32) -> 1048798.4 | N48: =IF(N$19="","",'Property Returns'!K$35+(N$19=Effective_Hold_Period)*'Property Returns'!K$32) -> 1071705.4 | ... U48: =IF(U$19="","",'Property Returns'!R$35+(U$19=Effective_Hold_Period)*'Property Returns'!R$32) -> 21352091
B49: Management Fees | F49: 0 | G49: 20000 | H49: 20000 | I49: 20000 | J49: 20000 | K49: 20000 | L49: 20000 | M49: 20000 | N49: 20000 | O49: 20000 | P49: 20000 | Q49: 20000 | R49: 20000 | S49: 20000 | T49: 20000 | U49: 20000
B50: Acquisition/Disposition Fees | F50: 10000 | G50: 0 | H50: 0 | I50: 0 | J50: 0 | K50: 0 | L50: 0 | M50: 0 | N50: 0 | O50: 0 | P50: 0 | Q50: 0 | R50: 0 | S50: 0 | T50: 0 | U50: 10000
B51: Adjusted Net Property-Level Cash Flow | F51: =IF(F$46="","",F48-F49-F50) -> -19668792 | G51: =IF(G$46="","",G48-G49-G50) -> 500766.52 | H51: =IF(H$46="","",H48-H49-H50) -> 680465.93 | I51: =IF(I$46="","",I48-I49-I50) -> 937071.22 | J51: =IF(J$46="","",J48-J49-J50) -> 959997.63 | K51: =IF(K$46="","",K48-K49-K50) -> 982934.16 | L51: =IF(L$46="","",L48-L49-L50) -> 1005871.1 | M51: =IF(M$46="","",M48-M49-M50) -> 1028798.4 | ... U51: =IF(U$46="","",U48-U49-U50) -> 21322091
B53: Levered IRR | F53: =IF(AND(MIN(F$51:U$51)<0,MAX(F$51:U$51)>0),IRR(F$51:U$51)) -> 0.050565853
B54: Equity Multiple | F54: =SUMIF(F$51:U$51,">0")/-SUMIF(F$51:U$51,"<0") -> 1.7926059
B56: Return of Capital & Hurdle 1 (Preferred Return)
B57: Return Threshold - Up to: | C57: =IF($D$4="IRR",TEXT($E$14,"0.00%"),TEXT($E$14,"0.00x")) -> 8.00%
B58: LP Capital Account
B59: Beginning Balance | F59: =IF(F$46="","",0) -> 0 | G59: =IF(G$46="","",F$63) -> 17701913 | H59: =IF(H$46="","",G$63) -> 18667376 | I59: =IF(I$46="","",H$63) -> 19548346 | J59: =IF(J$46="","",I$63) -> 20268850 | K59: =IF(K$46="","",J$63) -> 21026360 | L59: =IF(L$46="","",K$63) -> 21823828 | M59: =IF(M$46="","",L$63) -> 22664450 | N59: =IF(N$46="","",M$63) -> 23551688 | ... U59: =IF(U$46="","",T$63) -> 31424745
B60: + Contributions This Period | F60: =IF(F$46="","",-MIN(0,F$51*Equity_Share_LPs)) -> 17701913 | G60: =IF(G$46="","",-MIN(0,G$51*Equity_Share_LPs)) -> 0 | H60: =IF(H$46="","",-MIN(0,H$51*Equity_Share_LPs)) -> 0 | I60: =IF(I$46="","",-MIN(0,I$51*Equity_Share_LPs)) -> 0 | J60: =IF(J$46="","",-MIN(0,J$51*Equity_Share_LPs)) -> 0 | K60: =IF(K$46="","",-MIN(0,K$51*Equity_Share_LPs)) -> 0 | L60: =IF(L$46="","",-MIN(0,L$51*Equity_Share_LPs)) -> 0 | M60: =IF(M$46="","",-MIN(0,M$51*Equity_Share_LPs)) -> 0 | ... U60: =IF(U$46="","",-MIN(0,U$51*Equity_Share_LPs)) -> 0
B61: + Pref Accrual | F61: =IF($D$4="IRR",F$59*Preferred_Return,0) -> 0 | G61: =IF($D$4="IRR",G$59*Preferred_Return,0) -> 1416153 | H61: =IF($D$4="IRR",H$59*Preferred_Return,0) -> 1493390.1 | I61: =IF($D$4="IRR",I$59*Preferred_Return,0) -> 1563867.7 | J61: =IF($D$4="IRR",J$59*Preferred_Return,0) -> 1621508 | K61: =IF($D$4="IRR",K$59*Preferred_Return,0) -> 1682108.8 | L61: =IF($D$4="IRR",L$59*Preferred_Return,0) -> 1745906.3 | M61: =IF($D$4="IRR",M$59*Preferred_Return,0) -> 1813156 | ... U61: =IF($D$4="IRR",U$59*Preferred_Return,0) -> 2513979.6
B62: - Distributions This Period | F62: =IF(F$46="","",IF($D$4="EM",MIN($F$73-F$74,MAX(F51,0)*$I$14),MIN(F59+F61,MAX(F51,0)*$I$14))) -> 0 | G62: =IF(G$46="","",IF($D$4="EM",MIN($F$73-G$74,MAX(G51,0)*$I$14),MIN(G59+G61,MAX(G51,0)*$I$14))) -> 450689.87 | H62: =IF(H$46="","",IF($D$4="EM",MIN($F$73-H$74,MAX(H51,0)*$I$14),MIN(H59+H61,MAX(H51,0)*$I$14))) -> 612419.34 | I62: =IF(I$46="","",IF($D$4="EM",MIN($F$73-I$74,MAX(I51,0)*$I$14),MIN(I59+I61,MAX(I51,0)*$I$14))) -> 843364.09 | J62: =IF(J$46="","",IF($D$4="EM",MIN($F$73-J$74,MAX(J51,0)*$I$14),MIN(J59+J61,MAX(J51,0)*$I$14))) -> 863997.86 | K62: =IF(K$46="","",IF($D$4="EM",MIN($F$73-K$74,MAX(K51,0)*$I$14),MIN(K59+K61,MAX(K51,0)*$I$14))) -> 884640.75 | L62: =IF(L$46="","",IF($D$4="EM",MIN($F$73-L$74,MAX(L51,0)*$I$14),MIN(L59+L61,MAX(L51,0)*$I$14))) -> 905284.02 | M62: =IF(M$46="","",IF($D$4="EM",MIN($F$73-M$74,MAX(M51,0)*$I$14),MIN(M59+M61,MAX(M51,0)*$I$14))) -> 925918.57 | ... U62: =IF(U$46="","",IF($D$4="EM",MIN($F$73-U$74,MAX(U51,0)*$I$14),MIN(U59+U61,MAX(U51,0)*$I$14))) -> 19189882
B63: Ending Balance | F63: =IF(F$46="","",IF($D$4="EM", MAX(F$59+F$60+F$61-F$62,0),F$59+F$60+F$61-F$62)) -> 17701913 | G63: =IF(G$46="","",IF($D$4="EM", MAX(G$59+G$60+G$61-G$62,0),G$59+G$60+G$61-G$62)) -> 18667376 | H63: =IF(H$46="","",IF($D$4="EM", MAX(H$59+H$60+H$61-H$62,0),H$59+H$60+H$61-H$62)) -> 19548346 | I63: =IF(I$46="","",IF($D$4="EM", MAX(I$59+I$60+I$61-I$62,0),I$59+I$60+I$61-I$62)) -> 20268850 | J63: =IF(J$46="","",IF($D$4="EM", MAX(J$59+J$60+J$61-J$62,0),J$59+J$60+J$61-J$62)) -> 21026360 | K63: =IF(K$46="","",IF($D$4="EM", MAX(K$59+K$60+K$61-K$62,0),K$59+K$60+K$61-K$62)) -> 21823828 | L63: =IF(L$46="","",IF($D$4="EM", MAX(L$59+L$60+L$61-L$62,0),L$59+L$60+L$61-L$62)) -> 22664450 | M63: =IF(M$46="","",IF($D$4="EM", MAX(M$59+M$60+M$61-M$62,0),M$59+M$60+M$61-M$62)) -> 23551688 | ... U63: =IF(U$46="","",IF($D$4="EM", MAX(U$59+U$60+U$61-U$62,0),U$59+U$60+U$61-U$62)) -> 14748842
B65: GP Capital Account
B66: Beginning Balance | F66: =IF(F$46="","",0) -> 0 | G66: =IF(G$46="","",F$70) -> 1966879.2 | H66: =IF(H$46="","",G$70) -> 2074152.9 | I66: =IF(I$46="","",H$70) -> 2172038.5 | J66: =IF(J$46="","",I$70) -> 2252094.4 | K66: =IF(K$46="","",J$70) -> 2336262.2 | L66: =IF(L$46="","",K$70) -> 2424869.8 | M66: =IF(M$46="","",L$70) -> 2518272.3 | N66: =IF(N$46="","",M$70) -> 2616854.2 | ... U66: =IF(U$46="","",T$70) -> 3491638.3
B67: + Contributions This Period | F67: =IF(F$46="","",-MIN(0,F$51*Equity_Share_Sponsor)) -> 1966879.2 | G67: =IF(G$46="","",-MIN(0,G$51*Equity_Share_Sponsor)) -> 0 | H67: =IF(H$46="","",-MIN(0,H$51*Equity_Share_Sponsor)) -> 0 | I67: =IF(I$46="","",-MIN(0,I$51*Equity_Share_Sponsor)) -> 0 | J67: =IF(J$46="","",-MIN(0,J$51*Equity_Share_Sponsor)) -> 0 | K67: =IF(K$46="","",-MIN(0,K$51*Equity_Share_Sponsor)) -> 0 | L67: =IF(L$46="","",-MIN(0,L$51*Equity_Share_Sponsor)) -> 0 | M67: =IF(M$46="","",-MIN(0,M$51*Equity_Share_Sponsor)) -> 0 | ... U67: =IF(U$46="","",-MIN(0,U$51*Equity_Share_Sponsor)) -> 0
B68: + Pref Accrual | F68: =IF($D$4="IRR",F$66*Preferred_Return,0) -> 0 | G68: =IF($D$4="IRR",G$66*Preferred_Return,0) -> 157350.33 | H68: =IF($D$4="IRR",H$66*Preferred_Return,0) -> 165932.23 | I68: =IF($D$4="IRR",I$66*Preferred_Return,0) -> 173763.08 | J68: =IF($D$4="IRR",J$66*Preferred_Return,0) -> 180167.56 | K68: =IF($D$4="IRR",K$66*Preferred_Return,0) -> 186900.98 | L68: =IF($D$4="IRR",L$66*Preferred_Return,0) -> 193989.58 | M68: =IF($D$4="IRR",M$66*Preferred_Return,0) -> 201461.78 | ... U68: =IF($D$4="IRR",U$66*Preferred_Return,0) -> 279331.06
B69: - Distributions This Period | F69: =IF(F$46="","",F$79) -> 0 | G69: =IF(G$46="","",G$79) -> 50076.652 | H69: =IF(H$46="","",H$79) -> 68046.593 | I69: =IF(I$46="","",I$79) -> 93707.122 | J69: =IF(J$46="","",J$79) -> 95999.763 | K69: =IF(K$46="","",K$79) -> 98293.416 | L69: =IF(L$46="","",L$79) -> 100587.11 | M69: =IF(M$46="","",M$79) -> 102879.84 | ... U69: =IF(U$46="","",U$79) -> 245130.2
B70: Ending Balance | F70: =IF(F$46="","",IF($D$4="EM",MAX(F$66+F$67+F$68-F$69,0),F$66+F$67+F$68-F$69)) -> 1966879.2 | G70: =IF(G$46="","",IF($D$4="EM",MAX(G$66+G$67+G$68-G$69,0),G$66+G$67+G$68-G$69)) -> 2074152.9 | H70: =IF(H$46="","",IF($D$4="EM",MAX(H$66+H$67+H$68-H$69,0),H$66+H$67+H$68-H$69)) -> 2172038.5 | I70: =IF(I$46="","",IF($D$4="EM",MAX(I$66+I$67+I$68-I$69,0),I$66+I$67+I$68-I$69)) -> 2252094.4 | J70: =IF(J$46="","",IF($D$4="EM",MAX(J$66+J$67+J$68-J$69,0),J$66+J$67+J$68-J$69)) -> 2336262.2 | K70: =IF(K$46="","",IF($D$4="EM",MAX(K$66+K$67+K$68-K$69,0),K$66+K$67+K$68-K$69)) -> 2424869.8 | L70: =IF(L$46="","",IF($D$4="EM",MAX(L$66+L$67+L$68-L$69,0),L$66+L$67+L$68-L$69)) -> 2518272.3 | M70: =IF(M$46="","",IF($D$4="EM",MAX(M$66+M$67+M$68-M$69,0),M$66+M$67+M$68-M$69)) -> 2616854.2 | ... U70: =IF(U$46="","",IF($D$4="EM",MAX(U$66+U$67+U$68-U$69,0),U$66+U$67+U$68-U$69)) -> 3525839.2
B72: Distribution Sizing
B73: LP total Entitlement at this Hurdle | F73: =IF($D$4="EM",(SUM($F$60:$U$60)*Preferred_Return),INDEX($F$63:$U$63,MATCH(Effective_Hold_Period,$F$46:$U$46,0))) -> 14748842
B74: - Prior Cumulative LP Distributions | F74: =IF(F$46="","",0) -> 0 | G74: =IF(G$46="","",SUM($F$62:F$62)) -> 0 | H74: =IF(H$46="","",SUM($F$62:G$62)) -> 450689.87 | I74: =IF(I$46="","",SUM($F$62:H$62)) -> 1063109.2 | J74: =IF(J$46="","",SUM($F$62:I$62)) -> 1906473.3 | K74: =IF(K$46="","",SUM($F$62:J$62)) -> 2770471.2 | L74: =IF(L$46="","",SUM($F$62:K$62)) -> 3655111.9 | M74: =IF(M$46="","",SUM($F$62:L$62)) -> 4560395.9 | N74: =IF(N$46="","",SUM($F$62:M$62)) -> 5486314.5 | ... U74: =IF(U$46="","",SUM($F$62:T$62)) -> 12542670
B75: Remaining LP Entitlement | F75: =IF(F$46="","",MAX($F$73-F$74,0)) -> 14748842 | G75: =IF(G$46="","",MAX($F$73-G$74,0)) -> 14748842 | H75: =IF(H$46="","",MAX($F$73-H$74,0)) -> 14298152 | I75: =IF(I$46="","",MAX($F$73-I$74,0)) -> 13685733 | J75: =IF(J$46="","",MAX($F$73-J$74,0)) -> 12842369 | K75: =IF(K$46="","",MAX($F$73-K$74,0)) -> 11978371 | L75: =IF(L$46="","",MAX($F$73-L$74,0)) -> 11093730 | M75: =IF(M$46="","",MAX($F$73-M$74,0)) -> 10188446 | ... U75: =IF(U$46="","",MAX($F$73-U$74,0)) -> 2206171.8
B77: Cash Flow Available This Period | F77: =IF(F$46="","",MAX(F$51,0)) -> 0 | G77: =IF(G$46="","",MAX(G$51,0)) -> 500766.52 | H77: =IF(H$46="","",MAX(H$51,0)) -> 680465.93 | I77: =IF(I$46="","",MAX(I$51,0)) -> 937071.22 | J77: =IF(J$46="","",MAX(J$51,0)) -> 959997.63 | K77: =IF(K$46="","",MAX(K$51,0)) -> 982934.16 | L77: =IF(L$46="","",MAX(L$51,0)) -> 1005871.1 | M77: =IF(M$46="","",MAX(M$51,0)) -> 1028798.4 | ... U77: =IF(U$46="","",MAX(U$51,0)) -> 21322091
B78: LP Distribution | F78: =IF(F$46="","",IF($D$5="LP First",MIN(F$75,F$77),MIN(F$75,F$77*$I$14))) -> 0 | G78: =IF(G$46="","",IF($D$5="LP First",MIN(G$75,G$77),MIN(G$75,G$77*$I$14))) -> 450689.87 | H78: =IF(H$46="","",IF($D$5="LP First",MIN(H$75,H$77),MIN(H$75,H$77*$I$14))) -> 612419.34 | I78: =IF(I$46="","",IF($D$5="LP First",MIN(I$75,I$77),MIN(I$75,I$77*$I$14))) -> 843364.09 | J78: =IF(J$46="","",IF($D$5="LP First",MIN(J$75,J$77),MIN(J$75,J$77*$I$14))) -> 863997.86 | K78: =IF(K$46="","",IF($D$5="LP First",MIN(K$75,K$77),MIN(K$75,K$77*$I$14))) -> 884640.75 | L78: =IF(L$46="","",IF($D$5="LP First",MIN(L$75,L$77),MIN(L$75,L$77*$I$14))) -> 905284.02 | M78: =IF(M$46="","",IF($D$5="LP First",MIN(M$75,M$77),MIN(M$75,M$77*$I$14))) -> 925918.57 | ... U78: =IF(U$46="","",IF($D$5="LP First",MIN(U$75,U$77),MIN(U$75,U$77*$I$14))) -> 2206171.8
B79: GP Distribution | F79: =IF(F$46="","",IF(GP_Only_No_LPs,F$77,IF($D$5="LP First",MAX(F$77-F$78,0),F$78/$I$14*$H$14))) -> 0 | G79: =IF(G$46="","",IF(GP_Only_No_LPs,G$77,IF($D$5="LP First",MAX(G$77-G$78,0),G$78/$I$14*$H$14))) -> 50076.652 | H79: =IF(H$46="","",IF(GP_Only_No_LPs,H$77,IF($D$5="LP First",MAX(H$77-H$78,0),H$78/$I$14*$H$14))) -> 68046.593 | I79: =IF(I$46="","",IF(GP_Only_No_LPs,I$77,IF($D$5="LP First",MAX(I$77-I$78,0),I$78/$I$14*$H$14))) -> 93707.122 | J79: =IF(J$46="","",IF(GP_Only_No_LPs,J$77,IF($D$5="LP First",MAX(J$77-J$78,0),J$78/$I$14*$H$14))) -> 95999.763 | K79: =IF(K$46="","",IF(GP_Only_No_LPs,K$77,IF($D$5="LP First",MAX(K$77-K$78,0),K$78/$I$14*$H$14))) -> 98293.416 | L79: =IF(L$46="","",IF(GP_Only_No_LPs,L$77,IF($D$5="LP First",MAX(L$77-L$78,0),L$78/$I$14*$H$14))) -> 100587.11 | M79: =IF(M$46="","",IF(GP_Only_No_LPs,M$77,IF($D$5="LP First",MAX(M$77-M$78,0),M$78/$I$14*$H$14))) -> 102879.84 | ... U79: =IF(U$46="","",IF(GP_Only_No_LPs,U$77,IF($D$5="LP First",MAX(U$77-U$78,0),U$78/$I$14*$H$14))) -> 245130.2
B80: Total Distributions This Period | F80: =IF(F$46="","",F$78+F$79) -> 0 | G80: =IF(G$46="","",G$78+G$79) -> 500766.52 | H80: =IF(H$46="","",H$78+H$79) -> 680465.93 | I80: =IF(I$46="","",I$78+I$79) -> 937071.22 | J80: =IF(J$46="","",J$78+J$79) -> 959997.63 | K80: =IF(K$46="","",K$78+K$79) -> 982934.16 | L80: =IF(L$46="","",L$78+L$79) -> 1005871.1 | M80: =IF(M$46="","",M$78+M$79) -> 1028798.4 | ... U80: =IF(U$46="","",U$78+U$79) -> 2451302
B81: Cash Flow Remaining | F81: =IF(F$46="","",MAX(F$77-F$80,0)) -> 0 | G81: =IF(G$46="","",MAX(G$77-G$80,0)) -> 0 | H81: =IF(H$46="","",MAX(H$77-H$80,0)) -> 0 | I81: =IF(I$46="","",MAX(I$77-I$80,0)) -> 0 | J81: =IF(J$46="","",MAX(J$77-J$80,0)) -> 0 | K81: =IF(K$46="","",MAX(K$77-K$80,0)) -> 0 | L81: =IF(L$46="","",MAX(L$77-L$80,0)) -> 0 | M81: =IF(M$46="","",MAX(M$77-M$80,0)) -> 0 | ... U81: =IF(U$46="","",MAX(U$77-U$80,0)) -> 18870789
B83: Hurdle 2
B84: Return Threshold - Up to: | C84: =IF($D$4="IRR",TEXT($E$15,"0.00%"),TEXT($E$15,"0.00x")) -> 12.00%
B85: Distribution Sizing
B86: LP total Entitlement at this Hurdle | F86: =IF($D$4="EM",SUM($F$60:$U$60)*$E$15,INDEX($F$63:$U$63,MATCH(Effective_Hold_Period,$F$46:$U$46,0))*($E$15/$E$14)) -> 22123263
B87: - Prior Cumulative LP Distributions | F87: =IF(F$46="","",0) -> 0 | G87: =IF(G$46="","",SUM($F$78:F$78)) -> 0 | H87: =IF(H$46="","",SUM($F$78:G$78)) -> 450689.87 | I87: =IF(I$46="","",SUM($F$78:H$78)) -> 1063109.2 | J87: =IF(J$46="","",SUM($F$78:I$78)) -> 1906473.3 | K87: =IF(K$46="","",SUM($F$78:J$78)) -> 2770471.2 | L87: =IF(L$46="","",SUM($F$78:K$78)) -> 3655111.9 | M87: =IF(M$46="","",SUM($F$78:L$78)) -> 4560395.9 | N87: =IF(N$46="","",SUM($F$78:M$78)) -> 5486314.5 | ... U87: =IF(U$46="","",SUM($F$78:T$78)) -> 12542670
B88: Remaining LP Entitlement | F88: =IF(F$46="","",MAX($F$86-F$87,0)) -> 22123263 | G88: =IF(G$46="","",MAX($F$86-G$87,0)) -> 22123263 | H88: =IF(H$46="","",MAX($F$86-H$87,0)) -> 21672573 | I88: =IF(I$46="","",MAX($F$86-I$87,0)) -> 21060154 | J88: =IF(J$46="","",MAX($F$86-J$87,0)) -> 20216790 | K88: =IF(K$46="","",MAX($F$86-K$87,0)) -> 19352792 | L88: =IF(L$46="","",MAX($F$86-L$87,0)) -> 18468151 | M88: =IF(M$46="","",MAX($F$86-M$87,0)) -> 17562867 | ... U88: =IF(U$46="","",MAX($F$86-U$87,0)) -> 9580592.8
B90: Cash Flow Available This Period | F90: =IF(F$46="","",MAX(F$81,0)) -> 0 | G90: =IF(G$46="","",MAX(G$81,0)) -> 0 | H90: =IF(H$46="","",MAX(H$81,0)) -> 0 | I90: =IF(I$46="","",MAX(I$81,0)) -> 0 | J90: =IF(J$46="","",MAX(J$81,0)) -> 0 | K90: =IF(K$46="","",MAX(K$81,0)) -> 0 | L90: =IF(L$46="","",MAX(L$81,0)) -> 0 | M90: =IF(M$46="","",MAX(M$81,0)) -> 0 | ... U90: =IF(U$46="","",MAX(U$81,0)) -> 18870789
B91: LP Distribution | F91: =IF(F$46="","",MIN(F$88,F$90*$I$15)) -> 0 | G91: =IF(G$46="","",MIN(G$88,G$90*$I$15)) -> 0 | H91: =IF(H$46="","",MIN(H$88,H$90*$I$15)) -> 0 | I91: =IF(I$46="","",MIN(I$88,I$90*$I$15)) -> 0 | J91: =IF(J$46="","",MIN(J$88,J$90*$I$15)) -> 0 | K91: =IF(K$46="","",MIN(K$88,K$90*$I$15)) -> 0 | L91: =IF(L$46="","",MIN(L$88,L$90*$I$15)) -> 0 | M91: =IF(M$46="","",MIN(M$88,M$90*$I$15)) -> 0 | ... U91: =IF(U$46="","",MIN(U$88,U$90*$I$15)) -> 9580592.8
B92: GP Distribution | F92: =IF(F$46="","",IF(GP_Only_No_LPs,F$90,F$91/$I$15*$H$15)) -> 0 | G92: =IF(G$46="","",IF(GP_Only_No_LPs,G$90,G$91/$I$15*$H$15)) -> 0 | H92: =IF(H$46="","",IF(GP_Only_No_LPs,H$90,H$91/$I$15*$H$15)) -> 0 | I92: =IF(I$46="","",IF(GP_Only_No_LPs,I$90,I$91/$I$15*$H$15)) -> 0 | J92: =IF(J$46="","",IF(GP_Only_No_LPs,J$90,J$91/$I$15*$H$15)) -> 0 | K92: =IF(K$46="","",IF(GP_Only_No_LPs,K$90,K$91/$I$15*$H$15)) -> 0 | L92: =IF(L$46="","",IF(GP_Only_No_LPs,L$90,L$91/$I$15*$H$15)) -> 0 | M92: =IF(M$46="","",IF(GP_Only_No_LPs,M$90,M$91/$I$15*$H$15)) -> 0 | ... U92: =IF(U$46="","",IF(GP_Only_No_LPs,U$90,U$91/$I$15*$H$15)) -> 2247299.5
B93: Total Distributions This Period | F93: =IF(F$46="","",F$91+F$92) -> 0 | G93: =IF(G$46="","",G$91+G$92) -> 0 | H93: =IF(H$46="","",H$91+H$92) -> 0 | I93: =IF(I$46="","",I$91+I$92) -> 0 | J93: =IF(J$46="","",J$91+J$92) -> 0 | K93: =IF(K$46="","",K$91+K$92) -> 0 | L93: =IF(L$46="","",L$91+L$92) -> 0 | M93: =IF(M$46="","",M$91+M$92) -> 0 | ... U93: =IF(U$46="","",U$91+U$92) -> 11827892
B94: Cash Flow Remaining | F94: =IF(F$46="","",MAX(F$90-F$93,0)) -> 0 | G94: =IF(G$46="","",MAX(G$90-G$93,0)) -> 0 | H94: =IF(H$46="","",MAX(H$90-H$93,0)) -> 0 | I94: =IF(I$46="","",MAX(I$90-I$93,0)) -> 0 | J94: =IF(J$46="","",MAX(J$90-J$93,0)) -> 0 | K94: =IF(K$46="","",MAX(K$90-K$93,0)) -> 0 | L94: =IF(L$46="","",MAX(L$90-L$93,0)) -> 0 | M94: =IF(M$46="","",MAX(M$90-M$93,0)) -> 0 | ... U94: =IF(U$46="","",MAX(U$90-U$93,0)) -> 7042897
B96: Hurdle 3
B97: Return Threshold - Up to: | C97: =IF($D$4="IRR",TEXT($E$16,"0.00%"),TEXT($E$16,"0.00x")) -> 15.00%
B98: Distribution Sizing
B99: LP total Entitlement at this Hurdle | F99: =IF($D$4="EM",SUM($F$60:$U$60)*$E$16,INDEX($F$63:$U$63,MATCH(Effective_Hold_Period,$F$46:$U$46,0))*($E$16/$E$14)) -> 27654079
B100: - Prior Cumulative LP Distributions | F100: =IF(F$46="","",0) -> 0 | G100: =IF(G$46="","",SUM($F$78:F$78)+SUM($F$91:F$91)) -> 0 | H100: =IF(H$46="","",SUM($F$78:G$78)+SUM($F$91:G$91)) -> 450689.87 | I100: =IF(I$46="","",SUM($F$78:H$78)+SUM($F$91:H$91)) -> 1063109.2 | J100: =IF(J$46="","",SUM($F$78:I$78)+SUM($F$91:I$91)) -> 1906473.3 | K100: =IF(K$46="","",SUM($F$78:J$78)+SUM($F$91:J$91)) -> 2770471.2 | L100: =IF(L$46="","",SUM($F$78:K$78)+SUM($F$91:K$91)) -> 3655111.9 | M100: =IF(M$46="","",SUM($F$78:L$78)+SUM($F$91:L$91)) -> 4560395.9 | N100: =IF(N$46="","",SUM($F$78:M$78)+SUM($F$91:M$91)) -> 5486314.5 | ... U100: =IF(U$46="","",SUM($F$78:T$78)+SUM($F$91:T$91)) -> 12542670
B101: Remaining LP Entitlement | F101: =IF(F$46="","",MAX($F$99-F$100,0)) -> 27654079 | G101: =IF(G$46="","",MAX($F$99-G$100,0)) -> 27654079 | H101: =IF(H$46="","",MAX($F$99-H$100,0)) -> 27203389 | I101: =IF(I$46="","",MAX($F$99-I$100,0)) -> 26590970 | J101: =IF(J$46="","",MAX($F$99-J$100,0)) -> 25747605 | K101: =IF(K$46="","",MAX($F$99-K$100,0)) -> 24883608 | L101: =IF(L$46="","",MAX($F$99-L$100,0)) -> 23998967 | M101: =IF(M$46="","",MAX($F$99-M$100,0)) -> 23093683 | ... U101: =IF(U$46="","",MAX($F$99-U$100,0)) -> 15111409
B103: Cash Flow Available This Period | F103: =IF(F$46="","",MAX(F$94,0)) -> 0 | G103: =IF(G$46="","",MAX(G$94,0)) -> 0 | H103: =IF(H$46="","",MAX(H$94,0)) -> 0 | I103: =IF(I$46="","",MAX(I$94,0)) -> 0 | J103: =IF(J$46="","",MAX(J$94,0)) -> 0 | K103: =IF(K$46="","",MAX(K$94,0)) -> 0 | L103: =IF(L$46="","",MAX(L$94,0)) -> 0 | M103: =IF(M$46="","",MAX(M$94,0)) -> 0 | ... U103: =IF(U$46="","",MAX(U$94,0)) -> 7042897
B104: LP Distribution | F104: =IF(F$46="","",MIN(F$101,F$103*$I$16)) -> 0 | G104: =IF(G$46="","",MIN(G$101,G$103*$I$16)) -> 0 | H104: =IF(H$46="","",MIN(H$101,H$103*$I$16)) -> 0 | I104: =IF(I$46="","",MIN(I$101,I$103*$I$16)) -> 0 | J104: =IF(J$46="","",MIN(J$101,J$103*$I$16)) -> 0 | K104: =IF(K$46="","",MIN(K$101,K$103*$I$16)) -> 0 | L104: =IF(L$46="","",MIN(L$101,L$103*$I$16)) -> 0 | M104: =IF(M$46="","",MIN(M$101,M$103*$I$16)) -> 0 | ... U104: =IF(U$46="","",MIN(U$101,U$103*$I$16)) -> 5577974.5
B105: GP Distribution | F105: =IF(F$46="","",IF(GP_Only_No_LPs,F$103,F$104/$I$16*$H$16)) -> 0 | G105: =IF(G$46="","",IF(GP_Only_No_LPs,G$103,G$104/$I$16*$H$16)) -> 0 | H105: =IF(H$46="","",IF(GP_Only_No_LPs,H$103,H$104/$I$16*$H$16)) -> 0 | I105: =IF(I$46="","",IF(GP_Only_No_LPs,I$103,I$104/$I$16*$H$16)) -> 0 | J105: =IF(J$46="","",IF(GP_Only_No_LPs,J$103,J$104/$I$16*$H$16)) -> 0 | K105: =IF(K$46="","",IF(GP_Only_No_LPs,K$103,K$104/$I$16*$H$16)) -> 0 | L105: =IF(L$46="","",IF(GP_Only_No_LPs,L$103,L$104/$I$16*$H$16)) -> 0 | M105: =IF(M$46="","",IF(GP_Only_No_LPs,M$103,M$104/$I$16*$H$16)) -> 0 | ... U105: =IF(U$46="","",IF(GP_Only_No_LPs,U$103,U$104/$I$16*$H$16)) -> 1464922.6
B106: Total Distributions This Period | F106: =IF(F$46="","",F$104+F$105) -> 0 | G106: =IF(G$46="","",G$104+G$105) -> 0 | H106: =IF(H$46="","",H$104+H$105) -> 0 | I106: =IF(I$46="","",I$104+I$105) -> 0 | J106: =IF(J$46="","",J$104+J$105) -> 0 | K106: =IF(K$46="","",K$104+K$105) -> 0 | L106: =IF(L$46="","",L$104+L$105) -> 0 | M106: =IF(M$46="","",M$104+M$105) -> 0 | ... U106: =IF(U$46="","",U$104+U$105) -> 7042897
B107: Cash Flow Remaining | F107: =IF(F$46="","",MAX(F$103-F$106,0)) -> 0 | G107: =IF(G$46="","",MAX(G$103-G$106,0)) -> 0 | H107: =IF(H$46="","",MAX(H$103-H$106,0)) -> 0 | I107: =IF(I$46="","",MAX(I$103-I$106,0)) -> 0 | J107: =IF(J$46="","",MAX(J$103-J$106,0)) -> 0 | K107: =IF(K$46="","",MAX(K$103-K$106,0)) -> 0 | L107: =IF(L$46="","",MAX(L$103-L$106,0)) -> 0 | M107: =IF(M$46="","",MAX(M$103-M$106,0)) -> 0 | ... U107: =IF(U$46="","",MAX(U$103-U$106,0)) -> 0
B109: Hurdle 4
B110: Return Threshold - Excess of: | C110: =IF($D$4="IRR",TEXT($E$16,"0.00%"),TEXT($E$16,"0.00x")) -> 15.00%
B111: Cash Flow Available This Period | F111: =IF(F$46="","",MAX(F$107,0)) -> 0 | G111: =IF(G$46="","",MAX(G$107,0)) -> 0 | H111: =IF(H$46="","",MAX(H$107,0)) -> 0 | I111: =IF(I$46="","",MAX(I$107,0)) -> 0 | J111: =IF(J$46="","",MAX(J$107,0)) -> 0 | K111: =IF(K$46="","",MAX(K$107,0)) -> 0 | L111: =IF(L$46="","",MAX(L$107,0)) -> 0 | M111: =IF(M$46="","",MAX(M$107,0)) -> 0 | ... U111: =IF(U$46="","",MAX(U$107,0)) -> 0
B112: LP Distribution | F112: =IF(F$46="","",F$111*$I$17) -> 0 | G112: =IF(G$46="","",G$111*$I$17) -> 0 | H112: =IF(H$46="","",H$111*$I$17) -> 0 | I112: =IF(I$46="","",I$111*$I$17) -> 0 | J112: =IF(J$46="","",J$111*$I$17) -> 0 | K112: =IF(K$46="","",K$111*$I$17) -> 0 | L112: =IF(L$46="","",L$111*$I$17) -> 0 | M112: =IF(M$46="","",M$111*$I$17) -> 0 | ... U112: =IF(U$46="","",U$111*$I$17) -> 0
B113: GP Distribution | F113: =IF(F$46="","",F$111*$H$17) -> 0 | G113: =IF(G$46="","",G$111*$H$17) -> 0 | H113: =IF(H$46="","",H$111*$H$17) -> 0 | I113: =IF(I$46="","",I$111*$H$17) -> 0 | J113: =IF(J$46="","",J$111*$H$17) -> 0 | K113: =IF(K$46="","",K$111*$H$17) -> 0 | L113: =IF(L$46="","",L$111*$H$17) -> 0 | M113: =IF(M$46="","",M$111*$H$17) -> 0 | ... U113: =IF(U$46="","",U$111*$H$17) -> 0
B114: Total Distributions This Period | F114: =IF(F$46="","",F$112+F$113) -> 0 | G114: =IF(G$46="","",G$112+G$113) -> 0 | H114: =IF(H$46="","",H$112+H$113) -> 0 | I114: =IF(I$46="","",I$112+I$113) -> 0 | J114: =IF(J$46="","",J$112+J$113) -> 0 | K114: =IF(K$46="","",K$112+K$113) -> 0 | L114: =IF(L$46="","",L$112+L$113) -> 0 | M114: =IF(M$46="","",M$112+M$113) -> 0 | ... U114: =IF(U$46="","",U$112+U$113) -> 0
B115: Cash Flow Remaining | F115: =IF(F$46="","",MAX(F$111-F$114,0)) -> 0 | G115: =IF(G$46="","",MAX(G$111-G$114,0)) -> 0 | H115: =IF(H$46="","",MAX(H$111-H$114,0)) -> 0 | I115: =IF(I$46="","",MAX(I$111-I$114,0)) -> 0 | J115: =IF(J$46="","",MAX(J$111-J$114,0)) -> 0 | K115: =IF(K$46="","",MAX(K$111-K$114,0)) -> 0 | L115: =IF(L$46="","",MAX(L$111-L$114,0)) -> 0 | M115: =IF(M$46="","",MAX(M$111-M$114,0)) -> 0 | ... U115: =IF(U$46="","",MAX(U$111-U$114,0)) -> 0

Sheet Debt
B2: Permanent Financing
C3: Year | D3: 1 | E3: =IF(OR(D$3="",D$3=Effective_Hold_Period),"",D3+1) -> 2 | F3: =IF(OR(E$3="",E$3=Effective_Hold_Period),"",E3+1) -> 3 | G3: =IF(OR(F$3="",F$3=Effective_Hold_Period),"",F3+1) -> 4 | H3: =IF(OR(G$3="",G$3=Effective_Hold_Period),"",G3+1) -> 5 | I3: =IF(OR(H$3="",H$3=Effective_Hold_Period),"",H3+1) -> 6 | J3: =IF(OR(I$3="",I$3=Effective_Hold_Period),"",I3+1) -> 7 | K3: =IF(OR(J$3="",J$3=Effective_Hold_Period),"",J3+1) -> 8 | L3: =IF(OR(K$3="",K$3=Effective_Hold_Period),"",K3+1) -> 9 | ... R3: =IF(OR(Q$3="",Q$3=Effective_Hold_Period),"",Q3+1) -> 15
C4: Year Ending | D4: =EOMONTH(Analysis_Start,11) -> 44196 | E4: =IF(E3="","",EOMONTH(Analysis_Start,(11*E3)+D3)) -> 44561 | F4: =IF(F3="","",EOMONTH(Analysis_Start,(11*F3)+E3)) -> 44926 | G4: =IF(G3="","",EOMONTH(Analysis_Start,(11*G3)+F3)) -> 45291 | H4: =IF(H3="","",EOMONTH(Analysis_Start,(11*H3)+G3)) -> 45657 | I4: =IF(I3="","",EOMONTH(Analysis_Start,(11*I3)+H3)) -> 46022 | J4: =IF(J3="","",EOMONTH(Analysis_Start,(11*J3)+I3)) -> 46387 | K4: =IF(K3="","",EOMONTH(Analysis_Start,(11*K3)+J3)) -> 46752 | L4: =IF(L3="","",EOMONTH(Analysis_Start,(11*L3)+K3)) -> 47118 | ... R4: =IF(R3="","",EOMONTH(Analysis_Start,(11*R3)+Q3)) -> 49309
B5: Property Name: | C5: ='Property Summary'!$C$3 -> XYZ Condos
C6: Debt Service | D6: =IF(D4="","",IF(VLOOKUP($C5,'Property Assumptions'!$C$5:$V$5,14,FALSE)<D$3,VLOOKUP($C5,'Property Assumptions'!$C$5:$V$5,11,FALSE),VLOOKUP($C5,'Property Assumptions'!$C$5:$V$5,12,FALSE))) -> 1331881 | E6: =IF(E4="","",IF(VLOOKUP($C5,'Property Assumptions'!$C$5:$V$5,14,FALSE)<E$3,VLOOKUP($C5,'Property Assumptions'!$C$5:$V$5,11,FALSE),VLOOKUP($C5,'Property Assumptions'!$C$5:$V$5,12,FALSE))) -> 1331881 | F6: =IF(F4="","",IF(VLOOKUP($C5,'Property Assumptions'!$C$5:$V$5,14,FALSE)<F$3,VLOOKUP($C5,'Property Assumptions'!$C$5:$V$5,11,FALSE),VLOOKUP($C5,'Property Assumptions'!$C$5:$V$5,12,FALSE))) -> 1331881 | G6: =IF(G4="","",IF(VLOOKUP($C5,'Property Assumptions'!$C$5:$V$5,14,FALSE)<G$3,VLOOKUP($C5,'Property Assumptions'!$C$5:$V$5,11,FALSE),VLOOKUP($C5,'Property Assumptions'!$C$5:$V$5,12,FALSE))) -> 1331881 | H6: =IF(H4="","",IF(VLOOKUP($C5,'Property Assumptions'!$C$5:$V$5,14,FALSE)<H$3,VLOOKUP($C5,'Property Assumptions'!$C$5:$V$5,11,FALSE),VLOOKUP($C5,'Property Assumptions'!$C$5:$V$5,12,FALSE))) -> 1331881 | I6: =IF(I4="","",IF(VLOOKUP($C5,'Property Assumptions'!$C$5:$V$5,14,FALSE)<I$3,VLOOKUP($C5,'Property Assumptions'!$C$5:$V$5,11,FALSE),VLOOKUP($C5,'Property Assumptions'!$C$5:$V$5,12,FALSE))) -> 1331881 | J6: =IF(J4="","",IF(VLOOKUP($C5,'Property Assumptions'!$C$5:$V$5,14,FALSE)<J$3,VLOOKUP($C5,'Property Assumptions'!$C$5:$V$5,11,FALSE),VLOOKUP($C5,'Property Assumptions'!$C$5:$V$5,12,FALSE))) -> 1331881 | K6: =IF(K4="","",IF(VLOOKUP($C5,'Property Assumptions'!$C$5:$V$5,14,FALSE)<K$3,VLOOKUP($C5,'Property Assumptions'!$C$5:$V$5,11,FALSE),VLOOKUP($C5,'Property Assumptions'!$C$5:$V$5,12,FALSE))) -> 1331881 | ... R6: =IF(R4="","",IF(VLOOKUP($C5,'Property Assumptions'!$C$5:$V$5,14,FALSE)<R$3,VLOOKUP($C5,'Property Assumptions'!$C$5:$V$5,11,FALSE),VLOOKUP($C5,'Property Assumptions'!$C$5:$V$5,12,FALSE))) -> 1331881
C7: Loan Balance | D7: =IF(D3="","",IF(D3<='Property Summary'!$F$27,Debt,-PV('Property Summary'!$F$26/12,(('Property Summary'!$F$28-D$3)+'Property Summary'!$F$28)*12,PMT('Property Summary'!$F$26/12,'Property Summary'!$F$28*12,-Debt)))) -> 18112533 | E7: =IF(E3="","",IF(E3<='Property Summary'!$F$27,Debt,-PV('Property Summary'!$F$26/12,(('Property Summary'!$F$28-E$3)+'Property Summary'!$F$28)*12,PMT('Property Summary'!$F$26/12,'Property Summary'!$F$28*12,-Debt)))) -> 18093176 | F7: =IF(F3="","",IF(F3<='Property Summary'!$F$27,Debt,-PV('Property Summary'!$F$26/12,(('Property Summary'!$F$28-F$3)+'Property Summary'!$F$28)*12,PMT('Property Summary'!$F$26/12,'Property Summary'!$F$28*12,-Debt)))) -> 18072368 | G7: =IF(G3="","",IF(G3<='Property Summary'!$F$27,Debt,-PV('Property Summary'!$F$26/12,(('Property Summary'!$F$28-G$3)+'Property Summary'!$F$28)*12,PMT('Property Summary'!$F$26/12,'Property Summary'!$F$28*12,-Debt)))) -> 18050000 | H7: =IF(H3="","",IF(H3<='Property Summary'!$F$27,Debt,-PV('Property Summary'!$F$26/12,(('Property Summary'!$F$28-H$3)+'Property Summary'!$F$28)*12,PMT('Property Summary'!$F$26/12,'Property Summary'!$F$28*12,-Debt)))) -> 18025955 | I7: =IF(I3="","",IF(I3<='Property Summary'!$F$27,Debt,-PV('Property Summary'!$F$26/12,(('Property Summary'!$F$28-I$3)+'Property Summary'!$F$28)*12,PMT('Property Summary'!$F$26/12,'Property Summary'!$F$28*12,-Debt)))) -> 18000108 | J7: =IF(J3="","",IF(J3<='Property Summary'!$F$27,Debt,-PV('Property Summary'!$F$26/12,(('Property Summary'!$F$28-J$3)+'Property Summary'!$F$28)*12,PMT('Property Summary'!$F$26/12,'Property Summary'!$F$28*12,-Debt)))) -> 17972324 | K7: =IF(K3="","",IF(K3<='Property Summary'!$F$27,Debt,-PV('Property Summary'!$F$26/12,(('Property Summary'!$F$28-K$3)+'Property Summary'!$F$28)*12,PMT('Property Summary'!$F$26/12,'Property Summary'!$F$28*12,-Debt)))) -> 17942457 | ... R7: =IF(R3="","",IF(R3<='Property Summary'!$F$27,Debt,-PV('Property Summary'!$F$26/12,(('Property Summary'!$F$28-R$3)+'Property Summary'!$F$28)*12,PMT('Property Summary'!$F$26/12,'Property Summary'!$F$28*12,-Debt)))) -> 17660369

Sheet Calculations
B2: Inputs (from Rent Roll/Unit Mix)
P3: Blended
B4: Unit Type | C4: # of Units | D4: Beds | E4: Baths | F4: ="Rentable Area ("&'Property Summary'!$I$26&")" -> Rentable Area (SQFT) | G4: In-Place Rent/Mo. | H4: Market Rent/Mo. | I4: Month to Roll to Market | J4: Lease Term | K4: CapEx/Unit/Mo. | L4: Free Rent Per Lease | M4: Days Vacant Between Leases | N4: Releasing Cost per Unit | O4: Probability of Renewal | P4: Free Rent | Q4: Days Vacant | R4: Releasing Cost
B5: ='Rent Roll'!B5 -> Studio | C5: ='Rent Roll'!C5 -> 22 | D5: ='Rent Roll'!D5 -> 0 | E5: ='Rent Roll'!E5 -> 1 | F5: ='Rent Roll'!F5 -> 470 | G5: ='Rent Roll'!G5 -> 2200 | H5: ='Rent Roll'!H5 -> 2350 | I5: ='Rent Roll'!I5 -> 13 | ... O5: ='Rent Roll'!O5 -> 0.6 | P5: =IF($B5<>"", (1-$O5)*$L5, "") -> 0 | Q5: =IF($B5<>"", (1-$O5)*$M5, "") -> 10 | R5: =IF($B5<>"", (1-$O5)*$N5, "") -> 160
B6: ='Rent Roll'!B6 -> 1bd/1ba | C6: ='Rent Roll'!C6 -> 24 | D6: ='Rent Roll'!D6 -> 1 | E6: ='Rent Roll'!E6 -> 1 | F6: ='Rent Roll'!F6 -> 630 | G6: ='Rent Roll'!G6 -> 2340 | H6: ='Rent Roll'!H6 -> 2500 | I6: ='Rent Roll'!I6 -> 16 | ... O6: ='Rent Roll'!O6 -> 0.6 | P6: =IF($B6<>"", (1-$O6)*$L6, "") -> 0 | Q6: =IF($B6<>"", (1-$O6)*$M6, "") -> 10 | R6: =IF($B6<>"", (1-$O6)*$N6, "") -> 160
B7: ='Rent Roll'!B7 -> 2bd/2ba | C7: ='Rent Roll'!C7 -> 20 | D7: ='Rent Roll'!D7 -> 2 | E7: ='Rent Roll'!E7 -> 2 | F7: ='Rent Roll'!F7 -> 955 | G7: ='Rent Roll'!G7 -> 4800 | H7: ='Rent Roll'!H7 -> 4950 | I7: ='Rent Roll'!I7 -> 19 | ... O7: ='Rent Roll'!O7 -> 0.6 | P7: =IF($B7<>"", (1-$O7)*$L7, "") -> 0 | Q7: =IF($B7<>"", (1-$O7)*$M7, "") -> 11.2 | R7: =IF($B7<>"", (1-$O7)*$N7, "") -> 220
B8: ='Rent Roll'!B8 -> 3bd/3ba | C8: ='Rent Roll'!C8 -> 8 | D8: ='Rent Roll'!D8 -> 3 | E8: ='Rent Roll'!E8 -> 3 | F8: ='Rent Roll'!F8 -> 1120 | G8: ='Rent Roll'!G8 -> 5400 | H8: ='Rent Roll'!H8 -> 5500 | I8: ='Rent Roll'!I8 -> 14 | ... O8: ='Rent Roll'!O8 -> 0.6 | P8: =IF($B8<>"", (1-$O8)*$L8, "") -> 0 | Q8: =IF($B8<>"", (1-$O8)*$M8, "") -> 12.8 | R8: =IF($B8<>"", (1-$O8)*$N8, "") -> 240
B9: ='Rent Roll'!B9 -> 4bd/4ba | C9: ='Rent Roll'!C9 -> 6 | D9: ='Rent Roll'!D9 -> 4 | E9: ='Rent Roll'!E9 -> 4 | F9: ='Rent Roll'!F9 -> 1500 | G9: ='Rent Roll'!G9 -> 5900 | H9: ='Rent Roll'!H9 -> 6150 | I9: ='Rent Roll'!I9 -> 20 | ... O9: ='Rent Roll'!O9 -> 0.6 | P9: =IF($B9<>"", (1-$O9)*$L9, "") -> 0 | Q9: =IF($B9<>"", (1-$O9)*$M9, "") -> 15.2 | R9: =IF($B9<>"", (1-$O9)*$N9, "") -> 320
B12: Rents
B13: Year | C13: =ROUNDUP(C14/12,0) -> 1 | D13: =ROUNDUP(D14/12,0) -> 1 | E13: =ROUNDUP(E14/12,0) -> 1 | F13: =ROUNDUP(F14/12,0) -> 1 | G13: =ROUNDUP(G14/12,0) -> 1 | H13: =ROUNDUP(H14/12,0) -> 1 | I13: =ROUNDUP(I14/12,0) -> 1 | J13: =ROUNDUP(J14/12,0) -> 1 | ... FZ13: =ROUNDUP(FZ14/12,0) -> 15
B14: Month | C14: 1 | D14: =C14+1 -> 2 | E14: =D14+1 -> 3 | F14: =E14+1 -> 4 | G14: =F14+1 -> 5 | H14: =G14+1 -> 6 | I14: =H14+1 -> 7 | J14: =I14+1 -> 8 | K14: =J14+1 -> 9 | ... FZ14: =FY14+1 -> 180
B15: Month Ending | C15: =EOMONTH(Analysis_Start,0) -> 43861 | D15: =EOMONTH(C15,1) -> 43890 | E15: =EOMONTH(D15,1) -> 43921 | F15: =EOMONTH(E15,1) -> 43951 | G15: =EOMONTH(F15,1) -> 43982 | H15: =EOMONTH(G15,1) -> 44012 | I15: =EOMONTH(H15,1) -> 44043 | J15: =EOMONTH(I15,1) -> 44074 | K15: =EOMONTH(J15,1) -> 44104 | ... FZ15: =EOMONTH(FY15,1) -> 49309
C16: =IF(OR($B5="",$B5=0),"",($G5*(C$14<$I5)+$H5*(C$14>=$I5))*$C5*(1+'Property Summary'!$I$18)^(C$13-1)) -> 48400 | D16: =IF(OR($B5="",$B5=0),"",($G5*(D$14<$I5)+$H5*(D$14>=$I5))*$C5*(1+'Property Summary'!$I$18)^(D$13-1)) -> 48400 | E16: =IF(OR($B5="",$B5=0),"",($G5*(E$14<$I5)+$H5*(E$14>=$I5))*$C5*(1+'Property Summary'!$I$18)^(E$13-1)) -> 48400 | F16: =IF(OR($B5="",$B5=0),"",($G5*(F$14<$I5)+$H5*(F$14>=$I5))*$C5*(1+'Property Summary'!$I$18)^(F$13-1)) -> 48400 | G16: =IF(OR($B5="",$B5=0),"",($G5*(G$14<$I5)+$H5*(G$14>=$I5))*$C5*(1+'Property Summary'!$I$18)^(G$13-1)) -> 48400 | H16: =IF(OR($B5="",$B5=0),"",($G5*(H$14<$I5)+$H5*(H$14>=$I5))*$C5*(1+'Property Summary'!$I$18)^(H$13-1)) -> 48400 | I16: =IF(OR($B5="",$B5=0),"",($G5*(I$14<$I5)+$H5*(I$14>=$I5))*$C5*(1+'Property Summary'!$I$18)^(I$13-1)) -> 48400 | J16: =IF(OR($B5="",$B5=0),"",($G5*(J$14<$I5)+$H5*(J$14>=$I5))*$C5*(1+'Property Summary'!$I$18)^(J$13-1)) -> 48400 | ... FZ16: =IF(OR($B5="",$B5=0),"",($G5*(FZ$14<$I5)+$H5*(FZ$14>=$I5))*$C5*(1+'Property Summary'!$I$18)^(FZ$13-1)) -> 63681.771
C17: =IF(OR($B6="",$B6=0),"",($G6*(C$14<$I6)+$H6*(C$14>=$I6))*$C6*(1+'Property Summary'!$I$18)^(C$13-1)) -> 56160 | D17: =IF(OR($B6="",$B6=0),"",($G6*(D$14<$I6)+$H6*(D$14>=$I6))*$C6*(1+'Property Summary'!$I$18)^(D$13-1)) -> 56160 | E17: =IF(OR($B6="",$B6=0),"",($G6*(E$14<$I6)+$H6*(E$14>=$I6))*$C6*(1+'Property Summary'!$I$18)^(E$13-1)) -> 56160 | F17: =IF(OR($B6="",$B6=0),"",($G6*(F$14<$I6)+$H6*(F$14>=$I6))*$C6*(1+'Property Summary'!$I$18)^(F$13-1)) -> 56160 | G17: =IF(OR($B6="",$B6=0),"",($G6*(G$14<$I6)+$H6*(G$14>=$I6))*$C6*(1+'Property Summary'!$I$18)^(G$13-1)) -> 56160 | H17: =IF(OR($B6="",$B6=0),"",($G6*(H$14<$I6)+$H6*(H$14>=$I6))*$C6*(1+'Property Summary'!$I$18)^(H$13-1)) -> 56160 | I17: =IF(OR($B6="",$B6=0),"",($G6*(I$14<$I6)+$H6*(I$14>=$I6))*$C6*(1+'Property Summary'!$I$18)^(I$13-1)) -> 56160 | J17: =IF(OR($B6="",$B6=0),"",($G6*(J$14<$I6)+$H6*(J$14>=$I6))*$C6*(1+'Property Summary'!$I$18)^(J$13-1)) -> 56160 | ... FZ17: =IF(OR($B6="",$B6=0),"",($G6*(FZ$14<$I6)+$H6*(FZ$14>=$I6))*$C6*(1+'Property Summary'!$I$18)^(FZ$13-1)) -> 73905.344
C18: =IF(OR($B7="",$B7=0),"",($G7*(C$14<$I7)+$H7*(C$14>=$I7))*$C7*(1+'Property Summary'!$I$18)^(C$13-1)) -> 96000 | D18: =IF(OR($B7="",$B7=0),"",($G7*(D$14<$I7)+$H7*(D$14>=$I7))*$C7*(1+'Property Summary'!$I$18)^(D$13-1)) -> 96000 | E18: =IF(OR($B7="",$B7=0),"",($G7*(E$14<$I7)+$H7*(E$14>=$I7))*$C7*(1+'Property Summary'!$I$18)^(E$13-1)) -> 96000 | F18: =IF(OR($B7="",$B7=0),"",($G7*(F$14<$I7)+$H7*(F$14>=$I7))*$C7*(1+'Property Summary'!$I$18)^(F$13-1)) -> 96000 | G18: =IF(OR($B7="",$B7=0),"",($G7*(G$14<$I7)+$H7*(G$14>=$I7))*$C7*(1+'Property Summary'!$I$18)^(G$13-1)) -> 96000 | H18: =IF(OR($B7="",$B7=0),"",($G7*(H$14<$I7)+$H7*(H$14>=$I7))*$C7*(1+'Property Summary'!$I$18)^(H$13-1)) -> 96000 | I18: =IF(OR($B7="",$B7=0),"",($G7*(I$14<$I7)+$H7*(I$14>=$I7))*$C7*(1+'Property Summary'!$I$18)^(I$13-1)) -> 96000 | J18: =IF(OR($B7="",$B7=0),"",($G7*(J$14<$I7)+$H7*(J$14>=$I7))*$C7*(1+'Property Summary'!$I$18)^(J$13-1)) -> 96000 | ... FZ18: =IF(OR($B7="",$B7=0),"",($G7*(FZ$14<$I7)+$H7*(FZ$14>=$I7))*$C7*(1+'Property Summary'!$I$18)^(FZ$13-1)) -> 121943.82
C19: =IF(OR($B8="",$B8=0),"",($G8*(C$14<$I8)+$H8*(C$14>=$I8))*$C8*(1+'Property Summary'!$I$18)^(C$13-1)) -> 43200 | D19: =IF(OR($B8="",$B8=0),"",($G8*(D$14<$I8)+$H8*(D$14>=$I8))*$C8*(1+'Property Summary'!$I$18)^(D$13-1)) -> 43200 | E19: =IF(OR($B8="",$B8=0),"",($G8*(E$14<$I8)+$H8*(E$14>=$I8))*$C8*(1+'Property Summary'!$I$18)^(E$13-1)) -> 43200 | F19: =IF(OR($B8="",$B8=0),"",($G8*(F$14<$I8)+$H8*(F$14>=$I8))*$C8*(1+'Property Summary'!$I$18)^(F$13-1)) -> 43200 | G19: =IF(OR($B8="",$B8=0),"",($G8*(G$14<$I8)+$H8*(G$14>=$I8))*$C8*(1+'Property Summary'!$I$18)^(G$13-1)) -> 43200 | H19: =IF(OR($B8="",$B8=0),"",($G8*(H$14<$I8)+$H8*(H$14>=$I8))*$C8*(1+'Property Summary'!$I$18)^(H$13-1)) -> 43200 | I19: =IF(OR($B8="",$B8=0),"",($G8*(I$14<$I8)+$H8*(I$14>=$I8))*$C8*(1+'Property Summary'!$I$18)^(I$13-1)) -> 43200 | J19: =IF(OR($B8="",$B8=0),"",($G8*(J$14<$I8)+$H8*(J$14>=$I8))*$C8*(1+'Property Summary'!$I$18)^(J$13-1)) -> 43200 | ... FZ19: =IF(OR($B8="",$B8=0),"",($G8*(FZ$14<$I8)+$H8*(FZ$14>=$I8))*$C8*(1+'Property Summary'!$I$18)^(FZ$13-1)) -> 54197.252
C20: =IF(OR($B9="",$B9=0),"",($G9*(C$14<$I9)+$H9*(C$14>=$I9))*$C9*(1+'Property Summary'!$I$18)^(C$13-1)) -> 35400 | D20: =IF(OR($B9="",$B9=0),"",($G9*(D$14<$I9)+$H9*(D$14>=$I9))*$C9*(1+'Property Summary'!$I$18)^(D$13-1)) -> 35400 | E20: =IF(OR($B9="",$B9=0),"",($G9*(E$14<$I9)+$H9*(E$14>=$I9))*$C9*(1+'Property Summary'!$I$18)^(E$13-1)) -> 35400 | F20: =IF(OR($B9="",$B9=0),"",($G9*(F$14<$I9)+$H9*(F$14>=$I9))*$C9*(1+'Property Summary'!$I$18)^(F$13-1)) -> 35400 | G20: =IF(OR($B9="",$B9=0),"",($G9*(G$14<$I9)+$H9*(G$14>=$I9))*$C9*(1+'Property Summary'!$I$18)^(G$13-1)) -> 35400 | H20: =IF(OR($B9="",$B9=0),"",($G9*(H$14<$I9)+$H9*(H$14>=$I9))*$C9*(1+'Property Summary'!$I$18)^(H$13-1)) -> 35400 | I20: =IF(OR($B9="",$B9=0),"",($G9*(I$14<$I9)+$H9*(I$14>=$I9))*$C9*(1+'Property Summary'!$I$18)^(I$13-1)) -> 35400 | J20: =IF(OR($B9="",$B9=0),"",($G9*(J$14<$I9)+$H9*(J$14>=$I9))*$C9*(1+'Property Summary'!$I$18)^(J$13-1)) -> 35400 | ... FZ20: =IF(OR($B9="",$B9=0),"",($G9*(FZ$14<$I9)+$H9*(FZ$14>=$I9))*$C9*(1+'Property Summary'!$I$18)^(FZ$13-1)) -> 45451.786
B22: Total | C22: =SUM(C16:C21) -> 279160 | D22: =SUM(D16:D21) -> 279160 | E22: =SUM(E16:E21) -> 279160 | F22: =SUM(F16:F21) -> 279160 | G22: =SUM(G16:G21) -> 279160 | H22: =SUM(H16:H21) -> 279160 | I22: =SUM(I16:I21) -> 279160 | J22: =SUM(J16:J21) -> 279160 | ... FZ22: =SUM(FZ16:FZ21) -> 359179.97
B24: CapEx
B25: Year | C25: =ROUNDUP(C26/12,0) -> 1 | D25: =ROUNDUP(D26/12,0) -> 1 | E25: =ROUNDUP(E26/12,0) -> 1 | F25: =ROUNDUP(F26/12,0) -> 1 | G25: =ROUNDUP(G26/12,0) -> 1 | H25: =ROUNDUP(H26/12,0) -> 1 | I25: =ROUNDUP(I26/12,0) -> 1 | J25: =ROUNDUP(J26/12,0) -> 1 | ... FZ25: =ROUNDUP(FZ26/12,0) -> 15
B26: Month | C26: 1 | D26: =C26+1 -> 2 | E26: =D26+1 -> 3 | F26: =E26+1 -> 4 | G26: =F26+1 -> 5 | H26: =G26+1 -> 6 | I26: =H26+1 -> 7 | J26: =I26+1 -> 8 | K26: =J26+1 -> 9 | ... FZ26: =FY26+1 -> 180
B27: Month Ending | C27: =EOMONTH(Analysis_Start,0) -> 43861 | D27: =EOMONTH(C15,1) -> 43890 | E27: =EOMONTH(D15,1) -> 43921 | F27: =EOMONTH(E15,1) -> 43951 | G27: =EOMONTH(F15,1) -> 43982 | H27: =EOMONTH(G15,1) -> 44012 | I27: =EOMONTH(H15,1) -> 44043 | J27: =EOMONTH(I15,1) -> 44074 | K27: =EOMONTH(J15,1) -> 44104 | ... FZ27: =EOMONTH(FY15,1) -> 49309
C28: =IF(OR($B5="",$B5=0),"",($K5*$C5*(1+'Property Summary'!$I$21)^(C$13-1))) -> 1540 | D28: =IF(OR($B5="",$B5=0),"",($K5*$C5*(1+'Property Summary'!$I$21)^(D$13-1))) -> 1540 | E28: =IF(OR($B5="",$B5=0),"",($K5*$C5*(1+'Property Summary'!$I$21)^(E$13-1))) -> 1540 | F28: =IF(OR($B5="",$B5=0),"",($K5*$C5*(1+'Property Summary'!$I$21)^(F$13-1))) -> 1540 | G28: =IF(OR($B5="",$B5=0),"",($K5*$C5*(1+'Property Summary'!$I$21)^(G$13-1))) -> 1540 | H28: =IF(OR($B5="",$B5=0),"",($K5*$C5*(1+'Property Summary'!$I$21)^(H$13-1))) -> 1540 | I28: =IF(OR($B5="",$B5=0),"",($K5*$C5*(1+'Property Summary'!$I$21)^(I$13-1))) -> 1540 | J28: =IF(OR($B5="",$B5=0),"",($K5*$C5*(1+'Property Summary'!$I$21)^(J$13-1))) -> 1540 | ... FZ28: =IF(OR($B5="",$B5=0),"",($K5*$C5*(1+'Property Summary'!$I$21)^(FZ$13-1))) -> 2175.9797
C29: =IF(OR($B6="",$B6=0),"",($K6*$C6*(1+'Property Summary'!$I$21)^(C$13-1))) -> 1800 | D29: =IF(OR($B6="",$B6=0),"",($K6*$C6*(1+'Property Summary'!$I$21)^(D$13-1))) -> 1800 | E29: =IF(OR($B6="",$B6=0),"",($K6*$C6*(1+'Property Summary'!$I$21)^(E$13-1))) -> 1800 | F29: =IF(OR($B6="",$B6=0),"",($K6*$C6*(1+'Property Summary'!$I$21)^(F$13-1))) -> 1800 | G29: =IF(OR($B6="",$B6=0),"",($K6*$C6*(1+'Property Summary'!$I$21)^(G$13-1))) -> 1800 | H29: =IF(OR($B6="",$B6=0),"",($K6*$C6*(1+'Property Summary'!$I$21)^(H$13-1))) -> 1800 | I29: =IF(OR($B6="",$B6=0),"",($K6*$C6*(1+'Property Summary'!$I$21)^(I$13-1))) -> 1800 | J29: =IF(OR($B6="",$B6=0),"",($K6*$C6*(1+'Property Summary'!$I$21)^(J$13-1))) -> 1800 | ... FZ29: =IF(OR($B6="",$B6=0),"",($K6*$C6*(1+'Property Summary'!$I$21)^(FZ$13-1))) -> 2543.3529
C30: =IF(OR($B7="",$B7=0),"",($K7*$C7*(1+'Property Summary'!$I$21)^(C$13-1))) -> 2400 | D30: =IF(OR($B7="",$B7=0),"",($K7*$C7*(1+'Property Summary'!$I$21)^(D$13-1))) -> 2400 | E30: =IF(OR($B7="",$B7=0),"",($K7*$C7*(1+'Property Summary'!$I$21)^(E$13-1))) -> 2400 | F30: =IF(OR($B7="",$B7=0),"",($K7*$C7*(1+'Property Summary'!$I$21)^(F$13-1))) -> 2400 | G30: =IF(OR($B7="",$B7=0),"",($K7*$C7*(1+'Property Summary'!$I$21)^(G$13-1))) -> 2400 | H30: =IF(OR($B7="",$B7=0),"",($K7*$C7*(1+'Property Summary'!$I$21)^(H$13-1))) -> 2400 | I30: =IF(OR($B7="",$B7=0),"",($K7*$C7*(1+'Property Summary'!$I$21)^(I$13-1))) -> 2400 | J30: =IF(OR($B7="",$B7=0),"",($K7*$C7*(1+'Property Summary'!$I$21)^(J$13-1))) -> 2400 | ... FZ30: =IF(OR($B7="",$B7=0),"",($K7*$C7*(1+'Property Summary'!$I$21)^(FZ$13-1))) -> 3391.1372
C31: =IF(OR($B8="",$B8=0),"",($K8*$C8*(1+'Property Summary'!$I$21)^(C$13-1))) -> 1280 | D31: =IF(OR($B8="",$B8=0),"",($K8*$C8*(1+'Property Summary'!$I$21)^(D$13-1))) -> 1280 | E31: =IF(OR($B8="",$B8=0),"",($K8*$C8*(1+'Property Summary'!$I$21)^(E$13-1))) -> 1280 | F31: =IF(OR($B8="",$B8=0),"",($K8*$C8*(1+'Property Summary'!$I$21)^(F$13-1))) -> 1280 | G31: =IF(OR($B8="",$B8=0),"",($K8*$C8*(1+'Property Summary'!$I$21)^(G$13-1))) -> 1280 | H31: =IF(OR($B8="",$B8=0),"",($K8*$C8*(1+'Property Summary'!$I$21)^(H$13-1))) -> 1280 | I31: =IF(OR($B8="",$B8=0),"",($K8*$C8*(1+'Property Summary'!$I$21)^(I$13-1))) -> 1280 | J31: =IF(OR($B8="",$B8=0),"",($K8*$C8*(1+'Property Summary'!$I$21)^(J$13-1))) -> 1280 | ... FZ31: =IF(OR($B8="",$B8=0),"",($K8*$C8*(1+'Property Summary'!$I$21)^(FZ$13-1))) -> 1808.6065
C32: =IF(OR($B9="",$B9=0),"",($K9*$C9*(1+'Property Summary'!$I$21)^(C$13-1))) -> 1080 | D32: =IF(OR($B9="",$B9=0),"",($K9*$C9*(1+'Property Summary'!$I$21)^(D$13-1))) -> 1080 | E32: =IF(OR($B9="",$B9=0),"",($K9*$C9*(1+'Property Summary'!$I$21)^(E$13-1))) -> 1080 | F32: =IF(OR($B9="",$B9=0),"",($K9*$C9*(1+'Property Summary'!$I$21)^(F$13-1))) -> 1080 | G32: =IF(OR($B9="",$B9=0),"",($K9*$C9*(1+'Property Summary'!$I$21)^(G$13-1))) -> 1080 | H32: =IF(OR($B9="",$B9=0),"",($K9*$C9*(1+'Property Summary'!$I$21)^(H$13-1))) -> 1080 | I32: =IF(OR($B9="",$B9=0),"",($K9*$C9*(1+'Property Summary'!$I$21)^(I$13-1))) -> 1080 | J32: =IF(OR($B9="",$B9=0),"",($K9*$C9*(1+'Property Summary'!$I$21)^(J$13-1))) -> 1080 | ... FZ32: =IF(OR($B9="",$B9=0),"",($K9*$C9*(1+'Property Summary'!$I$21)^(FZ$13-1))) -> 1526.0117
B34: Total | C34: =SUM(C28:C33) -> 8100 | D34: =SUM(D28:D33) -> 8100 | E34: =SUM(E28:E33) -> 8100 | F34: =SUM(F28:F33) -> 8100 | G34: =SUM(G28:G33) -> 8100 | H34: =SUM(H28:H33) -> 8100 | I34: =SUM(I28:I33) -> 8100 | J34: =SUM(J28:J33) -> 8100 | ... FZ34: =SUM(FZ28:FZ33) -> 11445.088
B36: Rollover/Lease Expiration Tracking
B37: Year | C37: =ROUNDUP(C38/12,0) -> 1 | D37: =ROUNDUP(D38/12,0) -> 1 | E37: =ROUNDUP(E38/12,0) -> 1 | F37: =ROUNDUP(F38/12,0) -> 1 | G37: =ROUNDUP(G38/12,0) -> 1 | H37: =ROUNDUP(H38/12,0) -> 1 | I37: =ROUNDUP(I38/12,0) -> 1 | J37: =ROUNDUP(J38/12,0) -> 1 | ... FZ37: =ROUNDUP(FZ38/12,0) -> 15
B38: Month | C38: 1 | D38: =C38+1 -> 2 | E38: =D38+1 -> 3 | F38: =E38+1 -> 4 | G38: =F38+1 -> 5 | H38: =G38+1 -> 6 | I38: =H38+1 -> 7 | J38: =I38+1 -> 8 | K38: =J38+1 -> 9 | ... FZ38: =FY38+1 -> 180
B39: Month Ending | C39: =EOMONTH(Analysis_Start,0) -> 43861 | D39: =EOMONTH(C15,1) -> 43890 | E39: =EOMONTH(D15,1) -> 43921 | F39: =EOMONTH(E15,1) -> 43951 | G39: =EOMONTH(F15,1) -> 43982 | H39: =EOMONTH(G15,1) -> 44012 | I39: =EOMONTH(H15,1) -> 44043 | J39: =EOMONTH(I15,1) -> 44074 | K39: =EOMONTH(J15,1) -> 44104 | ... FZ39: =EOMONTH(FY15,1) -> 49309
C40: =IF(OR($B5="",$B5=0),"",INT(C$38/$J5)=C$38/$J5) -> FALSE | D40: =IF(OR($B5="",$B5=0),"",INT(D$38/$J5)=D$38/$J5) -> FALSE | E40: =IF(OR($B5="",$B5=0),"",INT(E$38/$J5)=E$38/$J5) -> FALSE | F40: =IF(OR($B5="",$B5=0),"",INT(F$38/$J5)=F$38/$J5) -> FALSE | G40: =IF(OR($B5="",$B5=0),"",INT(G$38/$J5)=G$38/$J5) -> FALSE | H40: =IF(OR($B5="",$B5=0),"",INT(H$38/$J5)=H$38/$J5) -> FALSE | I40: =IF(OR($B5="",$B5=0),"",INT(I$38/$J5)=I$38/$J5) -> FALSE | J40: =IF(OR($B5="",$B5=0),"",INT(J$38/$J5)=J$38/$J5) -> FALSE | ... FZ40: =IF(OR($B5="",$B5=0),"",INT(FZ$38/$J5)=FZ$38/$J5) -> TRUE
C41: =IF(OR($B6="",$B6=0),"",INT(C$38/$J6)=C$38/$J6) -> FALSE | D41: =IF(OR($B6="",$B6=0),"",INT(D$38/$J6)=D$38/$J6) -> FALSE | E41: =IF(OR($B6="",$B6=0),"",INT(E$38/$J6)=E$38/$J6) -> FALSE | F41: =IF(OR($B6="",$B6=0),"",INT(F$38/$J6)=F$38/$J6) -> FALSE | G41: =IF(OR($B6="",$B6=0),"",INT(G$38/$J6)=G$38/$J6) -> FALSE | H41: =IF(OR($B6="",$B6=0),"",INT(H$38/$J6)=H$38/$J6) -> FALSE | I41: =IF(OR($B6="",$B6=0),"",INT(I$38/$J6)=I$38/$J6) -> FALSE | J41: =IF(OR($B6="",$B6=0),"",INT(J$38/$J6)=J$38/$J6) -> FALSE | ... FZ41: =IF(OR($B6="",$B6=0),"",INT(FZ$38/$J6)=FZ$38/$J6) -> TRUE
C42: =IF(OR($B7="",$B7=0),"",INT(C$38/$J7)=C$38/$J7) -> FALSE | D42: =IF(OR($B7="",$B7=0),"",INT(D$38/$J7)=D$38/$J7) -> FALSE | E42: =IF(OR($B7="",$B7=0),"",INT(E$38/$J7)=E$38/$J7) -> FALSE | F42: =IF(OR($B7="",$B7=0),"",INT(F$38/$J7)=F$38/$J7) -> FALSE | G42: =IF(OR($B7="",$B7=0),"",INT(G$38/$J7)=G$38/$J7) -> FALSE | H42: =IF(OR($B7="",$B7=0),"",INT(H$38/$J7)=H$38/$J7) -> FALSE | I42: =IF(OR($B7="",$B7=0),"",INT(I$38/$J7)=I$38/$J7) -> FALSE | J42: =IF(OR($B7="",$B7=0),"",INT(J$38/$J7)=J$38/$J7) -> FALSE | ... FZ42: =IF(OR($B7="",$B7=0),"",INT(FZ$38/$J7)=FZ$38/$J7) -> TRUE
C43: =IF(OR($B8="",$B8=0),"",INT(C$38/$J8)=C$38/$J8) -> FALSE | D43: =IF(OR($B8="",$B8=0),"",INT(D$38/$J8)=D$38/$J8) -> FALSE | E43: =IF(OR($B8="",$B8=0),"",INT(E$38/$J8)=E$38/$J8) -> FALSE | F43: =IF(OR($B8="",$B8=0),"",INT(F$38/$J8)=F$38/$J8) -> FALSE | G43: =IF(OR($B8="",$B8=0),"",INT(G$38/$J8)=G$38/$J8) -> FALSE | H43: =IF(OR($B8="",$B8=0),"",INT(H$38/$J8)=H$38/$J8) -> FALSE | I43: =IF(OR($B8="",$B8=0),"",INT(I$38/$J8)=I$38/$J8) -> FALSE | J43: =IF(OR($B8="",$B8=0),"",INT(J$38/$J8)=J$38/$J8) -> FALSE | ... FZ43: =IF(OR($B8="",$B8=0),"",INT(FZ$38/$J8)=FZ$38/$J8) -> TRUE
C44: =IF(OR($B9="",$B9=0),"",INT(C$38/$J9)=C$38/$J9) -> FALSE | D44: =IF(OR($B9="",$B9=0),"",INT(D$38/$J9)=D$38/$J9) -> FALSE | E44: =IF(OR($B9="",$B9=0),"",INT(E$38/$J9)=E$38/$J9) -> FALSE | F44: =IF(OR($B9="",$B9=0),"",INT(F$38/$J9)=F$38/$J9) -> FALSE | G44: =IF(OR($B9="",$B9=0),"",INT(G$38/$J9)=G$38/$J9) -> FALSE | H44: =IF(OR($B9="",$B9=0),"",INT(H$38/$J9)=H$38/$J9) -> FALSE | I44: =IF(OR($B9="",$B9=0),"",INT(I$38/$J9)=I$38/$J9) -> FALSE | J44: =IF(OR($B9="",$B9=0),"",INT(J$38/$J9)=J$38/$J9) -> FALSE | ... FZ44: =IF(OR($B9="",$B9=0),"",INT(FZ$38/$J9)=FZ$38/$J9) -> TRUE
B48: Free Rent
B49: Year | C49: =ROUNDUP(C50/12,0) -> 1 | D49: =ROUNDUP(D50/12,0) -> 1 | E49: =ROUNDUP(E50/12,0) -> 1 | F49: =ROUNDUP(F50/12,0) -> 1 | G49: =ROUNDUP(G50/12,0) -> 1 | H49: =ROUNDUP(H50/12,0) -> 1 | I49: =ROUNDUP(I50/12,0) -> 1 | J49: =ROUNDUP(J50/12,0) -> 1 | ... FZ49: =ROUNDUP(FZ50/12,0) -> 15
B50: Month | C50: 1 | D50: =C50+1 -> 2 | E50: =D50+1 -> 3 | F50: =E50+1 -> 4 | G50: =F50+1 -> 5 | H50: =G50+1 -> 6 | I50: =H50+1 -> 7 | J50: =I50+1 -> 8 | K50: =J50+1 -> 9 | ... FZ50: =FY50+1 -> 180
B51: Month Ending | C51: =EOMONTH(Analysis_Start,0) -> 43861 | D51: =EOMONTH(C15,1) -> 43890 | E51: =EOMONTH(D15,1) -> 43921 | F51: =EOMONTH(E15,1) -> 43951 | G51: =EOMONTH(F15,1) -> 43982 | H51: =EOMONTH(G15,1) -> 44012 | I51: =EOMONTH(H15,1) -> 44043 | J51: =EOMONTH(I15,1) -> 44074 | K51: =EOMONTH(J15,1) -> 44104 | ... FZ51: =EOMONTH(FY15,1) -> 49309
C52: =IF(OR($B5="",$B5=0),"",$P5*C16*B40) -> 0 | D52: =IF(OR($B5="",$B5=0),"",$P5*D16*C40) -> 0 | E52: =IF(OR($B5="",$B5=0),"",$P5*E16*D40) -> 0 | F52: =IF(OR($B5="",$B5=0),"",$P5*F16*E40) -> 0 | G52: =IF(OR($B5="",$B5=0),"",$P5*G16*F40) -> 0 | H52: =IF(OR($B5="",$B5=0),"",$P5*H16*G40) -> 0 | I52: =IF(OR($B5="",$B5=0),"",$P5*I16*H40) -> 0 | J52: =IF(OR($B5="",$B5=0),"",$P5*J16*I40) -> 0 | ... FZ52: =IF(OR($B5="",$B5=0),"",$P5*FZ16*FY40) -> 0
C53: =IF(OR($B6="",$B6=0),"",$P6*C17*B41) -> 0 | D53: =IF(OR($B6="",$B6=0),"",$P6*D17*C41) -> 0 | E53: =IF(OR($B6="",$B6=0),"",$P6*E17*D41) -> 0 | F53: =IF(OR($B6="",$B6=0),"",$P6*F17*E41) -> 0 | G53: =IF(OR($B6="",$B6=0),"",$P6*G17*F41) -> 0 | H53: =IF(OR($B6="",$B6=0),"",$P6*H17*G41) -> 0 | I53: =IF(OR($B6="",$B6=0),"",$P6*I17*H41) -> 0 | J53: =IF(OR($B6="",$B6=0),"",$P6*J17*I41) -> 0 | ... FZ53: =IF(OR($B6="",$B6=0),"",$P6*FZ17*FY41) -> 0
C54: =IF(OR($B7="",$B7=0),"",$P7*C18*B42) -> 0 | D54: =IF(OR($B7="",$B7=0),"",$P7*D18*C42) -> 0 | E54: =IF(OR($B7="",$B7=0),"",$P7*E18*D42) -> 0 | F54: =IF(OR($B7="",$B7=0),"",$P7*F18*E42) -> 0 | G54: =IF(OR($B7="",$B7=0),"",$P7*G18*F42) -> 0 | H54: =IF(OR($B7="",$B7=0),"",$P7*H18*G42) -> 0 | I54: =IF(OR($B7="",$B7=0),"",$P7*I18*H42) -> 0 | J54: =IF(OR($B7="",$B7=0),"",$P7*J18*I42) -> 0 | ... FZ54: =IF(OR($B7="",$B7=0),"",$P7*FZ18*FY42) -> 0
C55: =IF(OR($B8="",$B8=0),"",$P8*C19*B43) -> 0 | D55: =IF(OR($B8="",$B8=0),"",$P8*D19*C43) -> 0 | E55: =IF(OR($B8="",$B8=0),"",$P8*E19*D43) -> 0 | F55: =IF(OR($B8="",$B8=0),"",$P8*F19*E43) -> 0 | G55: =IF(OR($B8="",$B8=0),"",$P8*G19*F43) -> 0 | H55: =IF(OR($B8="",$B8=0),"",$P8*H19*G43) -> 0 | I55: =IF(OR($B8="",$B8=0),"",$P8*I19*H43) -> 0 | J55: =IF(OR($B8="",$B8=0),"",$P8*J19*I43) -> 0 | ... FZ55: =IF(OR($B8="",$B8=0),"",$P8*FZ19*FY43) -> 0
C56: =IF(OR($B9="",$B9=0),"",$P9*C20*B44) -> 0 | D56: =IF(OR($B9="",$B9=0),"",$P9*D20*C44) -> 0 | E56: =IF(OR($B9="",$B9=0),"",$P9*E20*D44) -> 0 | F56: =IF(OR($B9="",$B9=0),"",$P9*F20*E44) -> 0 | G56: =IF(OR($B9="",$B9=0),"",$P9*G20*F44) -> 0 | H56: =IF(OR($B9="",$B9=0),"",$P9*H20*G44) -> 0 | I56: =IF(OR($B9="",$B9=0),"",$P9*I20*H44) -> 0 | J56: =IF(OR($B9="",$B9=0),"",$P9*J20*I44) -> 0 | ... FZ56: =IF(OR($B9="",$B9=0),"",$P9*FZ20*FY44) -> 0
B58: Total | C58: =SUM(C52:C57) -> 0 | D58: =SUM(D52:D57) -> 0 | E58: =SUM(E52:E57) -> 0 | F58: =SUM(F52:F57) -> 0 | G58: =SUM(G52:G57) -> 0 | H58: =SUM(H52:H57) -> 0 | I58: =SUM(I52:I57) -> 0 | J58: =SUM(J52:J57) -> 0 | ... FZ58: =SUM(FZ52:FZ57) -> 0
B60: Vacancy
B61: Year | C61: =ROUNDUP(C62/12,0) -> 1 | D61: =ROUNDUP(D62/12,0) -> 1 | E61: =ROUNDUP(E62/12,0) -> 1 | F61: =ROUNDUP(F62/12,0) -> 1 | G61: =ROUNDUP(G62/12,0) -> 1 | H61: =ROUNDUP(H62/12,0) -> 1 | I61: =ROUNDUP(I62/12,0) -> 1 | J61: =ROUNDUP(J62/12,0) -> 1 | ... FZ61: =ROUNDUP(FZ62/12,0) -> 15
B62: Month | C62: 1 | D62: =C62+1 -> 2 | E62: =D62+1 -> 3 | F62: =E62+1 -> 4 | G62: =F62+1 -> 5 | H62: =G62+1 -> 6 | I62: =H62+1 -> 7 | J62: =I62+1 -> 8 | K62: =J62+1 -> 9 | ... FZ62: =FY62+1 -> 180
B63: Month Ending | C63: =EOMONTH(Analysis_Start,0) -> 43861 | D63: =EOMONTH(C15,1) -> 43890 | E63: =EOMONTH(D15,1) -> 43921 | F63: =EOMONTH(E15,1) -> 43951 | G63: =EOMONTH(F15,1) -> 43982 | H63: =EOMONTH(G15,1) -> 44012 | I63: =EOMONTH(H15,1) -> 44043 | J63: =EOMONTH(I15,1) -> 44074 | K63: =EOMONTH(J15,1) -> 44104 | ... FZ63: =EOMONTH(FY15,1) -> 49309
C64: =IF(OR($B5="",$B5=0),"",($Q5/30)*C16*B40) -> 0 | D64: =IF(OR($B5="",$B5=0),"",($Q5/30)*D16*C40) -> 0 | E64: =IF(OR($B5="",$B5=0),"",($Q5/30)*E16*D40) -> 0 | F64: =IF(OR($B5="",$B5=0),"",($Q5/30)*F16*E40) -> 0 | G64: =IF(OR($B5="",$B5=0),"",($Q5/30)*G16*F40) -> 0 | H64: =IF(OR($B5="",$B5=0),"",($Q5/30)*H16*G40) -> 0 | I64: =IF(OR($B5="",$B5=0),"",($Q5/30)*I16*H40) -> 0 | J64: =IF(OR($B5="",$B5=0),"",($Q5/30)*J16*I40) -> 0 | ... FZ64: =IF(OR($B5="",$B5=0),"",($Q5/30)*FZ16*FY40) -> 0
C65: =IF(OR($B6="",$B6=0),"",($Q6/30)*C17*B41) -> 0 | D65: =IF(OR($B6="",$B6=0),"",($Q6/30)*D17*C41) -> 0 | E65: =IF(OR($B6="",$B6=0),"",($Q6/30)*E17*D41) -> 0 | F65: =IF(OR($B6="",$B6=0),"",($Q6/30)*F17*E41) -> 0 | G65: =IF(OR($B6="",$B6=0),"",($Q6/30)*G17*F41) -> 0 | H65: =IF(OR($B6="",$B6=0),"",($Q6/30)*H17*G41) -> 0 | I65: =IF(OR($B6="",$B6=0),"",($Q6/30)*I17*H41) -> 0 | J65: =IF(OR($B6="",$B6=0),"",($Q6/30)*J17*I41) -> 0 | ... FZ65: =IF(OR($B6="",$B6=0),"",($Q6/30)*FZ17*FY41) -> 0
C66: =IF(OR($B7="",$B7=0),"",($Q7/30)*C18*B42) -> 0 | D66: =IF(OR($B7="",$B7=0),"",($Q7/30)*D18*C42) -> 0 | E66: =IF(OR($B7="",$B7=0),"",($Q7/30)*E18*D42) -> 0 | F66: =IF(OR($B7="",$B7=0),"",($Q7/30)*F18*E42) -> 0 | G66: =IF(OR($B7="",$B7=0),"",($Q7/30)*G18*F42) -> 0 | H66: =IF(OR($B7="",$B7=0),"",($Q7/30)*H18*G42) -> 0 | I66: =IF(OR($B7="",$B7=0),"",($Q7/30)*I18*H42) -> 0 | J66: =IF(OR($B7="",$B7=0),"",($Q7/30)*J18*I42) -> 0 | ... FZ66: =IF(OR($B7="",$B7=0),"",($Q7/30)*FZ18*FY42) -> 0
C67: =IF(OR($B8="",$B8=0),"",($Q8/30)*C19*B43) -> 0 | D67: =IF(OR($B8="",$B8=0),"",($Q8/30)*D19*C43) -> 0 | E67: =IF(OR($B8="",$B8=0),"",($Q8/30)*E19*D43) -> 0 | F67: =IF(OR($B8="",$B8=0),"",($Q8/30)*F19*E43) -> 0 | G67: =IF(OR($B8="",$B8=0),"",($Q8/30)*G19*F43) -> 0 | H67: =IF(OR($B8="",$B8=0),"",($Q8/30)*H19*G43) -> 0 | I67: =IF(OR($B8="",$B8=0),"",($Q8/30)*I19*H43) -> 0 | J67: =IF(OR($B8="",$B8=0),"",($Q8/30)*J19*I43) -> 0 | ... FZ67: =IF(OR($B8="",$B8=0),"",($Q8/30)*FZ19*FY43) -> 0
C68: =IF(OR($B9="",$B9=0),"",($Q9/30)*C20*B44) -> 0 | D68: =IF(OR($B9="",$B9=0),"",($Q9/30)*D20*C44) -> 0 | E68: =IF(OR($B9="",$B9=0),"",($Q9/30)*E20*D44) -> 0 | F68: =IF(OR($B9="",$B9=0),"",($Q9/30)*F20*E44) -> 0 | G68: =IF(OR($B9="",$B9=0),"",($Q9/30)*G20*F44) -> 0 | H68: =IF(OR($B9="",$B9=0),"",($Q9/30)*H20*G44) -> 0 | I68: =IF(OR($B9="",$B9=0),"",($Q9/30)*I20*H44) -> 0 | J68: =IF(OR($B9="",$B9=0),"",($Q9/30)*J20*I44) -> 0 | ... FZ68: =IF(OR($B9="",$B9=0),"",($Q9/30)*FZ20*FY44) -> 0
B70: Total | C70: =MAX(C71,C72) -> 36290.8 | D70: =MAX(D71,D72) -> 36290.8 | E70: =MAX(E71,E72) -> 36290.8 | F70: =MAX(F71,F72) -> 36290.8 | G70: =MAX(G71,G72) -> 36290.8 | H70: =MAX(H71,H72) -> 36290.8 | I70: =MAX(I71,I72) -> 36290.8 | J70: =MAX(J71,J72) -> 36290.8 | ... FZ70: =MAX(FZ71,FZ72) -> 46693.396
B71: General Vacancy | C71: ='Property Summary'!$F$15*C22 -> 36290.8 | D71: ='Property Summary'!$F$15*D22 -> 36290.8 | E71: ='Property Summary'!$F$15*E22 -> 36290.8 | F71: ='Property Summary'!$F$15*F22 -> 36290.8 | G71: ='Property Summary'!$F$15*G22 -> 36290.8 | H71: ='Property Summary'!$F$15*H22 -> 36290.8 | I71: ='Property Summary'!$F$15*I22 -> 36290.8 | J71: ='Property Summary'!$F$15*J22 -> 36290.8 | ... FZ71: ='Property Summary'!$F$15*FZ22 -> 46693.396
B72: Property Vacancy | C72: =SUM(C64:C69) -> 0 | D72: =SUM(D64:D69) -> 0 | E72: =SUM(E64:E69) -> 0 | F72: =SUM(F64:F69) -> 0 | G72: =SUM(G64:G69) -> 0 | H72: =SUM(H64:H69) -> 0 | I72: =SUM(I64:I69) -> 0 | J72: =SUM(J64:J69) -> 0 | ... FZ72: =SUM(FZ64:FZ69) -> 0
B74: Releasing Costs
B75: Year | C75: =ROUNDUP(C76/12,0) -> 1 | D75: =ROUNDUP(D76/12,0) -> 1 | E75: =ROUNDUP(E76/12,0) -> 1 | F75: =ROUNDUP(F76/12,0) -> 1 | G75: =ROUNDUP(G76/12,0) -> 1 | H75: =ROUNDUP(H76/12,0) -> 1 | I75: =ROUNDUP(I76/12,0) -> 1 | J75: =ROUNDUP(J76/12,0) -> 1 | ... FZ75: =ROUNDUP(FZ76/12,0) -> 15
B76: Month | C76: 1 | D76: =C76+1 -> 2 | E76: =D76+1 -> 3 | F76: =E76+1 -> 4 | G76: =F76+1 -> 5 | H76: =G76+1 -> 6 | I76: =H76+1 -> 7 | J76: =I76+1 -> 8 | K76: =J76+1 -> 9 | ... FZ76: =FY76+1 -> 180
B77: Month Ending | C77: =EOMONTH(Analysis_Start,0) -> 43861 | D77: =EOMONTH(C15,1) -> 43890 | E77: =EOMONTH(D15,1) -> 43921 | F77: =EOMONTH(E15,1) -> 43951 | G77: =EOMONTH(F15,1) -> 43982 | H77: =EOMONTH(G15,1) -> 44012 | I77: =EOMONTH(H15,1) -> 44043 | J77: =EOMONTH(I15,1) -> 44074 | K77: =EOMONTH(J15,1) -> 44104 | ... FZ77: =EOMONTH(FY15,1) -> 49309
C78: =IF(OR($B5="",$B5=0),"",(B40*($R5*(1+'Property Summary'!$I$22)^(C$75-1)))*$C5) -> 0 | D78: =IF(OR($B5="",$B5=0),"",(C40*($R5*(1+'Property Summary'!$I$22)^(D$75-1)))*$C5) -> 0 | E78: =IF(OR($B5="",$B5=0),"",(D40*($R5*(1+'Property Summary'!$I$22)^(E$75-1)))*$C5) -> 0 | F78: =IF(OR($B5="",$B5=0),"",(E40*($R5*(1+'Property Summary'!$I$22)^(F$75-1)))*$C5) -> 0 | G78: =IF(OR($B5="",$B5=0),"",(F40*($R5*(1+'Property Summary'!$I$22)^(G$75-1)))*$C5) -> 0 | H78: =IF(OR($B5="",$B5=0),"",(G40*($R5*(1+'Property Summary'!$I$22)^(H$75-1)))*$C5) -> 0 | I78: =IF(OR($B5="",$B5=0),"",(H40*($R5*(1+'Property Summary'!$I$22)^(I$75-1)))*$C5) -> 0 | J78: =IF(OR($B5="",$B5=0),"",(I40*($R5*(1+'Property Summary'!$I$22)^(J$75-1)))*$C5) -> 0 | ... FZ78: =IF(OR($B5="",$B5=0),"",(FY40*($R5*(1+'Property Summary'!$I$22)^(FZ$75-1)))*$C5) -> 0
C79: =IF(OR($B6="",$B6=0),"",(B41*($R6*(1+'Property Summary'!$I$22)^(C$75-1)))*$C6) -> 0 | D79: =IF(OR($B6="",$B6=0),"",(C41*($R6*(1+'Property Summary'!$I$22)^(D$75-1)))*$C6) -> 0 | E79: =IF(OR($B6="",$B6=0),"",(D41*($R6*(1+'Property Summary'!$I$22)^(E$75-1)))*$C6) -> 0 | F79: =IF(OR($B6="",$B6=0),"",(E41*($R6*(1+'Property Summary'!$I$22)^(F$75-1)))*$C6) -> 0 | G79: =IF(OR($B6="",$B6=0),"",(F41*($R6*(1+'Property Summary'!$I$22)^(G$75-1)))*$C6) -> 0 | H79: =IF(OR($B6="",$B6=0),"",(G41*($R6*(1+'Property Summary'!$I$22)^(H$75-1)))*$C6) -> 0 | I79: =IF(OR($B6="",$B6=0),"",(H41*($R6*(1+'Property Summary'!$I$22)^(I$75-1)))*$C6) -> 0 | J79: =IF(OR($B6="",$B6=0),"",(I41*($R6*(1+'Property Summary'!$I$22)^(J$75-1)))*$C6) -> 0 | ... FZ79: =IF(OR($B6="",$B6=0),"",(FY41*($R6*(1+'Property Summary'!$I$22)^(FZ$75-1)))*$C6) -> 0
C80: =IF(OR($B7="",$B7=0),"",(B42*($R7*(1+'Property Summary'!$I$22)^(C$75-1)))*$C7) -> 0 | D80: =IF(OR($B7="",$B7=0),"",(C42*($R7*(1+'Property Summary'!$I$22)^(D$75-1)))*$C7) -> 0 | E80: =IF(OR($B7="",$B7=0),"",(D42*($R7*(1+'Property Summary'!$I$22)^(E$75-1)))*$C7) -> 0 | F80: =IF(OR($B7="",$B7=0),"",(E42*($R7*(1+'Property Summary'!$I$22)^(F$75-1)))*$C7) -> 0 | G80: =IF(OR($B7="",$B7=0),"",(F42*($R7*(1+'Property Summary'!$I$22)^(G$75-1)))*$C7) -> 0 | H80: =IF(OR($B7="",$B7=0),"",(G42*($R7*(1+'Property Summary'!$I$22)^(H$75-1)))*$C7) -> 0 | I80: =IF(OR($B7="",$B7=0),"",(H42*($R7*(1+'Property Summary'!$I$22)^(I$75-1)))*$C7) -> 0 | J80: =IF(OR($B7="",$B7=0),"",(I42*($R7*(1+'Property Summary'!$I$22)^(J$75-1)))*$C7) -> 0 | ... FZ80: =IF(OR($B7="",$B7=0),"",(FY42*($R7*(1+'Property Summary'!$I$22)^(FZ$75-1)))*$C7) -> 0
C81: =IF(OR($B8="",$B8=0),"",(B43*($R8*(1+'Property Summary'!$I$22)^(C$75-1)))*$C8) -> 0 | D81: =IF(OR($B8="",$B8=0),"",(C43*($R8*(1+'Property Summary'!$I$22)^(D$75-1)))*$C8) -> 0 | E81: =IF(OR($B8="",$B8=0),"",(D43*($R8*(1+'Property Summary'!$I$22)^(E$75-1)))*$C8) -> 0 | F81: =IF(OR($B8="",$B8=0),"",(E43*($R8*(1+'Property Summary'!$I$22)^(F$75-1)))*$C8) -> 0 | G81: =IF(OR($B8="",$B8=0),"",(F43*($R8*(1+'Property Summary'!$I$22)^(G$75-1)))*$C8) -> 0 | H81: =IF(OR($B8="",$B8=0),"",(G43*($R8*(1+'Property Summary'!$I$22)^(H$75-1)))*$C8) -> 0 | I81: =IF(OR($B8="",$B8=0),"",(H43*($R8*(1+'Property Summary'!$I$22)^(I$75-1)))*$C8) -> 0 | J81: =IF(OR($B8="",$B8=0),"",(I43*($R8*(1+'Property Summary'!$I$22)^(J$75-1)))*$C8) -> 0 | ... FZ81: =IF(OR($B8="",$B8=0),"",(FY43*($R8*(1+'Property Summary'!$I$22)^(FZ$75-1)))*$C8) -> 0
C82: =IF(OR($B9="",$B9=0),"",(B44*($R9*(1+'Property Summary'!$I$22)^(C$75-1)))*$C9) -> 0 | D82: =IF(OR($B9="",$B9=0),"",(C44*($R9*(1+'Property Summary'!$I$22)^(D$75-1)))*$C9) -> 0 | E82: =IF(OR($B9="",$B9=0),"",(D44*($R9*(1+'Property Summary'!$I$22)^(E$75-1)))*$C9) -> 0 | F82: =IF(OR($B9="",$B9=0),"",(E44*($R9*(1+'Property Summary'!$I$22)^(F$75-1)))*$C9) -> 0 | G82: =IF(OR($B9="",$B9=0),"",(F44*($R9*(1+'Property Summary'!$I$22)^(G$75-1)))*$C9) -> 0 | H82: =IF(OR($B9="",$B9=0),"",(G44*($R9*(1+'Property Summary'!$I$22)^(H$75-1)))*$C9) -> 0 | I82: =IF(OR($B9="",$B9=0),"",(H44*($R9*(1+'Property Summary'!$I$22)^(I$75-1)))*$C9) -> 0 | J82: =IF(OR($B9="",$B9=0),"",(I44*($R9*(1+'Property Summary'!$I$22)^(J$75-1)))*$C9) -> 0 | ... FZ82: =IF(OR($B9="",$B9=0),"",(FY44*($R9*(1+'Property Summary'!$I$22)^(FZ$75-1)))*$C9) -> 0
B84: Total | C84: =SUM(C78:C83) -> 0 | D84: =SUM(D78:D83) -> 0 | E84: =SUM(E78:E83) -> 0 | F84: =SUM(F78:F83) -> 0 | G84: =SUM(G78:G83) -> 0 | H84: =SUM(H78:H83) -> 0 | I84: =SUM(I78:I83) -> 0 | J84: =SUM(J78:J83) -> 0 | ... FZ84: =SUM(FZ78:FZ83) -> 0

Sheet Property Assumptions
B2: Property Assumptions
C3: Property Assumptions | G3: Property Valuation | L3: Financing Assumptions
B4: # | C4: Property Name | D4: City, State/Region | E4: Net Rentable Area (NRA) | F4: Occupancy % | G4: Purchase Price | H4: Cap Rate | I4: PSF | J4: Equity Required | K4: Acquisition Cost % | L4: Interest Rate | M4: Amortization Payment | N4: I/O Payment | O4: Initial Loan Balance | P4: Years I/O | Q4: Amortization Period | R4: Term | S4: LTV | T4: Unlevered All-In Basis | U4: Upfront CapEx | V4: Lender Fees %
B5: 1 | C5: =Property_Name -> XYZ Condos | D5: ='Property Summary'!$C$4 -> Grand Cayman, CI | E5: =TEXT('Property Summary'!$I$27,"#,##0")&" "&'Property Summary'!I26 -> 62,520 SQFT | F5: ='Property Summary'!$C$5 -> 0.89 | G5: =Purchase_Price -> 35382269 | H5: ='Property Summary'!$F$7 -> 0.065 | I5: ='Property Summary'!C19/'Property Summary'!I27 -> 676.9219 | J5: =IF(B5="","",T5-O5+(O5*V5)) -> 19658792 | K5: ='Property Summary'!$F$5 -> 0.01 | L5: ='Property Summary'!$F$26 -> 0.0725 | M5: =IF(B5="","",-PMT((L5/12),(Q5-P5)*12,O5)*12) -> 1331881 | N5: =IF(B5="","",O5*L5) -> 1179575 | O5: =Debt -> 16270000 | P5: ='Property Summary'!F27 -> 0 | Q5: ='Property Summary'!F28 -> 30 | R5: ='Property Summary'!F29 -> 10 | S5: ='Property Summary'!F20 -> 0.45983484 | T5: =IF(B5="","",G5+(G5*K5)+U5) -> 35766092 | U5: ='Property Summary'!$F$4 -> 30000 | V5: ='Property Summary'!$F$30 -> 0.01
